Workbook

Sheet All Life Carriers Profile
A1: Service-Carrier ID | B1: Paycode | C1: Full Name | D1: Active? | E1: Service Main | F1: Level | G1: Rating | H1: Broker | I1: Short Carrier Name | J1: Carrier Initial | K1: Logo | L1: Main Address | M1: City | N1: State | O1: Zip | P1: Main Phone | Q1: Agent Support Phone | R1: Public URL | S1: Agent URL | T1: Email Commission | U1: Email New Business | V1: Admin Cutoff | W1: Admin Release Date | X1: Admin Min CK | Y1: Admin Min EFT | Z1: Admin Commission Policy | AA1: Admin Chargeback Schedule | AB1: Admin Advance Cap | AC1: Admin Comm Contact | AD1: Admin Other Notes
A2: L-AAI-EZT | B2: Diamond, 95, 90, 85, 80, 75, 70, 65, 60, 55, 50, 45, 40 | C2: American Income Life EZ Term | D2: Yes | E2: Life Insurance | F2: Hide | G2: 0 | H2: Brokers Alliance | I2: Am Income - EZ Term | J2: AAI-EZT | L2: 1201 Wooded Acres Drive | M2: Wasco | N2: TX | O2: 76710 | P2: 800-433-3405 | R2: https://www.ailife.com/ | S2: https://impactaws.ailife.com/main | V2: Daily | W2: Daily | X2: 50 | Y2: 10 | Z2: N/A | AA2: Unearned;Death Claim 1-24 mos 100% | AB2: 2,000.00 max per case | AC2: 800-736-7311
A3: L-AAI-EZUL | B3: Diamond, 95, 90, 85, 80, 75, 70, 65, 60, 55, 50, 45 | C3: American Income Life EZ UL | D3: Yes | E3: Life Insurance | F3: Hide | G3: 0 | H3: Brokers Alliance | I3: Am Income - EZ UL | J3: AAI-EZUL | L3: 1201 Wooded Acres Drive | M3: Wasco | N3: TX | O3: 76710 | P3: 800-433-3405 | R3: https://www.ailife.com/ | S3: https://impactaws.ailife.com/main | V3: Daily | W3: Daily | X3: 50 | Y3: 10 | Z3: N/A | AA3: Unearned;Death Claim 1-24 mos 100% | AB3: 2,000.00 max per case | AC3: 800-736-7311
A4: L-AAI-FE | B4: Diamond, 115, 110, 105, 100, 95, 90, 85, 80, 75, 70, 65, 60, 55, 50, 45 | C4: American Income Life Final Expense | D4: Yes | E4: Life Insurance | F4: Hide | G4: 0 | H4: Brokers Alliance | I4: Am Income - FE | J4: AAI-FE | L4: 1200 Wooded Acres Drive | M4: Wasco | N4: TX | O4: 76710 | P4: 800-433-3405 | R4: https://www.ailife.com/ | S4: https://impactaws.ailife.com/main | V4: Daily | W4: Daily | X4: 50 | Y4: 10 | Z4: N/A | AA4: Unearned;Death Claim 1-24 mos 100% | AB4: 2,000.00 max per case | AC4: 800-736-7311
A5: L-AAI-HP | B5: Diamond, 110, 105, 100, 95, 90, 85, 80, 75, 70, 69, 65, 60, 55, 50, 45, 40, 0 | C5: American Income Life Home Protector | D5: Yes | E5: Life Insurance | F5: Hide | G5: 0 | H5: Brokers Alliance | I5: Am Income - Home Protector | J5: AAI-HP | L5: 1201 Wooded Acres Drive | M5: Wasco | N5: TX | O5: 76710 | P5: 800-433-3405 | R5: https://www.ailife.com/ | S5: https://impactaws.ailife.com/main | V5: Daily | W5: Daily | X5: 50 | Y5: 10 | Z5: N/A | AA5: Unearned;Death Claim 1-24 mos 100% | AB5: 2,000.00 max per case | AC5: 800-736-7311
A6: L-AAI-SP | B6: Diamond, 125, 120, 115, 110, 105, 100, 95, 90, 85, 80, 75, 70, 65, 60, 55 | C6: American Income Life Survivor Protector | D6: Yes | E6: Life Insurance | F6: Hide | G6: 0 | H6: Brokers Alliance | I6: Am Income - Survivor Protector | J6: AAI-SP | L6: 1201 Wooded Acres Drive | M6: Wasco | N6: TX | O6: 76710 | P6: 800-433-3405 | R6: https://www.ailife.com/ | S6: https://impactaws.ailife.com/main | V6: Daily | W6: Daily | X6: 50 | Y6: 10 | Z6: N/A | AA6: Unearned;Death Claim 1-24 mos 100% | AB6: 2,000.00 max per case | AC6: 800-736-7311
A7: L-ALLZ | B7: Diamond, 80, 75, 70, 65, 60, 55, 50, 45, 40, 35, 30, 25, 20, 15, 10, 5 | C7: Allianz Life Insurance Company of North America | D7: Yes | E7: Life Insurance | F7: Top | G7: 0 | H7: Brokers Alliance | I7: Allianz | J7: ALLZ | L7: PO BOX 59060 | M7: Minneapolis | N7: MN | O7: 55459 | P7: 800-950-5872 | R7: https://www.allianzlife.com/ | S7: https://www.allianzlife.com/for-financial-professionals | V7: Daily | W7: Paper ck mailed out the 15th & 30th and EFT release daily (48-72hrs) | X7: 50 | Y7: No min | Z7: No | AA7: Surrendered 1-6 mos: 100%, 7-12 mos: 50% includes death of the owner | AB7: $12,000 per policy rolling $50,000 per agent | AC7: 800-950-7372 | AD7: Only Allianz Life Pro+ (old products included for reference the past)
A8: L-ANICO | C8: American National | D8: No | E8: Life Insurance | F8: Hide | G8: 0 | H8: Brokers Alliance | I8: American National | J8: ANICO | L8: PO Box 3297 | M8: Springfield | N8: MO | O8: 65808 | P8: 888-501-4043 | Q8: 800-615-7372 | R8: https://www.americannational.com/wps/portal/ | S8: https://img.anicoweb.com/wps/portal/ | V8: Friday | W8: Checks mailed Tuesday or Weds/EFT in acct Wed | X8: 100 | Y8: No min | Z8: Non Commissionable Term: ~$62.50 | AA8: 1-6 mos 100%; 7 > varies | AB8: Depends on the agent. Not on BA. $2,500 per cycle | AC8: 888-801-8845 | AD8: **As of 12/1/2022, American National will no longer accept applications for Signature Term Life Insurance.
A9: L-ANINY | C9: American National - NY | D9: Yes | E9: Life Insurance | F9: Hide | G9: 0 | H9: Brokers Alliance | I9: American National-NY | J9: ANINY | L9: PO Box 4408 | M9: Springfield | N9: MO | O9: 65808 | P9: 866-490-3163 | Q9: 800-615-7372 | R9: https://www.americannational.com/wps/portal/ | S9: https://img.anicoweb.com/wps/portal/ | V9: Friday | W9: Checks mailed Tuesday or Weds/EFT in acct Wed | X9: 100 | Y9: No min | Z9: Non Commissionable Term: ~$62.50 | AA9: 1-6 mos 100%; 7 > varies | AB9: Depends on the agent. Not on BA. $2,500 per cycle | AC9: 888-801-8845
A10: L-ASSUR | B10: Diamond, Level 18, Level 19, Level 20, Level 22, Level 24, Level 26, Level 28, Level 30, Level 32, Level 34, Level 36, Level 38, Level 50 | C10: Assurity Life Insurance Company | D10: Yes | E10: Life Insurance | F10: Top | G10: 0 | H10: Brokers Alliance | I10: Assurity | J10: ASSUR | L10: 2000 Q Street | M10: Lincoln | N10: NE | O10: 68503 | P10: 402-476-6500 | Q10: 800-869-0355 x 4279 | R10: https://www.assurity.com/ | S10: https://www.assurity.com/agent-center | V10: Friday; Bi-Monthly | W10: Manday | X10: 250 | Y10: No min | Z10: Term/CI Non Commissionable $70 | AA10: <9--3mos CB | AB10: $1,500 per policy; max per agent $25k | AC10: 800-869-0390
A11: L-AXA | B11: Diamond, Sch 90, Sch 85, Sch 80, Sch 75, Sch 70, Sch 65, Sch 60, Sch 55, Sch 50, 50, 45, 40 | C11: AXA | D11: Yes | F11: Hide
A12: L-AMERI | C12: Ameritas | D12: No | E12: Life Insurance | F12: Hide | G12: 0 | H12: Brokers Alliance | I12: Ameritas | J12: AMERI | L12: 5900 O Street, P.O. Box 81889 | M12: Lincoln | N12: NE | O12: 68501 | P12: 800-745-1112 | R12: https://www.ameritas.com/sign-in/#tab|2 | S12: https://service.ameritas.com/service/login.asp | V12: Thursday | W12: Friday | X12: N/A | Y12: No min | Z12: Varies--Commissionable | AA12: Unearned | AB12: $5,000 per policy
A13: L-BALT-FE | B13: Diamond, 115, 110, 105, 100, 95, 90, 85, 80, 75, 70, 65, 60, 55, 50, 40 | C13: Baltimore Life - Final Expense | D13: Yes
A14: L-BALT-WL | B14: Diamond, SPWL14, SPWL13.5, SPWL13, SPWL12.5, SPWL12, SPWL11.5, SPWL11, SPWL10.5, SPWL10, SPWL9.5, SPWL9, SPWL8.5, SPWL8, SPWL7.5, SPWL7, SPWL6.5, SPWL6 | C14: Baltimore Life - SPWL | D14: Yes
A15: L-BALT-T | B15: Diamond, 60, 55, 50, 45, 40 | C15: Baltimore Life - Term | D15: Yes
A16: L-BANNR | B16: Diamond, BEGA-1, AB90, AB85, AB80, AB75, AB70, AB65, AB60, BMGA85, BMGA80, BMGA75, BMGA70, BMGA65, BMGA60, BMGA90, BEGA90, BEGA85, BEGA80, BEGA75, BEGA70, BDGA90, BDGA85, BDGA80, BDGA75, BDGA70, BDGA65, BDGA60 | C16: Banner Life Insurance Company | D16: Yes | E16: Life Insurance | F16: Mid | G16: 0 | H16: Brokers Alliance | I16: Banner (Legal Life Ins Comp.) | J16: BANNR | L16: 3275 Bennett Creek Avenue | M16: Frederick | N16: MD | O16: 21704 | P16: 301-810-4440 | Q16: 301-279-4800 | R16: https://www.lgamerica.com | S16: https://www.lgamerica.com/advisor | V16: D/W/M | W16: Checks mailed 1st, 11th and 21st/ ETfs Daily | X16: 50 | Y16: 50 | Z16: The policy fee for OPTerm 10, 15, 20, 25, and 30 is non-commissionable. | AA16: Unearned | AB16: $2,500 per policy | AC16: 800-638-8428
A17: L-BRIGT | B17: Diamond, Max Base | C17: Brighthouse Financial | D17: Yes | E17: Life Insurance | F17: Hide | G17: 0 | H17: Brokers Alliance | I17: Brighthouse (FIRNA) | J17: BRIGT | L17: 11225 N Community House Road | M17: Charlotte | N17: NY | O17: 28277 | P17: 800-882-1292 | Q17: 855-861-5300 | R17: https://www.brighthousefinancial.com/products/life-insurance/ | S17: https://www.brighthousefinancialpro.com/ | V17: Friday | W17: Wednesday | X17: N/A | Y17: No min | Z17: N/A | AA17: Unearned | AB17: No Advancement | AC17: 877-638-0411
A18: L-CORE-AGLA | B18: Diamond, 11, 10, 9, 8, 7, 6, 5, 4, 3, 2, 1 | C18: Corebridge (AGLA) | D18: Yes | E18: Life Insurance | F18: Mid | G18: 0 | H18: Brokers Alliance | I18: AGLA | J18: AGLA | L18: P.O. Box 25967 | M18: Shawnee Mission | N18: KS | O18: 66225 | P18: 800-225-5244 | R18: https://www.americangeneraltermlife.com/ | S18: https://www-1.aig.com/gpplogin | V18: Friday | W18: Tuesday | X18: 50 | Y18: 50 | Z18: Over $250K varies - $65 | AA18: 100% Month 1-6 50% Month 7-12 CB to Agent BA 40% bonus will be CB to us | AB18: $5,000 per policy | AC18: 800-255-2702
A19: L-CORE | B19: Diamond, A, B, C, D, E, F, G, H, I, J, M, N | C19: Corebridge (American General) | D19: Yes | E19: Life Insurance | F19: Top | G19: 0 | H19: Brokers Alliance | I19: Corebridge | J19: CORE | L19: P.O. Box 25967 | M19: Shawnee Mission | N19: KS | O19: 66225 | P19: 800-225-5244 | R19: https://www.americangeneraltermlife.com/ | S19: https://www-1.aig.com/gpplogin | V19: Saturday | W19: EFT deposited EVERY Tuesday/ Checks mailed every other Wed. | X19: 50 | Y19: 50 | Z19: $50.00 / Not commissionable | AA19: 1-6 Months 100% 7-12 months 50% | AB19: $5,000 per policy | AC19: 800-247-8837
A20: L-CORENY | B20: Diamond, Producer | C20: Corebridge NY | D20: Yes | E20: Life Insurance | F20: Hide | G20: 0 | H20: Brokers Alliance | I20: Corebridge-NY | J20: CORENY | L20: P.O. Box 25967 | M20: Shawnee Mission | N20: KS | O20: 66225 | P20: 800-225-5244 | R20: https://www.corebridgefinancial.com/what-we-offer/life-insurance | S20: https://live.cloud.api.aig.com | V20: Saturday | W20: EFT deposited EVERY Tuesday/ Checks mailed every other Wed. | X20: 50 | Y20: 50 | Z20: $50.00 / Not commissionable | AA20: Death Claim 1-12 mos prorated; Surrender 100% | AB20: $5,000 per policy | AC20: 800-247-8837
A21: L-CORERN | B21: Diamond, E, F, G | C21: Corebridge Renewals (American General) | D21: Yes | E21: Life Insurance | F21: TBD | G21: 0 | H21: Brokers Alliance | I21: Corebridge Renewals | J21: CORERE | L21: P.O. Box 25967 | M21: Shawnee Mission | N21: KS | O21: 66225 | P21: 800-225-5244 | R21: https://www.corebridgefinancial.com/what-we-offer/life-insurance | S21: https://live.cloud.api.aig.com | V21: Friday | W21: EFT deposited EVERY Tuesday/ Checks mailed every other Wed. | X21: 50 | Y21: 50 | Z21: $50.00 / Not commissionable | AA21: 1-6 Months 100% 7-12 months 50% | AB21: $5,000 per policy | AC21: 800-247-8838
A22: L-CORESIM | B22: Diamond, J, K, L, M, N, P, Q, T, U, R, S, Y, V, W, Z, A, B, C, D | C22: Corebridge SimpliNow | D22: Yes | F22: Hide
A23: L-COREWL | B23: Diamond, J, K, L, M, N, P, Q, T | C23: Corebridge Speciality (GIWL) | D23: Yes | E23: Life Insurance | F23: TBD | G23: 0 | H23: Brokers Alliance | I23: Corebridge-Special | J23: COREWL | L23: P.O. Box 25967 | M23: Shawnee Mission | N23: KS | O23: 66225 | P23: 800-225-5244 | R23: https://www.americangeneraltermlife.com/ | S23: https://www-1.aig.com/gpplogin/login/gp/html/en/jsp/login. | V23: Friday | W23: EFT deposited EVERY Tuesday/ Checks mailed every other Wed. | X23: 50 | Y23: 50 | Z23: $50.00 / Not commissionable | AA23: 1-6 Months 100% 7-12 months 50% | AB23: $5,000 per policy | AC23: 800-247-8837
A24: L-EQTL | B24: Diamond, 90, 85, 80, 75, 70, 65, 60, 55, 50 | C24: Equitable Life Insurance | D24: Yes | E24: Life Insurance | F24: TBD | G24: 0 | H24: Brokers Alliance | I24: Equitable Life | J24: EQTL | L24: 1290 Avenue of the Americas | M24: New York | N24: NY | O24: 10104 | P24: 800-342-4368 | Q24: 800-924-6669 | R24: https://equitable.com/customer-service/life-insurance#menu | S24: https://equitable.com/financial-professionals | V24: Daily; except renewals are 2 days before end of each month | W24: Checks mailed/EFTs sent 5-7 business days after policy is received | X24: No min | Y24: No min | Z24: $45 commissionable Level / $45 NOT commissionable on Graded | AA24: First year Graded: 100% Rescinded/Returned/Unearned: 100% | AB24: 2000 | AC24: 800-352-5122
A25: L-ETHOS | B25: Diamond, 100, 95, 90, 85, 80, 75, 70, 65, 60 | C25: Ethos Life Insurance | D25: Yes | E25: Life Insurance | F25: Top | G25: 0 | H25: Brokers Alliance | I25: Ethos (Banner) | J25: ETHOS | L25: 1606 Headway Circle 9013 | M25: Austin | N25: TX | O25: 78754 | P25: 415-915-0665 | Q25: 415-639-3968 | R25: https://www.ethoslife.com/life/ethos-term-life-insurance/ | S25: https://www.ethoslife.com/self-serve-organic/ | W25: 1st week of the month following activation | X25: undefined | Y25: undefined | AB25: No advance
A26: L-FAM | B26: Diamond, 90, 85, 80, 75, 70, 65, 50, 35 | C26: Family Life | D26: Yes | E26: Life Insurance | F26: Hide
A27: L-F&GL | B27: Diamond, LB, L2 (C), L3 (C), L4, L5, LE, L6, L7, L8, LL, LM, LN, LP, BA, L0, BB, BC, LZ | C27: Fidelity & Guaranty | D27: Yes | E27: Life Insurance | F27: Top | G27: 0 | H27: Brokers Alliance | I27: Fidelity & Guaranty | J27: F&GL | L27: 801 Grand Ave Suite 2600 | M27: Des Moines | N27: IA | O27: 50309 | P27: 888-513-8797 | R27: https://www.fglife.com/life-insurance | S27: https://saleslink.fglife.com/ | V27: Wednesday | W27: Checks mailed Monday/ EFTs released Friday | X27: 50 | Y27: 10 | Z27: $60.00 / not commissionable | AA27: 100% on 1st policy year, 50% 2nd, Over $25K 100% 0-24 mos | AB27: $3,500 per policy | AC27: 800-445-6758 | AD27: C-Carrier
A28: L-FIDEL | C28: Fidelity Life Insurance | D28: No | E28: Life Insurance | F28: TBD | G28: 0 | H28: Brokers Alliance | I28: Fidelity | J28: FIDEL | L28: 1350 E. Touhy Ave. Suite 205W | M28: Des PLaines | N28: IL | O28: 60018 | P28: 800-482-6616 | Q28: 866-853-3013 | R28: https://fidelitylife.com/ | S28: https://fidelitylife.com/login/ | V28: Thursday | W28: Tuesday | X28: 50 | Y28: 50 | Z28: N/A | AA28: Different for different agents | AB28: undefined | AC28: 800-369-3990 | AD28: Other product grids available by request
A29: L-FIDEL-ADB | B29: Diamond, A085, A080, A075, A070, A065, A060, A055, A050, A045, A040, A035, A030, A025, A020, A015, A010, A005 | C29: Fidelity ADB | D29: Yes
A30: L-FIDEL-FEGI | B30: Diamond, FG22, FG20, FG17, FG15, FG12, FG10, FG07, FG05, FG02, FG01, FG97, FG95, FG92, FG90 | C30: Fidelity FE & GI | D30: Yes
A31: L-FIDELHY | B31: Diamond, H115, H110, H105, H100, H095, H090, H085, H080, H075, H070, H065, H060, H055, H050, H045, H040, H035, H030, H025, H020, H015, H010, H005 | C31: Fidelity Hybrid | D31: Yes | F31: Hide
A32: L-FIDEL-RDSL | B32: Diamond, S085, S080, S075, S070, S065, S060, S055, S050, S045, S040, S035, S030, S025, S020, S015, S010, S005 | C32: Fidelity RDSL | D32: Yes
A33: L-FORESTL | C33: Foresters Financial | D33: No | E33: Life Insurance | F33: TBD | G33: 0 | H33: Brokers Alliance | I33: Foresters Old | J33: FORESLIFE | L33: 2221 Kenmore Ave Suite 108 | M33: Buffalo | N33: NY | O33: 14207 | P33: 800-828-1540 | R33: https://www.foresters.com/en/contact-us | S33: https://myezbiz.foresters.com/my.policy | V33: Wednesday | W33: Friday | X33: N/A | Y33: 50 | Z33: Varies | AA33: Unearned | AB33: Varies | AC33: 866-466-7166
A34: L-FORESPL | B34: Diamond, PLR MGA1, PLR GA02, PLR GA01, PLR AGT12, PLR AGT11, PLR AGT10, PLR AGT09, PLR AGT08, PLR AGT07, PLR AGT06, PLR AGT05, PLR AGT04, PLR AGT03, PLR AGT02, PLR AGT01 | C34: Foresters Planright | D34: Yes | E34: Life Insurance | F34: TBD | G34: 0 | H34: Brokers Alliance | I34: Foresters Traditional- Planright | J34: FORESPL | L34: 2221 Kenmore Ave Suite 108 | M34: Buffalo | N34: NY | O34: 14207 | P34: 800-828-1540 | R34: https://www.foresters.com/en/contact-us | S34: https://myezbiz.foresters.com/my.policy | V34: Wednesday | W34: Friday | X34: N/A | Y34: 50 | Z34: Varies | AA34: Unearned | AB34: Varies | AC34: 866-466-7166
A35: L-FORESTR | B35: Diamond, MGA 4, MGA 3, MGA 2, MGA 1, GA 3, GA 2, GA 1, Agent 11, Agent 10, Agent 9, Agent 8, Agent 7, Agent 6, Agent 5, Agent 4, Agent 3, Agent 2, Agent 1A | C35: Foresters Traditional | D35: Yes | F35: Top | I35: Foresters Traditional | J35: FORESTL
A36: L-FORESNY | B36: Diamond, GA 3, GA 2, GA 1, Agent 11, Agent 10, Agent 9, Agent 8, Agent 7, Agent 6, Agent 5, Agent 4, Agent 3, Agent 2, Agent 1A | C36: Foresters Traditional - NY | D36: Yes | E36: Life Insurance | F36: TBD | G36: 0 | H36: Brokers Alliance | I36: Foresters Traditional - NY | J36: FORESNY | L36: 2222 Kenmore Ave Suite 108 | M36: Buffalo | N36: NY | O36: 14207 | P36: 800-828-1541 | R36: https://www.foresters.com/en/contact-us | S36: https://myezbiz.foresters.com/my.policy | V36: Wednesday | W36: Friday | X36: N/A | Y36: 50 | Z36: Varies | AA36: Unearned | AB36: Medical-Non Commissionable | AC36: 866-466-7166 | AD36: *Commission Capped - Maximum commission age is 65 for Advantage Plus
A37: L-GERB | B37: Diamond, Level 3, Level 2, Level 1 | C37: Gerber Life Insurance | D37: Yes | E37: Life Insurance | F37: Hide | G37: 0 | H37: Brokers Alliance | I37: Gerber Life | J37: GERB | L37: 445 State Street | M37: Fremont | N37: MI | O37: 49412 | P37: 800-704-2180 | Q37: 800-428-4947 | R37: https://www.gerberlife.com/customer-service/contact-gerber-life | S37: https://www.gerberlife.com/gl/ap/view/agency/login.jsp | V37: Thursday | W37: Wednesday | X37: 25 | Y37: 25 | Z37: N/A | AA37: Death Claim within 1st year 100% 2nd yr 50% | AB37: As earned and only pay thru 1st year | AC37: 800-428-4947 | AD37: Face Amount split for state of Florida is ≤ $99,999, ≥ $100,000
A38: L-GLOAT | B38: Diamond, IND90, IND85, IND80, IND75, IND70, IND65, IND60, IND55, IND50, IND45, IND40 | C38: Global Atlantic Financial Group | D38: Yes | E38: Life Insurance | F38: TBD | G38: 0 | H38: Brokers Alliance | I38: Global Atlantic | J38: GLOAT | L38: 30 Hudson Yards 500 WEst 33rd St | M38: New York | N38: NY | O38: 10001 | P38: 866-645-2449 | Q38: 833-275-4248 | R38: https://www.globalatlantic.com/ | S38: https://auth.login.globalatlantic.com/user/login/public | V38: EFT: Friday; Check: Last business day | W38: EFT: Tuesday/Wednesday; Checks: Monthly first day following month | X38: 50 | Y38: 50 | Z38: N/A | AA38: 1-6 mos 100%; 7-12 mos 50% | AB38: Must be approved | AC38: 855-887-4487 | AD38: ECV Rider increases the target premium on the policy.
A39: L-GWEST | B39: Diamond, 110, 105, 100, 95, 90, 85, 80, 75, 70, 65, 60, 55, 50 | C39: Great Western | D39: Yes
A40: L-GCU | B40: Diamond, 115, 110, 105, 100, 90, 80, 70, 60 | C40: Greek Catholic Union Life Insurance | D40: Yes | E40: Life Insurance | F40: TBD | G40: 0 | H40: Brokers Alliance | I40: Greek Catholic Union | J40: GCU | L40: 5400 Tuscaraws Road | M40: Beaver | N40: PA | O40: 15009 | P40: 855-306-0607 | Q40: 800-722-4428 | R40: https://gcuusa.com/ | S40: https://portal.gcuusaonline.com/wps/portal | W40: Thursday | X40: No min | Y40: No min | AA40: Chargeback is prorated based on premiums paid during the first year that the certificate is in | AB40: 3000 | AC40: 800-722-4428
A41: L-GTL-LIFE | B41: Diamond, 50, 45, 40, 35, 30, 25, 20, 15 | C41: Guarantee Trust Life | D41: Yes
A42: L-GTL-OTH | B42: Diamond, 50, 47, 46, 45, 40, 35, 30, 25, 20, 15, 11, 10, 8, 6, 4, 2 | C42: Guarantee Trust Life - Other | D42: Yes
A43: L-GTL-HER | B43: Diamond, Level 35, Level 30, Level 25, Level 22, Level 20, Level 18, Level 15 | C43: Guarantee Trust Life - Heritage | D43: Yes
A44: L-ILLMUT | B44: Diamond, 55 | C44: Illinois Mutual | D44: Yes
A45: L-ILLMU-FE | B45: Diamond, 35, 30, 5 | C45: Illinois Mutual - FE | D45: Yes
A46: L-INACT | B46: Diamond, 261/131, 253, 241/242, 233, 221/222, 213, 203, 193, 183, 173, 160 | C46: InActive | D46: No
A47: L-INACTBALT | B47: Diamond, 120, 115, 110, 105, 95, 85, 75, 65 | C47: InActive (Baltimore) | D47: No
A48: L-INSTA | B48: Diamond, B110, B105, B100, B95, B90, B85, B80, B00 | C48: InstaBrain | D48: Yes
A49: L-INSTAHEAP | B49: Diamond, BH25, BH20, BH15, BH10, BH05, BH00, BH95, BH90, BH85, BH80 | C49: InstaBrain Heaped | D49: Yes
A50: L-JHAN | B50: Diamond, 90, 85, 80, 50 | C50: John Hancock | D50: Yes | E50: Life Insurance | F50: TBD | G50: 0 | H50: Brokers Alliance | I50: John Hancock | J50: JHAN | L50: 100 Summit Lake Drive 2nd floor | M50: Valhalla | N50: NY | O50: 10595 | P50: 800732-5543 | Q50: 888-888-8856 | R50: https://www.johnhancock.com/index.html | S50: https://partnerlink.jhancock.com | V50: Friday | W50: Checks: mailed Tuesdays; EFT: in acct Wednesdays | X50: 1000 | Y50: No min | Z50: Term: Varies Not Commissionable | AA50: Varies by Product: 1-18 months incurs CB | AB50: No Advancement | AC50: 800-505-9427
A51: L-JHANNY | B51: Diamond, Agent | C51: John Hancock - NY | D51: Yes | E51: Life Insurance | F51: TBD | G51: 0 | H51: Brokers Alliance | I51: John Hancock - NY | J51: JHANNY | L51: 100 Summit Lake Drive 2nd floor | M51: Valhalla | N51: NY | O51: 10595 | P51: 800-294-3575 | Q51: 800-395-113 | R51: https://www.johnhancock.com/index.html | S51: https://www.ps.jhancocknypensions.com/do/home/homePageFinder/ | V51: Friday | W51: Checks: mailed Tuesdays; EFT: in acct Wednesdays | X51: 1000 | Y51: No min | Z51: Term: Varies Not Commissionable | AA51: Varies by Product: 1-18 months incurs CB | AB51: No Advancement | AC51: 800-505-9427
A52: L-KANS | B52: Diamond, Level 16, Level 15, Level 14, Level 13, Level 12, Level 11, Level 10, Level 9, Level 8, Level 7, Level 6, Level 5, Level 4, Level 3, Level 2, Level 1 | C52: Kansas City Life | D52: Yes
A53: L-KANS-SI | B53: Diamond, Level 19, Level 18, Level 17, Level 16, Level 15, Level 14, Level 13, Level 12, Level 11, Level 10, Level 9, Level 8, Level 7, Level 6, Level 5, Level 4, Level 3, Level 2, Level 1 | C53: Kansas City Life - Simplified Issue | D53: Yes
A54: L-KEMP | B54: Diamond, CCBY, CCCX, CCDW, CCEV, CCFU, CCGT | C54: Kemper Life Insurance | D54: Yes | E54: Life Insurance | F54: TBD | G54: 0 | H54: Brokers Alliance | I54: Kemper | J54: KEMP | L54: 12115 Lackland Road | M54: St Louis | N54: MO | O54: 63146 | P54: 800-777-8467 | Q54: 866-859-5090 | R54: https://www.kemper.com/ | S54: https://signin.kemper.com/login/specialty/ | V54: Daily | W54: Daily;7 days after the bank draft date | X54: No min | Y54: No min | Z54: N/A | AA54: Charged once cancellation takes effect | AB54: 500 | AC54: 877-877-0199
A55: L-LIBBK | B55: Diamond, CE 115, CF 110, CG 105, CH 100, CI 95, CJ 90, CK 85, CL 80, CM 75, CN 70, CO 65, CP 60, CQ 55, CR 50, CS 45, CT 40, CU 35 | C55: Liberty Bankers Insurance Group for Life | D55: Yes | E55: Life Insurance | F55: TBD | G55: 0 | H55: Brokers Alliance | I55: Liberty Bankers | J55: LIBNBK | L55: 1605 Lyndon B. Johnson Freeway Suite 700 | M55: Dallas | N55: TX | O55: 75234 | P55: 800-972-6615 | Q55: 800-731-4300 | R55: https://lbig.com/life | S55: https://myportal.lbig.com/login.php | V55: Daily | W55: Daily | X55: 25 | Y55: 25 | Z55: $50 Commissionable | AA55: Unerned | AB55: $1,800 per client
A56: L-LFGANN | B56: Diamond, 90, 85, 80, 75, 70, 65, 60 | C56: Lincoln National | D56: Yes | E56: Life Insurance | F56: TBD | G56: 0 | H56: Brokers Alliance | I56: Lincoln Financial | J56: LFGANN | L56: 15260 Ventura Blvd, | M56: Sherman Oaks | N56: CA | O56: 91403 | P56: 818-906-3332 | Q56: 800-487-1485 | R56: https://www.lincolnfinancial.com/public/individuals/support/customerservice/annuityresources/myaccount | S56: https://auth.lincolnfinancial.com/login? | V56: Friday | W56: Check: Tuesday; EFT: Monday | X56: 2500 | Y56: 10 | Z56: $90.00 Not commissionable $75.00 ROP Products Not Commissionable | AA56: 1-6 mos 100%; 7-12 mos 50% | AB56: If agent set up on annualization based off of contract: 75% of annualized commissions max 4,000 on any one policy and 15,000 per month. If not on annualization based off of commission schedule | AC56: 800-238-6252
A57: L-LFGMG | B57: Diamond, 6 | C57: Lincoln National - Money Guard | D57: Yes | E57: Life Insurance | F57: TBD | G57: 0 | H57: Brokers Alliance | I57: Lincoln National - Money Guard | J57: LFGMG | L57: 15261 Ventura Blvd, | M57: Sherman Oaks | N57: CA | O57: 91403 | P57: 818-906-3333 | Q57: 800-487-1485 | R57: https://www.lincolnfinancial.com/public/individuals/support/customerservice/annuityresources/myaccount | S57: https://auth.lincolnfinancial.com/login? | V57: Friday | W57: Check: Tuesday; EFT: Monday | X57: 2500 | Y57: 10 | Z57: $90.00 Not commissionable $75.00 ROP Products Not Commissionable | AA57: 1-6 mos 100%; 7-12 mos 50% | AB57: If agent set up on annualization based off of contract: 75% of annualized commissions max 4,000 on any one policy and 15,000 per month. If not on annualization based off of commission schedule | AC57: 800-238-6253
A58: L-LSWNLG | B58: Diamond, GAK, GAJ, GAI, GAH, GAG, GAF, GAE, GAD, GAP, GAC, GAO, GAB, GAN, GAA | C58: LSW - National Life Group | D58: Yes | E58: Life Insurance | F58: TBD | G58: 0 | H58: Brokers Alliance | I58: National Life - LSW | J58: LSWNLG | L58: 1 National Life Drive | M58: Montpelier | N58: VT | O58: 5604 | P58: 800-732-8939 | Q58: 877-654-3499 | R58: https://www.nationallife.com/ | S58: https://nlg-prod.auth0.com/login? | V58: Thursday | W58: Checks mailed following Weds/ETfs in account by following Weds | X58: 350 | Y58: No | Z58: $72.00 / Not commissionable / 50% discount on policy fee for 2nd policy covering spouse | AA58: 100% < 12 mos | AB58: Varies by Agency | AC58: 800-906-3310
A59: L-MINNL | B59: Diamond, 95, 90, 85, 80, 75, 70, 65, 60, 55, 50 | C59: Minnesota Life Insurance Company | D59: Yes | I59: Minnesota Life
A60: L-MINNVL | B60: Diamond, BD 7, BD 8, BD 9, BD 10 | C60: Minnesota Life Insurance Company - VUL | D60: Yes | E60: Life Insurance | F60: TBD | G60: 0 | H60: Brokers Alliance | I60: Minnesota Life - VUL | J60: MN-VUL | L60: 401 Robert Street North | M60: Saint Paul | N60: MN | O60: 55101 | P60: 866-335-7356 | Q60: 877-696-6655 | R60: https://www.securian.com | S60: https://www.securian.com/financial-professionals.html | V60: Thursday | W60: Wednesday | X60: 25 | Y60: 25 | Z60: Varies by Product | AA60: Unearned; Surrended Value years 1-4 | AB60: As earned | AC60: 888-413-7860
A61: L-LSWNY | B61: Diamond, Street | C61: National LIfe Group NY | D61: Yes | E61: Life Insurance | F61: TBD | G61: 0 | H61: Brokers Alliance | I61: National Life - NY | J61: LSWNY | L61: 1 National Life Drive | M61: Montpelier | N61: VT | O61: 5604 | P61: 800-732-8940 | Q61: 877-654-3499 | R61: https://www.nationallife.com/ | S61: https://nlg-prod.auth0.com/login? | V61: Thursday | W61: Checks mailed following Weds/ETfs in account by following Weds | X61: 350 | Y61: No | Z61: $72.00 / Not commissionable / 50% discount on policy fee for 2nd policy covering spouse | AA61: 100% < 12 mos | AB61: Varies by Agency | AC61: 800-906-3310 | AD61: Compensation listed is commission WITH Expense Allowance
A62: L-NWLIF | B62: Diamond, L3 (C), L2 (C), LU8, LU7, LU6, LU5 | C62: National Western Life Insurance Company | D62: Yes | E62: Life Insurance | F62: TBD | G62: 0 | H62: Brokers Alliance | I62: National Western | J62: NWLIF | L62: 10801 N Mopac Expy, Bldg 3 | M62: Austin | N62: TX | O62: 78759 | P62: 800-922-9422 | Q62: 800-760-3434 | R62: https://www.nationalwesternlife.com/ | S62: https://www.mynwl.com/ | V62: Friday | W62: Check mailed Monday/ EFT's released Monday | X62: 100 | Y62: 50 | Z62: N/A | AA62: Varies by age and moths-- Chart on Schedule | AB62: $15,000 per policy | AC62: 800-760-3434 | AD62: C- Carrier
A63: L-NWIDE | B63: Diamond, 100 Level, 95 Level, 90 Level, 85 Level, 80 Level, 75 Level, 70 Level, 65 Level, 60 Level, 55 Level, 50 Level | C63: Nationwide | D63: Yes | E63: Life Insurance | F63: TBD | G63: 0 | H63: Brokers Alliance | I63: Nationwide | J63: NWIDE | L63: PO Box 182021 | M63: Columbus | N63: Ohio | O63: 43218 | P63: 877-669-6877 | Q63: 800-321-6064 | R63: https://www.nationwide.com | S63: https://agentcenter.nationwide.com/WorkspaceAC/login? | V63: Thursday | W63: Friday | X63: N/A | Y63: No min | Z63: Term: A: $75 SA: $38.48 Q: $19.73 M: $6.56 | AA63: Lapse 1-6 months 100%, 6-12 50% / Surrendered 100% 1-12 months | AB63: No advancement | AC63: 888-767-7373
A64: L-NYL | B64: Diamond, Producer | C64: New York Life | D64: Yes | E64: Life Insurance | F64: TBD | G64: 0 | H64: Brokers Alliance | I64: New York Life | J64: NYL | L64: PO Box 796 | M64: New York | N64: NY | O64: 10159 | P64: 800-695-4785 | Q64: 800-225-5695 | R64: https://www.newyorklife.com/ | S64: https://www.pfed.newyorklife.com:9031/idp/startSSO.ping? | V64: 2 business days prior to payment | W64: 15th and last business day | X64: 3 | Y64: No min | Z64: $100 Non Commisionable | AA64: < 6 mos 100%, otheriwse depends on the product | AB64: No advancement | AC64: 888-695-4748
A65: L-NAC | B65: Diamond, GA 100, GA 95, WA 90, WA 85, WA 80, WA 75, WA 70, WA 65, WA 60 | C65: Noth America Company for Life and Health | D65: Yes | E65: Life Insurance | F65: TBD | G65: 0 | H65: Brokers Alliance | I65: North American | J65: N-NACOLAH | L65: One Sammons Plaza | M65: Sioux Falls | N65: SD | O65: 57193 | P65: 877-8720757 | Q65: 866-322-7069 | R65: https://www.northamericancompany.com/naloginpage | S65: https://www.northamericancompany.com/naloginpage | V65: Friday | W65: Tuesday | X65: N/A | Y65: 50 | Z65: $65.00- Not commissionable (ADDvantage term products fee is based on the mode of the policy.) | AA65: Surrendered/Death Claim 1-6 mos 100%; 7-12 50%; Withdrawal varies on amount | AB65: 2500 | AC65: 800-800-3556
A66: L-ONEAM | B66: Diamond, Street | C66: One America Financial Partners, Inc. | D66: Yes | E66: Life Insurance | F66: TBD | G66: 0 | H66: Brokers Alliance | I66: One America | J66: ONEAM | L66: P.O. Box 368 | M66: Indianapolis | N66: IN | O66: 46206 | P66: 844-833-5420 | Q66: 844-833-5420 | R66: https://www.oneamerica.com/ | S66: https://www.oneamerica.com/financial-professionals/life-insurance-annuities | V66: Monthly | W66: 3rd business day of month | X66: 1 | Y66: 1 | AA66: < 6 mos 100%, 7-12 mos 50% | AB66: undefined | AC66: 800-428-9198
A67: L-OXF | B67: Diamond, AGENT, Agent 1, Agent 2, Agent 3, Agent 4, Agent 5, Agent 6, Agent 7, Agent 8, Agent 9, Agent 10, Agent 11, Agent 12, Agent 13, Agent 14 | C67: Oxford Life Insurance Company | D67: Yes | E67: Life Insurance | F67: TBD | G67: 0 | H67: Brokers Alliance | I67: Oxford | J67: OXF | L67: 2721 N Central Ave | M67: Phoenix | N67: AZ | O67: 85004 | P67: 866-641-9999 | Q67: 866-626-7532 | R67: https://oxfordlife.com/ | S67: https://oxfordlife.com/agent/ | V67: digitalmarketing@oxfordlife.com | X67: undefined | Y67: undefined | AB67: undefined
A68: L-PACLIFE | B68: Diamond, 85, 80, 75, 70, 65, 60, 50 | C68: Pacific Life Insurance | D68: Yes | E68: Life Insurance | F68: TBD | G68: 0 | H68: Brokers Alliance | I68: Pacific Life | J68: PACLIFE | L68: PO Box 2030 | M68: Omaha | N68: NE | O68: 68103 | P68: 800-347-7787 | Q68: 844-276-0193 | R68: https://www.pacificlife.com/ | S68: https://www.pacificlife.com/home/benefits-of-working-with-us/financial-professional-logins.html | V68: Friday | W68: Wednesday | X68: No min | Y68: No min | Z68: N/A | AA68: Unearned | AB68: No advancement | AC68: 800-800-7646
A69: L-PACLIFE-PT | B69: Diamond, PLGA, PL07, PL06, PL05, PL04, PL03, PL02, PL01 | C69: Pacific Life Insurance - Promise Term | D69: Yes | E69: Life Insurance | F69: TBD | G69: 0 | H69: Brokers Alliance | I69: Pacific Life - Promise Term | J69: PACLIFEPT | L69: PO Box 2031 | M69: Omaha | N69: NE | O69: 68103 | P69: 800-347-7788 | Q69: 844-276-0194 | R69: https://www.pacificlife.com/ | S69: https://www.pacificlife.com/home/benefits-of-working-with-us/financial-professional-logins.html | V69: Friday | W69: Wednesday | X69: 2500 | Y69: 5 | Z69: N/A | AA69: 100% for lapse/surrender/reversal; Unearned | AB69: $2500 on term; no advance on perm | AC69: 844-238-4872
A70: L-PRIN | B70: Diamond, Producer 50 | C70: Principal | D70: Yes | E70: Life Insurance | F70: TBD | G70: 0 | H70: Brokers Alliance | I70: Principal | J70: PRIN | L70: 6701 Westown Parkway suite 200 | M70: West Des Moines | N70: IA | O70: 50266 | P70: 800-986-3343 | Q70: 800-654-4278 | R70: https://www.principal.com/ | S70: https://advisors.principal.com/wps/portal/advisor/home | V70: Friday | W70: Wednesday | X70: 2500 | Y70: 5 | Z70: N/A | AA70: 100% for lapse/surrender/reversal; Unearned | AB70: $2500 on term; no advance on perm | AC70: 844-238-4873
A71: L-PRINNY | B71: Diamond, Producer 50 | C71: Principal - NY | D71: Yes | E71: Life Insurance | F71: TBD | G71: 0 | H71: Brokers Alliance | I71: Principal -NY | J71: PRINNY | L71: 6702 Westown Parkway suite 200 | M71: West Des Moines | N71: IA | O71: 50266 | P71: 877-657-7587 | Q71: 800-654-4278 | R71: https://www.principal.com/ | S71: https://advisors.principal.com/wps/portal/advisor/home | V71: 14th & 28th | W71: 15th and last day of month | X71: N/A | Y71: No min | Z71: Term: $75 Not commissionable | AA71: Varies based on Commission Schedule. Can chargeback up to 3 years. | AB71: No advancement | AC71: 800-388-4793
A72: L-PROS | B72: Diamond, 115, 110, 100, 95, 90, 85, 80, 75, 70, 65, 60, 55, 50, 45, 25 | C72: Prosperity Life | D72: Yes
A73: L-PROT | B73: Diamond, Sub-BGA A, Sub-BGA B, Recruiter A, Recruiter B, Recruiter C, Agent A, Agent B, Agent C, Agent D, Agent E, Agent F, Agent G, Agent H | C73: Protective | D73: Yes | E73: Life Insurance | F73: TBD | G73: 0 | H73: Brokers Alliance | I73: Protective | J73: PROT | L73: 111 Congressional Blvd. #500 | M73: Carmel | N73: IN | O73: 46032 | P73: 844-733-5433 | Q73: 877-778-3500 opti-1 | R73: https://www.protective.com/ | S73: https://www.myprotective.com/ | V73: Check: Last business day; EFT: Friday | W73: Check: Last business day; EFT: Tuesday | X73: 100 | Y73: No min | Z73: $60.00 $0 - $249,999 Commissionable / $50.00 $250,000 + Not commissionable | AA73: 1-6 mos 100%; 7-12 mos 50% | AB73: 7500 | AC73: 800-333-3418
A74: L-PROTNY | B74: Diamond, Agent 50 | C74: Protective - NY | D74: Yes | E74: Life Insurance | F74: TBD | G74: 0 | H74: Brokers Alliance | I74: Protective - NY | J74: PROTNY | L74: 111 Congressional Blvd. #500 | M74: Carmel | N74: IN | O74: 46032 | P74: 844-733-5433 | Q74: 877-778-3500 opti-1 | R74: https://www.protective.com/ | S74: https://www.myprotective.com/ | V74: Check: Last business day; EFT: Friday | W74: Check: Last business day; EFT: Tuesday | X74: 100 | Y74: No min | AA74: 1-6 mos 100%; 7-12 mos 50% | AB74: undefined | AC74: 800-333-3418
A75: L-PRUD | B75: Diamond, 75 (GA1), Broker 50 | C75: Prudential Financial, Inc. | D75: Yes | E75: Life Insurance | F75: TBD | G75: 0 | H75: Brokers Alliance | I75: Prudential | J75: PRUD | L75: 153 Halsey Street | M75: Newark | N75: NJ | O75: 7102 | P75: 800-424-1592 | R75: https://www.prudential.com/login | S75: https://www.prudential.com/advisor-login | V75: Thursday | W75: Check: Monday; EFT: Tuesday | X75: 250 | Y75: No min | Z75: $85.00 / Not commissionable | AA75: 1-6 mos 100%; 7-12 mos 50% | AB75: No advancment | AC75: 866-622-8778
A76: L-PRUNY | B76: Diamond, 75 (GA1), 50 | C76: Prudential - NY | D76: Yes | E76: Life Insurance | F76: TBD | G76: 0 | H76: Brokers Alliance | I76: Prudential -NY | J76: PRUNY | L76: 154 Halsey Street | M76: Newark | N76: NJ | O76: 7102 | P76: 800-424-1593 | R76: https://www.prudential.com/login | S76: https://www.prudential.com/advisor-login | V76: Friday | W76: Check: Monday; EFT: Tuesday | X76: 250 | Y76: No min | Z76: $85.00 / Not commissionable | AA76: 1-6 mos 100%; 7-12 mos 50% | AB76: No advancment | AC76: 866-622-8779
A77: L-ROYN | B77: Diamond, RGA, TGA, SGA, GA1, GA2, GA3, SA1, SA2, SA3 | C77: Royal Neighbors of America | D77: Yes | E77: Life Insurance | F77: TBD | G77: 0 | H77: Brokers Alliance | I77: Royal Neighbors | J77: ROYN | L77: 230 16th Street | M77: Rock Island | N77: IL | O77: 61201 | P77: 800-627-4762 | Q77: 800-770-4561 opti-5 then 5 | R77: https://www.royalneighbors.org/about-us/contact-us | S77: https://agent.royalneighbors.org/login | V77: Tuesday | W77: Checks mailed Wednesday/ETfs deposited daily | X77: 50 | Y77: 50 | Z77: Simplified Issue: $35; Term: $80; Whole Life: $50 all annual and commissionable | AA77: Unearned Premium | AB77: 2000 | AC77: 866-733-9758
A78: L-SAGIC | B78: Diamond, AGA, GA, PPGA, PGA, WA | C78: Sagicor Life Insurance Company | D78: Yes | E78: Life Insurance | F78: TBD | G78: 0 | H78: Brokers Alliance | I78: Sagicor | J78: SAGIC | L78: 4010 W. Boy Scout Blvd. Suite 800 | M78: Tampa | N78: FL | O78: 33607 | P78: 813-287-1602 | Q78: 888-724-4267 ext 4610 | R78: https://www.sagicor.com/en-US | S78: https://client.sagicor.com/ | V78: Daily | W78: No Checks/next day payout ETfs | X78: No | Y78: 50 | Z78: Annual $75 built into premium | AA78: 100% for Not Taken; 1-12 mos 100% | AB78: No advancement offered by carrier | AC78: 800-531-5067
A79: L-SBLI | B79: Diamond, VI, V, IV, III, II, I | C79: The Savings Bank Mutual Life Insurance Company | D79: Yes | E79: Life Insurance | F79: TBD | G79: 0 | H79: Brokers Alliance | I79: SBLI | J79: SBLI | L79: PO BOX 55249 | M79: Boston | N79: MA | O79: 2205 | P79: 888-630-5000 | Q79: 800-694-7254 | R79: https://www.sbli.com/ | S79: https://auth.sbli.com/ | V79: Friday | W79: Checks mailed on Monday/ EFT available Tuesday | X79: 250 | Y79: No min | Z79: $60.00 / Not commissionable | AA79: 1-6 mos 100% 7-12 50% | AB79: $900 per policy | AC79: 888-2247254 | AD79: Note: All numbers above shall be reduced by 30% for issue ages 76 and above.
A80: L-SBLI-FE | B80: Diamond, 12, 11, 10, 9, 8, 7, 6, 5, 4, 3, 2, 1 | C80: The Savings Bank Mutual Life Insurance Company-FE | D80: Yes
A81: L-SENT | B81: Diamond, MGA, RGA, GA, DL11, DL10, DL09, DL08, DL07, DL06, DL05, DL04, DL03, DL02, DL01 | C81: Sentinel | D81: Yes | E81: Life Insurance
A82: L-SYMET | B82: Diamond, Combo 13, Combo 12, Combo 11 | C82: Symetra | D82: Unk | E82: Life Insurance | F82: TBD | G82: 0 | H82: Brokers Alliance | I82: Symetra | J82: SYMET | L82: 777 108th Ave NE Suite 1200 | M82: Bellevue | N82: WA | O82: 98004 | P82: 800-796-3872 | Q82: 800-706-0700 | R82: https://www.symetra.com/ | S82: https://financialprofessionals.symetra.com/? | V82: Check: Quarterly; EFT: Friday | W82: Check: Last business day of Quarter; EFT: Friday | X82: 500 | Y82: No min | AA82: 1-6 mos 100%; 7-12 mos 50%; Death Claim 0% | AB82: No advancement | AC82: 800-210-1106
A83: L-TRANS | B83: Diamond, MO 5 Ptn 1 Rk 60, MO 5 Ptn 1 Rk 59, MO 5 Ptn 1 Rk 58, MO 5 Ptn 1 Rk 57, MO 5 Ptn 1 Rk 56, MO 5 Ptn 1 Rk 52, MO 5 Ptn 1 Rk 50, MO 5 Ptn 1 Rk 49, MO 5 Ptn 1 Rk 48, MO 5 Ptn 1 Rk 42, MO 5 Ptn 1 Rk 40, MO 5 Ptn 1 Rk 38, MO 5 Ptn 1 Rk 36, MO 5 Ptn 1 Rk 35, MO 5 Ptn 1 Rk 34, MO 5 Ptn 1 Rk 32, MO 5 Ptn 1 Rk 31, MO 5 Ptn 1 Rk 30, MO 5 Ptn 1 Rk 29, MO 5 Ptn 1 Rk 27, MO 5 Ptn 1 Rk 25, MO 5 Ptn 1 Rk 24, MO 5 Ptn 1 Rk 22, MO 5 Ptn 1 Rk 21, MO 5 Ptn 1 Rk 20, MO 5 Ptn 1 Rk 19, MO 5 Ptn 1 Rk 18, MO 5 Ptn 1 Rk 17, MO 5 Ptn 1 Rk 16, MO 5 Ptn 1 Rk 15, MO 5 Ptn 1 Rk 14, MO 5 Ptn 1 Rk 13, MO 5 Ptn 1 Rk 12, MO 5 Ptn 1 Rk 11, MO 5 Ptn 1 Rk 10, MO 5 Ptn 1 Rk 8, MO 5 Ptn 1 Rk 7, MO 5 Ptn 1 Rk 6 | C83: Transamerica Family Markets | D83: Unk | E83: Life Insurance | F83: TBD | G83: 0 | H83: Brokers Alliance | I83: Transamerica Family Markets | J83: TRANS | L83: 6400 C Street SW | M83: Cedar Rapids | N83: IA | O83: 52499 | P83: 800-7972643 | Q83: 800-797-2643 | R83: https://www.transamerica.com/ | S83: https://secure.transamerica.com/login/sign-in/login.html? | V83: Daily | W83: ETfs only--released Fridays | X83: 500 | Y83: No min | Z83: $80.00 Elite Trm II w/ & w/o ROP commissionable / $60.00 Home Protector commissionable | AA83: Unearned | AB83: $1,500 per policy | AC83: 877-454-4768
A84: L-UNHOME | B84: Diamond, 3040, 3035, 3030, 3025, 3020, 3015, 3010, 3005, 3115, 3110, 3107, 3106, 3105, 3104 | C84: United Home Life Insurance Company | D84: Yes | E84: Life Insurance | F84: TBD | G84: 0 | H84: Brokers Alliance | I84: United Home Life | J84: UNHOME | L84: 225 S East St | M84: Indianapolis | N84: IN | O84: 46202 | P84: 800-428-3001 | R84: https://www.unitedhomelife.com/ | S84: https://login.agentportal.unitedhomelife.com/apb2cprd. | V84: Daily | W84: Checks mailed end of month/EFTs released daily | X84: 25 | Y84: 25 | Z84: $100 Not commissionable | AA84: Annualized: 100% or remaining, AE: no CB | AB84: $1,500 per policy | AC84: 800-428-3001
A85: L-UO-UL | B85: Diamond, 10, 9, 8, 7, 6, 5, 4, 3, 2, 1 | C85: United of Omaha - Universal Life | D85: Yes | E85: Life Insurance
A86: L-UO-CWL | B86: Diamond, 29, 28, 27, 26, 25, 24, 23, 22, 21, 20, 19, 18, 17, 16 | C86: United of Omaha - CWL | D86: Yes | E86: Life Insurance
A87: L-UO-EXP | B87: Diamond, 25, 24, 23, 22, 21, 20, 19, 18, 17, 16, 15, 14, 13, 12, 11, 10, 9, 8, 7, 6, 5, 4, 3, 2, 1 | C87: United of Omaha - Express | D87: Yes | E87: Life Insurance | F87: TBD | G87: 0 | H87: Brokers Alliance | I87: United of Omaha - Express | J87: MOO | L87: 215 South 15th Street | M87: Omaha | N87: NE | O87: 68102 | P87: 888-989-2164 | R87: https://www.mutualofomaha.com/ | S87: https://accounts.mutualofomaha.com/samlAuthnRequest | V87: Tuesday | W87: Checks: Thursday; EFT: Friday | X87: 250 | Y87: 50 | Z87: $60.00 / Not commissionable | AA87: 1-6 mos 100%; 7-12 mos 50% | AB87: $2,000 per policy | AC87: 800-867-6873
A88: L-UOMOO | B88: Diamond, 8, 7, 6, 5, 4, 3, 2, 1 | C88: United of Omaha - TRAD | D88: Yes | E88: Life Insurance | F88: TBD | G88: 0 | H88: Brokers Alliance | I88: United of Omaha | J88: UOMOO | L88: 215 South 15th Street | M88: Omaha | N88: NE | O88: 68102 | P88: 888-989-2164 | R88: https://www.mutualofomaha.com/ | S88: https://accounts.mutualofomaha.com/samlAuthnRequest | V88: Tuesday | W88: Checks: Thursday; EFT: Friday | X88: 250 | Y88: 50 | Z88: $60.00 / Not commissionable | AA88: 1-6 mos 100%; 7-12 mos 50% | AB88: $2,000 per policy | AC88: 800-867-6873
A89: L-UO-FE | B89: Diamond, 24, 23, 22, 21, 20, 19, 18, 17, 16, 15, 14, 13, 12, 11, 10, 9, 8, 7, 6, 5, 4, 3, 2, 1 | C89: United of Omaha - FE | D89: Yes | E89: Life Insurance | F89: TBD | G89: 0 | H89: Brokers Alliance | I89: United of Omaha - FE | J89: MOOFE | L89: 215 South 15th Street | M89: Omaha | N89: NE | O89: 68102 | P89: 888-989-2164 | R89: https://www.mutualofomaha.com/ | S89: https://accounts.mutualofomaha.com/samlAuthnRequest | V89: Tuesday | W89: Checks: Thursday; EFT: Friday | X89: 250 | Y89: 50 | Z89: $60.00 / Not commissionable | AA89: 1-6 mos 100%; 7-12 mos 50% | AB89: $2,000 per policy | AC89: 800-867-6873
A90: L-UO-TLE | B90: Diamond, 35, 34, 33, 32, 31, 30, 29, 28, 27, 26, 25, 24, 23, 22, 21, 20, 19 | C90: United of Omaha - TLE | D90: Yes | E90: Life Insurance | F90: TBD | G90: 0 | H90: Brokers Alliance | I90: United of Omaha - TLE | J90: MOOTLE | L90: 215 South 15th Street | M90: Omaha | N90: NE | O90: 68102 | P90: 888-989-2164 | R90: https://www.mutualofomaha.com/ | S90: https://accounts.mutualofomaha.com/samlAuthnRequest | V90: Tuesday | W90: Checks: Thursday; EFT: Friday | X90: 250 | Y90: 50 | Z90: $60.00 / Not commissionable | AA90: 1-6 mos 100%; 7-12 mos 50% | AB90: $2,000 per policy | AC90: 800-867-6873
A91: L-WP | B91: Diamond, AGAB 40, AGAB 20 | C91: William Penn | D91: Yes | E91: Life Insurance | F91: TBD

Sheet L-AAI-EZT
A1: Row | B1: Service-Carrier ID | C1: Product Tier | D1: Types | E1: State Available | F1: Old Product name | G1: Sub-Name | H1: Sub-type | I1: Length | J1: Product Name Full | K1: Product Real | L1: All Vendor paycodes | M1: Product | N1: Criteria | O1: Notes | P1: Diamond | Q1: 95 | R1: 90 | S1: 85 | T1: 80 | U1: 75 | V1: 70 | W1: 65 | X1: 60 | Y1: 55 | Z1: 50 | AA1: 45 | AB1: 40
A2: 1 | B2: L-AAI-EZT | D2: Term | E2: All Avail. | F2: EZ Term 10 | H2: Term | I2: 10 | J2: EZ Term 10 Year | K2: Yes | L2: Diamond, 95, 90, 85, 80, 75, 70, 65, 60, 55, 50, 45, 40 | M2: EZ Term 10 | N2: Sub type: 10 Year Term | State: Alabama, Alaska, Arizona, Arkansas, California, Colorado, Connecticut, Delaware, Florida, Georgia, Hawaii, Idaho, Illinois, Indiana, Iowa, Kansas, Kentucky, Louisiana, Maine, Maryland, Massachusetts, Michigan, Minnesota, Mississippi, Missouri, Montana, Nebraska, Nevada, New Hampshire, New Jersey, New Mexico, North Carolina, North Dakota, Ohio, Oklahoma, Oregon, Pennsylvania, Rhode Island, South Carolina, South Dakota, Tennessee, Texas, Utah, Vermont, Virginia, Washington, West Virginia, Wisconsin, Wyoming | P2: 80 | Q2: 80 | R2: 75 | S2: 70 | T2: 65 | U2: 60 | V2: 55 | W2: 50 | X2: 45 | Y2: 40 | Z2: 35 | AA2: 30 | AB2: 25
A3: 2 | B3: L-AAI-EZT | C3: TBD | D3: Term | E3: All Avail. | F3: EZ Term 20 | H3: Term | I3: 20 | J3: EZ Term 20 Year | K3: Yes | L3: Diamond, 95, 90, 85, 80, 75, 70, 65, 60, 55, 50, 45, 40 | M3: EZ Term 20 | N3: Sub type: 20 Year Term | State: Alabama, Alaska, Arizona, Arkansas, California, Colorado, Connecticut, Delaware, Florida, Georgia, Hawaii, Idaho, Illinois, Indiana, Iowa, Kansas, Kentucky, Louisiana, Maine, Maryland, Massachusetts, Michigan, Minnesota, Mississippi, Missouri, Montana, Nebraska, Nevada, New Hampshire, New Jersey, New Mexico, North Carolina, North Dakota, Ohio, Oklahoma, Oregon, Pennsylvania, Rhode Island, South Carolina, South Dakota, Tennessee, Texas, Utah, Vermont, Virginia, Washington, West Virginia, Wisconsin, Wyoming | P3: 99 | Q3: 95 | R3: 90 | S3: 85 | T3: 80 | U3: 75 | V3: 70 | W3: 65 | X3: 60 | Y3: 55 | Z3: 50 | AA3: 45 | AB3: 40
A4: 3 | B4: L-AAI-EZT | C4: TBD | D4: Term | E4: All Avail. | F4: EZ Term 30 | H4: Term | I4: 30 | J4: EZ Term 30 Year | K4: Yes | L4: Diamond, 95, 90, 85, 80, 75, 70, 65, 60, 55, 50, 45, 40 | M4: EZ Term 30 | N4: Sub type: 30 Year Term | State: Alabama, Alaska, Arizona, Arkansas, California, Colorado, Connecticut, Delaware, Florida, Georgia, Hawaii, Idaho, Illinois, Indiana, Iowa, Kansas, Kentucky, Louisiana, Maine, Maryland, Massachusetts, Michigan, Minnesota, Mississippi, Missouri, Montana, Nebraska, Nevada, New Hampshire, New Jersey, New Mexico, North Carolina, North Dakota, Ohio, Oklahoma, Oregon, Pennsylvania, Rhode Island, South Carolina, South Dakota, Tennessee, Texas, Utah, Vermont, Virginia, Washington, West Virginia, Wisconsin, Wyoming | P4: 99 | Q4: 95 | R4: 90 | S4: 85 | T4: 80 | U4: 75 | V4: 70 | W4: 65 | X4: 60 | Y4: 55 | Z4: 50 | AA4: 45 | AB4: 40

Sheet L-AAI-EZUL
A1: Row | B1: Service-Carrier ID | C1: Tier | D1: Types | E1: State Available | F1: Old Product name | G1: Sub-Name | H1: Sub-type | I1: Length | J1: Product Name Full | K1: Product Real | L1: All Vendor paycodes | M1: Product | N1: Criteria | O1: Notes | P1: Diamond | Q1: 95 | R1: 90 | S1: 85 | T1: 80 | U1: 75 | V1: 70 | W1: 65 | X1: 60 | Y1: 55 | Z1: 50 | AA1: 45
A2: 1 | B2: L-AAI-EZUL | C2: TBD | D2: Perm | E2: All Avail. | F2: EZ UL | G2: Target | H2: Term | I2: Lifetime | J2: EZ UL (Target) | K2: Yes | L2: Diamond, 95, 90, 85, 80, 75, 70, 65, 60, 55, 50, 45 | M2: EZ UL | N2: Sub type: Target | State: All Available | Type: Perm | P2: 99 | Q2: 95 | R2: 90 | S2: 85 | T2: 80 | U2: 75 | V2: 70 | W2: 65 | X2: 60 | Y2: 55 | Z2: 50 | AA2: 45
A3: 2 | B3: L-AAI-EZUL | C3: TBD | D3: Perm | E3: All Avail. | F3: Excess of Target | H3: UL | I3: Lifetime | J3: EZ UL (Excess of Target) | K3: No | L3: Diamond, 95, 90, 85, 80, 75, 70, 65, 60, 55, 50, 45 | M3: EZ UL | N3: Sub type: Excess of Target | State: All Available | Excess year: 1+ | Type: Perm | Q3: 2.5 | R3: 2.5 | S3: 2.5 | T3: 2.5 | U3: 2 | V3: 2 | W3: 2 | X3: 2 | Y3: 2 | Z3: 2 | AA3: 2
A4: 3 | B4: L-AAI-EZUL | C4: TBD | D4: Perm | E4: All Avail. | F4: Renewal Years 2-6 | H4: UL | I4: Lifetime | J4: EZ UL (Renewal Years 2-6) | K4: No | L4: Diamond, 95, 90, 85, 80, 75, 70, 65, 60, 55, 50, 45 | M4: EZ UL | N4: Renewal year: 2 to 6 | State: All Available | Q4: 2.5 | R4: 2.5 | S4: 2.5 | T4: 2.5 | U4: 2 | V4: 2 | W4: 2 | X4: 2 | Y4: 2 | Z4: 2 | AA4: 2

Sheet L-AAI-FE
A1: Row | B1: Service-Carrier ID | C1: Product Tier | D1: Types | E1: State Available | F1: Old Product name | G1: Sub-Name | H1: Sub-type | I1: Length | J1: Product Name Full | K1: Product Real | L1: All Vendor paycodes | M1: Product | N1: Criteria | O1: Notes | P1: Diamond | Q1: 115 | R1: 110 | S1: 105 | T1: 100 | U1: 95 | V1: 90 | W1: 85 | X1: 80 | Y1: 75 | Z1: 70 | AA1: 65 | AB1: 60 | AC1: 55 | AD1: 50 | AE1: 45
A2: 1 | B2: L-AAI-FE | C2: TBD | D2: Final Expense | E2: All Avail. | G2: Ages 0-79 | H2: FE | I2: 80 | J2: Immediate Death Benefit Age 0-79 | K2: Yes | L2: Diamond, 115, 110, 105, 100, 95, 90, 85, 80, 75, 70, 65, 60, 55, 50, 45 | M2: Immediate Death Benefit | N2: Issue age: 0 to 79 | State: All Available | P2: 119 | Q2: 115 | R2: 110 | S2: 105 | T2: 100 | U2: 95 | V2: 90 | W2: 85 | X2: 80 | Y2: 75 | Z2: 70 | AA2: 65 | AB2: 60 | AC2: 55 | AD2: 50 | AE2: 45
A3: 2 | B3: L-AAI-FE | C3: TBD | D3: Final Expense | E3: All Avail. | H3: FE | I3: 80 | J3: Immediate Death Benefit Age 0-79 (Renewal Years 2-10) | K3: No | L3: Diamond, 115, 110, 105, 100, 95, 90, 85, 80, 75, 70, 65, 60, 55, 50, 45 | M3: Immediate Death Benefit | N3: Issue age: 0 to 79 | Renewal year: 2 to 10 | State: All Available | Q3: 7 | R3: 6.75 | S3: 6.5 | T3: 6 | U3: 5.5 | V3: 5 | W3: 4.5 | X3: 4 | Y3: 3.5 | Z3: 3 | AA3: 2.5 | AB3: 2 | AC3: 1.5 | AD3: 1 | AE3: 0.5
A4: 3 | B4: L-AAI-FE | C4: TBD | D4: Final Expense | E4: All Avail. | G4: Ages 80-85 | H4: FE | I4: 6 | J4: Immediate Death Benefit Age 80-85 | K4: Yes | L4: Diamond, 115, 110, 105, 100, 95, 90, 85, 80, 75, 70, 65, 60, 55, 50, 45 | M4: Immediate Death Benefit | N4: Issue age: 80 to 85 | State: All Available | P4: 84 | Q4: 80 | R4: 75 | S4: 70 | T4: 65 | U4: 60 | V4: 55 | W4: 50 | X4: 45 | Y4: 40 | Z4: 35 | AA4: 30 | AB4: 25 | AC4: 20 | AD4: 15 | AE4: 10
A5: 4 | B5: L-AAI-FE | C5: TBD | D5: Final Expense | E5: All Avail. | H5: FE | I5: 6 | J5: Immediate Death Benefit Age 80-85 (Renewal Years 2-10) | K5: No | L5: Diamond, 115, 110, 105, 100, 95, 90, 85, 80, 75, 70, 65, 60, 55, 50, 45 | M5: Immediate Death Benefit | N5: Issue age: 80 to 85 | Renewal year: 2 to 10 | State: All Available | Q5: 5 | R5: 4.5 | S5: 4 | T5: 3 | U5: 2.75 | V5: 2.5 | W5: 2.25 | X5: 2 | Y5: 1.75 | Z5: 1.5 | AA5: 1.25 | AB5: 1 | AC5: 0.75 | AD5: 0.5 | AE5: 0.25
A6: 5 | B6: L-AAI-FE | C6: TBD | D6: Final Expense | E6: All Avail. | G6: Ages 0-79 | H6: FE | I6: 80 | J6: Return Of Premium Plan Age 0-79 | K6: Yes | L6: Diamond, 115, 110, 105, 100, 95, 90, 85, 80, 75, 70, 65, 60, 55, 50, 45 | M6: Return Of Premium Plan | N6: Issue age: 0 to 79 | State: All Available | P6: 104 | Q6: 100 | R6: 95 | S6: 90 | T6: 85 | U6: 80 | V6: 75 | W6: 70 | X6: 65 | Y6: 60 | Z6: 55 | AA6: 50 | AB6: 47.5 | AC6: 45 | AD6: 42.5 | AE6: 40
A7: 6 | B7: L-AAI-FE | C7: TBD | D7: Final Expense | E7: All Avail. | H7: FE | I7: 80 | J7: Return Of Premium Plan Age 0-79 (Renewal Years 2-10) | K7: No | L7: Diamond, 115, 110, 105, 100, 95, 90, 85, 80, 75, 70, 65, 60, 55, 50, 45 | M7: Return Of Premium Plan | N7: Issue age: 0 to 79 | Renewal year: 2 to 10 | State: All Available | Q7: 5.25 | R7: 4.75 | S7: 4 | T7: 3.25 | U7: 3 | V7: 2.75 | W7: 2.5 | X7: 2.25 | Y7: 2 | Z7: 1.75 | AA7: 1.5 | AB7: 1.25 | AC7: 1 | AD7: 0.75 | AE7: 0.5
A8: 7 | B8: L-AAI-FE | C8: TBD | D8: Final Expense | E8: All Avail. | G8: Ages 80-85 | H8: FE | I8: 6 | J8: Return Of Premium Plan Age 80-85 | K8: Yes | L8: Diamond, 115, 110, 105, 100, 95, 90, 85, 80, 75, 70, 65, 60, 55, 50, 45 | M8: Return Of Premium Plan | N8: Issue age: 80 to 85 | State: All Available | P8: 84 | Q8: 80 | R8: 75 | S8: 70 | T8: 65 | U8: 60 | V8: 55 | W8: 50 | X8: 45 | Y8: 40 | Z8: 35 | AA8: 30 | AB8: 25 | AC8: 20 | AD8: 15 | AE8: 10
A9: 8 | B9: L-AAI-FE | C9: TBD | D9: Final Expense | E9: All Avail. | H9: FE | I9: 6 | J9: Return Of Premium Plan Age 80-85 (Renewal Years 2-10) | K9: No | L9: Diamond, 115, 110, 105, 100, 95, 90, 85, 80, 75, 70, 65, 60, 55, 50, 45 | M9: Return Of Premium Plan | N9: Issue age: 80 to 85 | Renewal year: 2 to 10 | State: All Available | Q9: 5 | R9: 4.5 | S9: 4 | T9: 3.25 | U9: 3 | V9: 2.75 | W9: 2.5 | X9: 2.25 | Y9: 2 | Z9: 1.75 | AA9: 1.5 | AB9: 1.25 | AC9: 1 | AD9: 0.75 | AE9: 0.25
A10: 9 | B10: L-AAI-FE | C10: TBD | D10: Final Expense | E10: All Avail. | G10: Ages 0-79 | H10: FE | I10: 80 | J10: Graded Death Benefit Age 0-79 | K10: Yes | L10: Diamond, 115, 110, 105, 100, 95, 90, 85, 80, 75, 70, 65, 60, 55, 50, 45 | M10: Graded Death Benefit | N10: Issue age: 0 to 79 | State: All Available | P10: 104 | Q10: 100 | R10: 95 | S10: 90 | T10: 85 | U10: 80 | V10: 75 | W10: 70 | X10: 65 | Y10: 60 | Z10: 55 | AA10: 50 | AB10: 47.5 | AC10: 45 | AD10: 42.5 | AE10: 40
A11: 10 | B11: L-AAI-FE | C11: TBD | D11: Final Expense | E11: All Avail. | H11: FE | I11: 80 | J11: Graded Death Benefit Age 0-79 (Renewal Years 2-10) | K11: No | L11: Diamond, 115, 110, 105, 100, 95, 90, 85, 80, 75, 70, 65, 60, 55, 50, 45 | M11: Graded Death Benefit | N11: Issue age: 0 to 79 | Renewal year: 2 to 10 | State: All Available | Q11: 5.25 | R11: 4.75 | S11: 4 | T11: 3.25 | U11: 3 | V11: 2.75 | W11: 2.5 | X11: 2.25 | Y11: 2 | Z11: 1.75 | AA11: 1.5 | AB11: 1.25 | AC11: 1 | AD11: 0.75 | AE11: 0.25
A12: 11 | B12: L-AAI-FE | C12: TBD | D12: Final Expense | E12: All Avail. | G12: Ages 80-85 | H12: FE | I12: 6 | J12: Graded Death Benefit Age 80-85 | K12: Yes | L12: Diamond, 115, 110, 105, 100, 95, 90, 85, 80, 75, 70, 65, 60, 55, 50, 45 | M12: Graded Death Benefit | N12: Issue age: 80 to 85 | State: All Available | P12: 84 | Q12: 80 | R12: 75 | S12: 70 | T12: 65 | U12: 60 | V12: 55 | W12: 50 | X12: 45 | Y12: 40 | Z12: 35 | AA12: 30 | AB12: 25 | AC12: 20 | AD12: 15 | AE12: 10
A13: 12 | B13: L-AAI-FE | C13: TBD | D13: Final Expense | E13: All Avail. | H13: FE | I13: 6 | J13: Graded Death Benefit Age 80-85 (Renewal Years 2-10) | K13: No | L13: Diamond, 115, 110, 105, 100, 95, 90, 85, 80, 75, 70, 65, 60, 55, 50, 45 | M13: Graded Death Benefit | N13: Issue age: 80 to 85 | Renewal year: 2 to 10 | State: All Available | Q13: 5 | R13: 4.5 | S13: 4 | T13: 3.25 | U13: 3 | V13: 2.75 | W13: 2.5 | X13: 2.25 | Y13: 2 | Z13: 1.75 | AA13: 1.5 | AB13: 1.25 | AC13: 1 | AD13: 0.75 | AE13: 0.25

Sheet L-AAI-HP
A1: Row | B1: Service-Carrier ID | C1: Product Tier | D1: Types | E1: State Available | F1: Old Product name | G1: Sub-Name | H1: Sub-type | I1: Length | J1: Product Name Full | K1: Product Real | L1: All Vendor paycodes | M1: Product | N1: Criteria | O1: Notes | P1: Diamond | Q1: 110 | R1: 105 | S1: 100 | T1: 95 | U1: 90 | V1: 85 | W1: 80 | X1: 75 | Y1: 70 | Z1: 69 | AA1: 65 | AB1: 60 | AC1: 55 | AD1: 50 | AE1: 45 | AF1: 40 | AG1: 0
A2: 1 | B2: L-AAI-HP | C2: TBD | D2: Unique | E2: All Avail. | H2: TBD | I2: 20 | J2: Home Protector 20 Year | K2: Yes | L2: Diamond, 110, 105, 100, 95, 90, 85, 80, 75, 70, 69, 65, 60, 55, 50, 45, 40, 0 | M2: Home Protector | N2: Sub type: 20 | State: All Available | P2: 114 | Q2: 110 | R2: 105 | S2: 100 | T2: 95 | U2: 90 | V2: 85 | W2: 80 | X2: 75 | Y2: 70 | Z2: 69 | AA2: 65 | AB2: 60 | AC2: 55 | AD2: 50 | AE2: 45 | AF2: 40 | AG2: 0
A3: 2 | B3: L-AAI-HP | C3: TBD | D3: Unique | E3: All Avail. | H3: TBD | I3: 30 | J3: Home Protector 30 Year | K3: Yes | L3: Diamond, 110, 105, 100, 95, 90, 85, 80, 75, 70, 69, 65, 60, 55, 50, 45, 40, 0 | M3: Home Protector | N3: Sub type: 30 | State: All Available | P3: 114 | Q3: 110 | R3: 105 | S3: 100 | T3: 95 | U3: 90 | V3: 85 | W3: 80 | X3: 75 | Y3: 70 | Z3: 69 | AA3: 65 | AB3: 60 | AC3: 55 | AD3: 50 | AE3: 45 | AF3: 40 | AG3: 0

Sheet L-AAI-SP
A1: Row | B1: Service-Carrier ID | C1: Product Tier | D1: Types | E1: State Available | F1: Old Product name | G1: Sub-Name | H1: Sub-type | I1: Length | J1: Product Name Full | K1: Product Real | L1: All Vendor paycodes | M1: Product | N1: Criteria | O1: Notes | P1: Diamond | Q1: 125 | R1: 120 | S1: 115 | T1: 110 | U1: 105 | V1: 100 | W1: 95 | X1: 90 | Y1: 85 | Z1: 80 | AA1: 75 | AB1: 70 | AC1: 65 | AD1: 60 | AE1: 55
A2: 1 | B2: L-AAI-SP | C2: TBD | D2: Unique | E2: All Avail. | F2: Survivor Protector | H2: TBD | I2: Lifetime | J2: Survivor Protector | K2: Yes | L2: Diamond, 125, 120, 115, 110, 105, 100, 95, 90, 85, 80, 75, 70, 65, 60, 55 | M2: Survivor Protector | N2: State: All Available | P2: 129 | Q2: 125 | R2: 120 | S2: 115 | T2: 110 | U2: 105 | V2: 100 | W2: 95 | X2: 90 | Y2: 85 | Z2: 80 | AA2: 75 | AB2: 70 | AC2: 65 | AD2: 60 | AE2: 55

Sheet L-ALLZ
A1: Row | B1: Service-Carrier ID | C1: Product Tier | D1: Types | E1: State Available | F1: Old Product name | G1: Sub-Name | H1: Sub-type | I1: Length | J1: Product Name Full | K1: Product Real | L1: All Vendor paycodes | M1: Product | N1: Criteria | O1: Notes | P1: Diamond | Q1: 80 | R1: 75 | S1: 70 | T1: 65 | U1: 60 | V1: 55 | W1: 50 | X1: 45 | Y1: 40 | Z1: 35 | AA1: 30 | AB1: 25 | AC1: 20 | AD1: 15 | AE1: 10 | AF1: 5
A2: 1 | B2: L-ALLZ | C2: TBD | D2: Perm | E2: All Avail. | F2: Allianz Life Pro+ Advantage | G2: Option A | H2: IUL | I2: Lifetime | J2: Allianz Life Pro+ Advantage (Option A) | K2: Yes | L2: Diamond, 80, 75, 70, 65, 60, 55, 50, 45, 40, 35, 30, 25, 20, 15, 10, 5 | M2: Allianz Life Pro+ Advantage | N2: Sub type: Option A | State: All Available | P2: 124 | Q2: 100 | R2: 95 | S2: 90 | T2: 85 | U2: 80 | V2: 75 | W2: 70 | X2: 65 | Y2: 60 | Z2: 55 | AA2: 50 | AB2: 45 | AC2: 40 | AD2: 35 | AE2: 30 | AF2: 25
A3: 2 | B3: L-ALLZ | C3: TBD | D3: Perm | E3: All Avail. | F3: Year 1 Excess and Years 2-10 Target and Excess | G3: Option A | H3: IUL | I3: Lifetime | J3: Allianz Life Pro+ Advantage (A: Yr 1-10 Excess) | K3: No | L3: Diamond, 80, 75, 70, 65, 60, 55, 50, 45, 40, 35, 30, 25, 20, 15, 10, 5 | M3: Allianz Life Pro+ Advantage | N3: Excess year: 1 to 10 | Q3: 2.5 | R3: 1.75 | S3: 1.75 | T3: 1.25 | U3: 0.75 | V3: 0.75 | W3: 0.75 | X3: 0.75 | Y3: 0.75 | Z3: 0.5 | AA3: 0.5 | AB3: 0.5 | AC3: 0.5 | AD3: 0.5 | AE3: 0.5 | AF3: 0.5
A4: 3 | B4: L-ALLZ | C4: TBD | D4: Perm | E4: All Avail. | F4: Allianz Life Pro+ Advantage | G4: Option B | H4: IUL | I4: Lifetime | J4: Allianz Life Pro+ Advantage (Option B) | K4: Yes | L4: Diamond, 80, 75, 70, 65, 60, 55, 50, 45, 40, 35, 30, 25, 20, 15, 10, 5 | M4: Allianz Life Pro+ Advantage | N4: Sub type: Option B | State: All Available | P4: 52 | Q4: 50 | R4: 47.5 | S4: 45 | T4: 42.5 | U4: 40 | V4: 37.5 | W4: 35 | X4: 32.5 | Y4: 30 | Z4: 27.5 | AA4: 25 | AB4: 22.5 | AC4: 20 | AD4: 17.5 | AE4: 15 | AF4: 12.5
A5: 4 | B5: L-ALLZ | C5: TBD | D5: Perm | E5: All Avail. | F5: Year 1 Target Premium Years 2-6 | G5: Option B | H5: IUL | I5: Lifetime | J5: Allianz Life Pro+ Advantage (B: Target 1-6) | K5: No | L5: Diamond, 80, 75, 70, 65, 60, 55, 50, 45, 40, 35, 30, 25, 20, 15, 10, 5 | M5: Allianz Life Pro+ Advantage | N5: Sub type: Year 1 Target Premium Years 2-6 | Policy year: 2 to 6 | Q5: 13.5 | R5: 12.8 | S5: 12.1 | T5: 11.4 | U5: 10.7 | V5: 10 | W5: 9.3 | X5: 8.6 | Y5: 7.9 | Z5: 7.2 | AA5: 6.5 | AB5: 5.8 | AC5: 5.1 | AD5: 4.4 | AE5: 3.7 | AF5: 3
A6: 5 | B6: L-ALLZ | C6: TBD | D6: Perm | E6: All Avail. | F6: Year 1 Excess and Years 2-10 Target and Excess | G6: Option B | H6: IUL | I6: Lifetime | J6: Allianz Life Pro+ Advantage (B: Excess 1-10) | K6: No | L6: Diamond, 80, 75, 70, 65, 60, 55, 50, 45, 40, 35, 30, 25, 20, 15, 10, 5 | M6: Allianz Life Pro+ Advantage | N6: Excess year: 1 to 10 | Q6: 2.5 | R6: 1.75 | S6: 1.75 | T6: 1.25 | U6: 0.75 | V6: 0.75 | W6: 0.75 | X6: 0.75 | Y6: 0.75 | Z6: 0.5 | AA6: 0.5 | AB6: 0.5 | AC6: 0.5 | AD6: 0.5 | AE6: 0.5 | AF6: 0.5

Sheet L-ASSUR
A1: Row | B1: Service-Carrier ID | C1: Product Tier | D1: Types | E1: State Available | F1: Old Product name | G1: Sub-Name | H1: Sub-type | I1: Length | J1: Product Name Full | K1: Product Real | L1: All Vendor paycodes | M1: Product | N1: Criteria | O1: Notes | P1: Diamond | Q1: Level 18 | R1: Level 19 | S1: Level 20 | T1: Level 22 | U1: Level 24 | V1: Level 26 | W1: Level 28 | X1: Level 30 | Y1: Level 32 | Z1: Level 34 | AA1: Level 36 | AB1: Level 38 | AC1: Level 50
A2: 1 | B2: L-ASSUR | C2: TBD | D2: Perm | E2: All Avail. | H2: WL | I2: Lifetime | J2: Assurity Whole Life Pay for Life | K2: Yes | L2: Diamond, Level 18, Level 19, Level 20, Level 22, Level 24, Level 26, Level 28, Level 30, Level 32, Level 34, Level 36, Level 38, Level 50 | M2: Assurity Whole Life Pay for Life | O2: Type: Perm State: All Avail. Product Name: Assurity Whole Life Pay for Life | P2: 97 | Q2: 80 | R2: 77.5 | S2: 75 | T2: 72.5 | U2: 70 | V2: 67.5 | W2: 65 | X2: 62.5 | Y2: 60 | Z2: 57.5 | AA2: 55 | AB2: 52.5 | AC2: 50
A3: 2 | B3: L-ASSUR | C3: TBD | D3: Perm | E3: All Avail. | H3: WL | I3: Lifetime | J3: Assurity Whole Life Pay for Life (Years 2-5) | K3: No | L3: Diamond, Level 18, Level 19, Level 20, Level 22, Level 24, Level 26, Level 28, Level 30, Level 32, Level 34, Level 36, Level 38, Level 50 | M3: Years 2-5 | O3: Product Name: Years 2-5 | Q3: 6.5 | R3: 6.5 | S3: 6.25 | T3: 6.25 | U3: 6 | V3: 5.75 | W3: 5.5 | X3: 5.25 | Y3: 5 | Z3: 5 | AA3: 5 | AB3: 5 | AC3: 5
A4: 3 | B4: L-ASSUR | C4: TBD | D4: Perm | E4: All Avail. | H4: WL | I4: Lifetime | J4: Assurity Whole Life Pay for Life (Years 6-10) | K4: No | L4: Diamond, Level 18, Level 19, Level 20, Level 22, Level 24, Level 26, Level 28, Level 30, Level 32, Level 34, Level 36, Level 38, Level 50 | M4: Years 6-10 | O4: Product Name: Years 6-10 | Q4: 3.5 | R4: 3.5 | S4: 3.25 | T4: 3.25 | U4: 3 | V4: 2.75 | W4: 2.5 | X4: 2.25 | Y4: 2 | Z4: 2 | AA4: 2 | AB4: 2 | AC4: 2
A5: 4 | B5: L-ASSUR | C5: TBD | D5: Perm | E5: All Avail. | H5: WL | I5: Lifetime | J5: Assurity Whole Life Pay for Life (Years 11+) | K5: No | L5: Diamond, Level 18, Level 19, Level 20, Level 22, Level 24, Level 26, Level 28, Level 30, Level 32, Level 34, Level 36, Level 38, Level 50 | M5: Years 11+ | O5: Product Name: Years 11+ | Q5: 1 | R5: 1 | S5: 1 | T5: 1 | U5: 0.75 | V5: 0.75 | W5: 0.75 | X5: 0.75 | Y5: 0.5 | Z5: 0.5 | AA5: 0.5 | AB5: 0.5 | AC5: 0.5
A6: 5 | B6: L-ASSUR | C6: TBD | D6: Perm | E6: All Avail. | G6: Ages 0-45 | H6: WL | I6: Lifetime | J6: Assurity Whole Life Pay to Age 65 | K6: Yes | L6: Diamond, Level 18, Level 19, Level 20, Level 22, Level 24, Level 26, Level 28, Level 30, Level 32, Level 34, Level 36, Level 38, Level 50 | M6: Assurity Whole Life Pay to Age 65 | O6: Type: Perm State: All Avail. Product Name: Assurity Whole Life Pay to Age 65 Sub Name: Ages 0-45 | P6: 67 | Q6: 62.5 | R6: 60 | S6: 57.5 | T6: 55 | U6: 52.5 | V6: 50 | W6: 47.5 | X6: 45 | Y6: 42.5 | Z6: 40 | AA6: 37.5 | AB6: 35 | AC6: 32.5
A7: 6 | B7: L-ASSUR | C7: TBD | D7: Perm | E7: All Avail. | H7: WL | I7: Lifetime | J7: Assurity Whole Life Pay to Age 65 (Years 2-5) | K7: No | L7: Diamond, Level 18, Level 19, Level 20, Level 22, Level 24, Level 26, Level 28, Level 30, Level 32, Level 34, Level 36, Level 38, Level 50 | M7: Years 2-5 | O7: Product Name: Years 2-5 | Q7: 3.5 | R7: 3.5 | S7: 3.25 | T7: 3.25 | U7: 3 | V7: 2.75 | W7: 2.5 | X7: 2.25 | Y7: 2 | Z7: 2 | AA7: 2 | AB7: 2 | AC7: 2
A8: 7 | B8: L-ASSUR | C8: TBD | D8: Perm | E8: All Avail. | H8: WL | I8: Lifetime | J8: Assurity Whole Life Pay to Age 65 (Years 6+) | K8: No | L8: Diamond, Level 18, Level 19, Level 20, Level 22, Level 24, Level 26, Level 28, Level 30, Level 32, Level 34, Level 36, Level 38, Level 50 | M8: Years 6+ | O8: Product Name: Years 6+ | Q8: 1 | R8: 1 | S8: 1 | T8: 1 | U8: 0.75 | V8: 0.75 | W8: 0.75 | X8: 0.75 | Y8: 0.5 | Z8: 0.5 | AA8: 0.5 | AB8: 0.5 | AC8: 0.5
A9: 8 | B9: L-ASSUR | C9: TBD | D9: Perm | E9: All Avail. | G9: Ages 46-54 | H9: WL | I9: Lifetime | J9: Assurity Whole Life Pay to Age 65 | K9: Yes | L9: Diamond, Level 18, Level 19, Level 20, Level 22, Level 24, Level 26, Level 28, Level 30, Level 32, Level 34, Level 36, Level 38, Level 50 | M9: Assurity Whole Life Pay to Age 65 | O9: Type: Perm State: All Avail. Product Name: Assurity Whole Life Pay to Age 65 Sub Name: Ages 46-54 | P9: 37.5 | Q9: 37.5 | R9: 36 | S9: 34 | T9: 32 | U9: 30 | V9: 28 | W9: 26 | X9: 24 | Y9: 22 | Z9: 20 | AA9: 18 | AB9: 18 | AC9: 16
A10: 9 | B10: L-ASSUR | C10: TBD | D10: Perm | E10: All Avail. | H10: WL | I10: Lifetime | J10: Assurity Whole Life Pay to Age 65 (Renewals) | K10: No | L10: Diamond, Level 18, Level 19, Level 20, Level 22, Level 24, Level 26, Level 28, Level 30, Level 32, Level 34, Level 36, Level 38, Level 50 | M10: Renewals | O10: Product Name: Renewals | Q10: 1 | R10: 1 | S10: 1 | T10: 1 | U10: 0.75 | V10: 0.75 | W10: 0.75 | X10: 0.75 | Y10: 0.5 | Z10: 0.5 | AA10: 0.5 | AB10: 0.5 | AC10: 0.5
A11: 10 | B11: L-ASSUR | C11: TBD | D11: Perm | E11: All Avail. | H11: WL | I11: Lifetime | J11: Assurity Whole Life 20 Pay | K11: Yes | L11: Diamond, Level 18, Level 19, Level 20, Level 22, Level 24, Level 26, Level 28, Level 30, Level 32, Level 34, Level 36, Level 38, Level 50 | M11: Assurity Whole Life 20 Pay | O11: Type: Perm State: All Avail. Product Name: Assurity Whole Life 20 Pay | P11: 67 | Q11: 62.5 | R11: 60 | S11: 57.5 | T11: 55 | U11: 52.5 | V11: 50 | W11: 47.5 | X11: 45 | Y11: 42.5 | Z11: 40 | AA11: 37.5 | AB11: 35 | AC11: 32.5
A12: 11 | B12: L-ASSUR | C12: TBD | D12: Perm | E12: All Avail. | H12: WL | I12: Lifetime | J12: Assurity Whole Life 20 Pay (Years 2-5) | K12: No | L12: Diamond, Level 18, Level 19, Level 20, Level 22, Level 24, Level 26, Level 28, Level 30, Level 32, Level 34, Level 36, Level 38, Level 50 | M12: Years 2-5 | O12: Product Name: Years 2-5 | Q12: 3.5 | R12: 3.5 | S12: 3.25 | T12: 3.25 | U12: 3 | V12: 2.75 | W12: 2.5 | X12: 2.25 | Y12: 2 | Z12: 2 | AA12: 2 | AB12: 2 | AC12: 2
A13: 12 | B13: L-ASSUR | C13: TBD | D13: Perm | E13: All Avail. | H13: WL | I13: Lifetime | J13: Assurity Whole Life 20 Pay (Years 6+) | K13: No | L13: Diamond, Level 18, Level 19, Level 20, Level 22, Level 24, Level 26, Level 28, Level 30, Level 32, Level 34, Level 36, Level 38, Level 50 | M13: Years 6+ | O13: Product Name: Years 6+ | Q13: 1 | R13: 1 | S13: 1 | T13: 1 | U13: 0.75 | V13: 0.75 | W13: 0.75 | X13: 0.75 | Y13: 0.5 | Z13: 0.5 | AA13: 0.5 | AB13: 0.5 | AC13: 0.5
A14: 13 | B14: L-ASSUR | C14: TBD | D14: Perm | E14: All Avail. | H14: WL | I14: Lifetime | J14: Assurity Whole Life 10 Pay | K14: Yes | L14: Diamond, Level 18, Level 19, Level 20, Level 22, Level 24, Level 26, Level 28, Level 30, Level 32, Level 34, Level 36, Level 38, Level 50 | M14: Assurity Whole Life 10 Pay | O14: Type: Perm State: All Avail. Product Name: Assurity Whole Life 10 Pay | P14: 37.5 | Q14: 37.5 | R14: 36 | S14: 34 | T14: 32 | U14: 30 | V14: 28 | W14: 26 | X14: 24 | Y14: 22 | Z14: 20 | AA14: 18 | AB14: 18 | AC14: 16
A15: 14 | B15: L-ASSUR | C15: TBD | D15: Perm | E15: All Avail. | H15: WL | I15: Lifetime | J15: Assurity Whole Life 10 Pay (Renewals) | K15: No | L15: Diamond, Level 18, Level 19, Level 20, Level 22, Level 24, Level 26, Level 28, Level 30, Level 32, Level 34, Level 36, Level 38, Level 50 | M15: Renewals | O15: Product Name: Renewals | Q15: 1 | R15: 1 | S15: 1 | T15: 1 | U15: 0.75 | V15: 0.75 | W15: 0.75 | X15: 0.75 | Y15: 0.5 | Z15: 0.5 | AA15: 0.5 | AB15: 0.5 | AC15: 0.5
A16: 15 | B16: L-ASSUR | C16: TBD | D16: Perm | E16: All Avail. | H16: WL | I16: Lifetime | J16: Assurity Whole Life Paid Up Additions Rider | K16: No | L16: Diamond, Level 18, Level 19, Level 20, Level 22, Level 24, Level 26, Level 28, Level 30, Level 32, Level 34, Level 36, Level 38, Level 50 | M16: Assurity Whole Life Paid Up Additions Rider | O16: Type: Perm State: All Avail. Product Name: Assurity Whole Life Paid Up Additions Rider | P16: 2.5 | Q16: 2.5 | R16: 2.4 | S16: 2.4 | T16: 2.3 | U16: 2.2 | V16: 2.1 | W16: 2 | X16: 2 | Y16: 2 | Z16: 1.75 | AA16: 1.75 | AB16: 1.75 | AC16: 1.75
A17: 16 | B17: L-ASSUR | C17: TBD | D17: Perm | E17: All Avail. | H17: WL | I17: Lifetime | J17: Assurity Whole Life Paid Up Additions Rider (Renewals) | K17: No | L17: Diamond, Level 18, Level 19, Level 20, Level 22, Level 24, Level 26, Level 28, Level 30, Level 32, Level 34, Level 36, Level 38, Level 50 | M17: Renewals | O17: Product Name: Renewals | Q17: 2.5 | R17: 2.4 | S17: 2.4 | T17: 2.3 | U17: 2.2 | V17: 2.1 | W17: 2 | X17: 2 | Y17: 2 | Z17: 1.75 | AA17: 1.75 | AB17: 1.75 | AC17: 1.75
A18: 17 | B18: L-ASSUR | C18: TBD | D18: Term | E18: All Avail. | H18: Term | I18: 10 | J18: 10 Year Term | K18: Yes | L18: Diamond, Level 18, Level 19, Level 20, Level 22, Level 24, Level 26, Level 28, Level 30, Level 32, Level 34, Level 36, Level 38, Level 50 | M18: 10 Year Term | O18: Type: Term State: All Avail. Product Name: 10 Year Term | P18: 87 | Q18: 80 | R18: 75 | S18: 70 | T18: 65 | U18: 60 | V18: 55 | W18: 50 | X18: 45 | Y18: 40 | Z18: 35 | AA18: 30 | AB18: 25 | AC18: 20
A19: 18 | B19: L-ASSUR | C19: TBD | D19: Term | E19: All Avail. | H19: Term | I19: 10 | J19: 10 Year Term (Years 2-10) | K19: No | L19: Diamond, Level 18, Level 19, Level 20, Level 22, Level 24, Level 26, Level 28, Level 30, Level 32, Level 34, Level 36, Level 38, Level 50 | M19: Years 2-10 | O19: Product Name: Years 2-10 | Q19: 1 | R19: 1 | S19: 1 | T19: 1 | U19: 0.75 | V19: 0.75 | W19: 0.75 | X19: 0.5 | Y19: 0.5 | Z19: 0.5 | AA19: 0.25 | AB19: 0.25 | AC19: 0.25
A20: 19 | B20: L-ASSUR | C20: TBD | D20: Term | E20: All Avail. | H20: Term | I20: 15 | J20: 15 Year Term | K20: Yes | L20: Diamond, Level 18, Level 19, Level 20, Level 22, Level 24, Level 26, Level 28, Level 30, Level 32, Level 34, Level 36, Level 38, Level 50 | M20: 15 Year Term | O20: Type: Term State: All Avail. Product Name: 15 Year Term | P20: 92 | Q20: 85 | R20: 80 | S20: 75 | T20: 70 | U20: 65 | V20: 60 | W20: 55 | X20: 50 | Y20: 45 | Z20: 40 | AA20: 35 | AB20: 30 | AC20: 25
A21: 20 | B21: L-ASSUR | C21: TBD | D21: Term | E21: All Avail. | H21: Term | I21: 15 | J21: 15 Year Term (Years 2-10) | K21: No | L21: Diamond, Level 18, Level 19, Level 20, Level 22, Level 24, Level 26, Level 28, Level 30, Level 32, Level 34, Level 36, Level 38, Level 50 | M21: Years 2-10 | O21: Product Name: Years 2-10 | Q21: 1 | R21: 1 | S21: 1 | T21: 1 | U21: 0.75 | V21: 0.75 | W21: 0.75 | X21: 0.5 | Y21: 0.5 | Z21: 0.5 | AA21: 0.25 | AB21: 0.25 | AC21: 0.25
A22: 21 | B22: L-ASSUR | C22: TBD | D22: Term | E22: All Avail. | H22: Term | I22: 20 | J22: 20 Year Term | K22: Yes | L22: Diamond, Level 18, Level 19, Level 20, Level 22, Level 24, Level 26, Level 28, Level 30, Level 32, Level 34, Level 36, Level 38, Level 50 | M22: 20 Year Term | O22: Type: Term State: All Avail. Product Name: 20 and 30 Year Term | P22: 107 | Q22: 95 | R22: 90 | S22: 85 | T22: 80 | U22: 75 | V22: 70 | W22: 65 | X22: 60 | Y22: 55 | Z22: 50 | AA22: 45 | AB22: 40 | AC22: 35
A23: 22 | B23: L-ASSUR | C23: TBD | D23: Term | E23: All Avail. | H23: Term | I23: 20 | J23: 20 Year Term (Years 2-10) | K23: No | L23: Diamond, Level 18, Level 19, Level 20, Level 22, Level 24, Level 26, Level 28, Level 30, Level 32, Level 34, Level 36, Level 38, Level 50 | M23: Years 2-10 | O23: Product Name: Years 2-10 | Q23: 1 | R23: 1 | S23: 1 | T23: 1 | U23: 0.75 | V23: 0.75 | W23: 0.75 | X23: 0.5 | Y23: 0.5 | Z23: 0.5 | AA23: 0.25 | AB23: 0.25 | AC23: 0.25
A24: 23 | B24: L-ASSUR | C24: TBD | D24: Perm | E24: All Avail. | H24: SPWL | I24: Lifetime | J24: Assurity Single Premium Whole Life | K24: Yes | L24: Diamond, Level 18, Level 19, Level 20, Level 22, Level 24, Level 26, Level 28, Level 30, Level 32, Level 34, Level 36, Level 38, Level 50 | M24: Assurity Single Premium Whole Life | O24: Type: Perm State: All Avail. Product Name: Assurity Single Premium Whole Life | P24: 10 | Q24: 10 | R24: 10 | S24: 9.75 | T24: 9.5 | U24: 9.25 | V24: 9 | W24: 8.75 | X24: 8.5 | Y24: 8.5 | Z24: 8.5 | AA24: 8.5 | AB24: 8.5 | AC24: 8.5
A25: 24 | B25: L-ASSUR | C25: TBD | D25: Sing Prem | E25: All Avail. | H25: SPWL | I25: Lifetime | J25: Assurity Single Premium Whole Life (Single Premium Insurance Rider) | K25: No | L25: Diamond, Level 18, Level 19, Level 20, Level 22, Level 24, Level 26, Level 28, Level 30, Level 32, Level 34, Level 36, Level 38, Level 50 | M25: Single Premium Insurance Rider | O25: Type: Sing Prem State: All Avail. Product Name: Single Premium Insurance Rider | P25: 3.5 | Q25: 3.5 | R25: 3.5 | S25: 3 | T25: 3 | U25: 3 | V25: 3 | W25: 3 | X25: 3 | Y25: 3 | Z25: 3 | AA25: 3 | AB25: 3 | AC25: 3
A26: 25 | B26: L-ASSUR | C26: TBD | D26: Perm | E26: All Avail. | G26: Ages 0-75 | H26: UL | I26: Lifetime | J26: Assurity Universal Life | K26: Yes | L26: Diamond, Level 18, Level 19, Level 20, Level 22, Level 24, Level 26, Level 28, Level 30, Level 32, Level 34, Level 36, Level 38, Level 50 | M26: Assurity Universal Life | O26: Type: Perm State: All Avail. Product Name: Assurity Universal Life Sub Name: Ages 0-75 | P26: 97 | Q26: 85 | R26: 82.5 | S26: 80 | T26: 77.5 | U26: 75 | V26: 72.5 | W26: 70 | X26: 67.5 | Y26: 65 | Z26: 62.5 | AA26: 60 | AB26: 57.5 | AC26: 55
A27: 26 | B27: L-ASSUR | C27: TBD | D27: Perm | E27: All Avail. | H27: UL | I27: Lifetime | J27: Assurity Universal Life (Years 2-10) | K27: No | L27: Diamond, Level 18, Level 19, Level 20, Level 22, Level 24, Level 26, Level 28, Level 30, Level 32, Level 34, Level 36, Level 38, Level 50 | M27: Years 2-10 | O27: Product Name: Years 2-10 | Q27: 3 | R27: 3 | S27: 2.75 | T27: 2.75 | U27: 2.5 | V27: 2.25 | W27: 2 | X27: 1.75 | Y27: 1.5 | Z27: 1.5 | AA27: 1.5 | AB27: 1.5 | AC27: 1.5
A28: 27 | B28: L-ASSUR | C28: TBD | D28: Perm | E28: All Avail. | H28: UL | I28: Lifetime | J28: Assurity Universal Life (Years 11+) | K28: No | L28: Diamond, Level 18, Level 19, Level 20, Level 22, Level 24, Level 26, Level 28, Level 30, Level 32, Level 34, Level 36, Level 38, Level 50 | M28: Years 11+ | O28: Product Name: Years 11+ | Q28: 1 | R28: 1 | S28: 1 | T28: 1 | U28: 0.75 | V28: 0.75 | W28: 0.75 | X28: 0.75 | Y28: 0.5 | Z28: 0.5 | AA28: 0.5 | AB28: 0.5 | AC28: 0.5
A29: 28 | B29: L-ASSUR | C29: TBD | D29: Perm | E29: All Avail. | G29: Ages 76-80 | H29: UL | I29: Lifetime | J29: Assurity Universal Life | K29: Yes | L29: Diamond, Level 18, Level 19, Level 20, Level 22, Level 24, Level 26, Level 28, Level 30, Level 32, Level 34, Level 36, Level 38, Level 50 | M29: Assurity Universal Life | O29: Type: Perm State: All Avail. Product Name: Assurity Universal Life Sub Name: Ages 76-80 | P29: 57 | Q29: 55 | R29: 52.5 | S29: 50 | T29: 47.5 | U29: 45 | V29: 42.5 | W29: 40 | X29: 37.5 | Y29: 35 | Z29: 32.5 | AA29: 30 | AB29: 27.5 | AC29: 25
A30: 29 | B30: L-ASSUR | C30: TBD | D30: Perm | E30: All Avail. | H30: UL | I30: Lifetime | J30: Assurity Universal Life (Years 2-10) | K30: No | L30: Diamond, Level 18, Level 19, Level 20, Level 22, Level 24, Level 26, Level 28, Level 30, Level 32, Level 34, Level 36, Level 38, Level 50 | M30: Years 2-10 | O30: Product Name: Years 2-10 | Q30: 3 | R30: 3 | S30: 2.75 | T30: 2.75 | U30: 2.5 | V30: 2.25 | W30: 2 | X30: 1.75 | Y30: 1.5 | Z30: 1.5 | AA30: 1.5 | AB30: 1.5 | AC30: 1.5
A31: 30 | B31: L-ASSUR | C31: TBD | D31: Perm | E31: All Avail. | H31: UL | I31: Lifetime | J31: Assurity Universal Life (Years 11+) | K31: No | L31: Diamond, Level 18, Level 19, Level 20, Level 22, Level 24, Level 26, Level 28, Level 30, Level 32, Level 34, Level 36, Level 38, Level 50 | M31: Years 11+ | O31: Product Name: Years 11+ | Q31: 1 | R31: 1 | S31: 1 | T31: 1 | U31: 0.75 | V31: 0.75 | W31: 0.75 | X31: 0.75 | Y31: 0.5 | Z31: 0.5 | AA31: 0.5 | AB31: 0.5 | AC31: 0.5
A32: 31 | B32: L-ASSUR | C32: TBD | D32: Perm | E32: All Avail. | G32: Ages 81-85 | H32: UL | I32: Lifetime | J32: Assurity Universal Life | K32: Yes | L32: Diamond, Level 18, Level 19, Level 20, Level 22, Level 24, Level 26, Level 28, Level 30, Level 32, Level 34, Level 36, Level 38, Level 50 | M32: Assurity Universal Life | O32: Type: Perm State: All Avail. Product Name: Assurity Universal Life Sub Name: Ages 81-85 | P32: 37.5 | Q32: 37.5 | R32: 36 | S32: 34 | T32: 32 | U32: 30 | V32: 28 | W32: 26 | X32: 24 | Y32: 22 | Z32: 20 | AA32: 18 | AB32: 18 | AC32: 16
A33: 32 | B33: L-ASSUR | C33: TBD | D33: Perm | E33: All Avail. | H33: UL | I33: Lifetime | J33: Assurity Universal Life (Years 2-10) | K33: No | L33: Diamond, Level 18, Level 19, Level 20, Level 22, Level 24, Level 26, Level 28, Level 30, Level 32, Level 34, Level 36, Level 38, Level 50 | M33: Years 2-10 | O33: Product Name: Years 2-10 | Q33: 3 | R33: 3 | S33: 2.75 | T33: 2.75 | U33: 2.5 | V33: 2.25 | W33: 2 | X33: 1.75 | Y33: 1.5 | Z33: 1.5 | AA33: 1.5 | AB33: 1.5 | AC33: 1.5
A34: 33 | B34: L-ASSUR | C34: TBD | D34: Perm | E34: All Avail. | H34: UL | I34: Lifetime | J34: Assurity Universal Life (Years 11+) | K34: No | L34: Diamond, Level 18, Level 19, Level 20, Level 22, Level 24, Level 26, Level 28, Level 30, Level 32, Level 34, Level 36, Level 38, Level 50 | M34: Years 11+ | O34: Product Name: Years 11+ | Q34: 1 | R34: 1 | S34: 1 | T34: 1 | U34: 0.75 | V34: 0.75 | W34: 0.75 | X34: 0.75 | Y34: 0.5 | Z34: 0.5 | AA34: 0.5 | AB34: 0.5 | AC34: 0.5
A35: 34 | B35: L-ASSUR | C35: TBD | D35: Term | E35: All Avail. | H35: Term | I35: 30 | J35: 30 year Term | K35: Yes | L35: Diamond, Level 18, Level 19, Level 20, Level 22, Level 24, Level 26, Level 28, Level 30, Level 32, Level 34, Level 36, Level 38, Level 50 | M35: 30 Year Term | P35: 107 | Q35: 95 | R35: 90 | S35: 85 | T35: 80 | U35: 75 | V35: 70 | W35: 65 | X35: 60 | Y35: 55 | Z35: 50 | AA35: 45 | AB35: 40 | AC35: 35
A36: 35 | B36: L-ASSUR | C36: TBD | D36: Term | E36: All Avail. | H36: Term | I36: 30 | J36: 30 year Term (Years 2-10) | K36: No | L36: Diamond, Level 18, Level 19, Level 20, Level 22, Level 24, Level 26, Level 28, Level 30, Level 32, Level 34, Level 36, Level 38, Level 50 | M36: Years 2-10 | Q36: 1 | R36: 1 | S36: 1 | T36: 1 | U36: 0.75 | V36: 0.75 | W36: 0.75 | X36: 0.5 | Y36: 0.5 | Z36: 0.5 | AA36: 0.25 | AB36: 0.25 | AC36: 0.25

Sheet L-AXA
A1: Row | B1: Service-Carrier ID | C1: Product Tier | D1: Types | E1: State Available | F1: Old Product name | G1: Sub-Name | H1: Sub-type | I1: Length | J1: Product Name Full | K1: Product Real | L1: All Vendor paycodes | M1: Product | N1: Criteria | O1: Notes | P1: Diamond | Q1: Sch 90 | R1: Sch 85 | S1: Sch 80 | T1: Sch 75 | U1: Sch 70 | V1: Sch 65 | W1: Sch 60 | X1: Sch 55 | Y1: Sch 50 | Z1: 50 | AA1: 45 | AB1: 40
A2: 1 | B2: L-AXA | C2: TBD | I2: Lifetime | J2: IUL Protect | K2: Yes | L2: Diamond, Sch 90, Sch 85, Sch 80, Sch 75, Sch 70, Sch 65, Sch 60, Sch 55, Sch 50, 50, 45, 40 | M2: IUL Protect | O2: Type: Perm State: All Avail. Product Name: IUL Protect Sub Name: Series 160 | P2: 96 | Q2: 90 | R2: 85 | S2: 80 | T2: 75 | U2: 70 | V2: 65 | W2: 60 | X2: 55 | Y2: 50
A3: 2 | B3: L-AXA | C3: TBD | I3: Lifetime | J3: IUL Protect (Excess Year 1) | K3: No | L3: Diamond, Sch 90, Sch 85, Sch 80, Sch 75, Sch 70, Sch 65, Sch 60, Sch 55, Sch 50, 50, 45, 40 | M3: Excess Year 1 | O3: Product Name: Excess Year 1 | Q3: 2 | R3: 2 | S3: 2 | T3: 1.5 | U3: 1.5 | V3: 1.5 | W3: 1 | X3: 1 | Y3: 1
A4: 3 | B4: L-AXA | C4: TBD | I4: Lifetime | J4: IUL Protect (Years 2-10) | K4: No | L4: Diamond, Sch 90, Sch 85, Sch 80, Sch 75, Sch 70, Sch 65, Sch 60, Sch 55, Sch 50, 50, 45, 40 | M4: Years 2-10 | O4: Product Name: Years 2-10 | Q4: 1.5 | R4: 1.5 | S4: 1.5 | T4: 1.5 | U4: 1.5 | V4: 1.5 | W4: 1.5 | X4: 1.5 | Y4: 1.5
A5: 4 | B5: L-AXA | C5: TBD | I5: Lifetime | J5: IUL Protect w/ CVPlus | K5: Yes | L5: Diamond, Sch 90, Sch 85, Sch 80, Sch 75, Sch 70, Sch 65, Sch 60, Sch 55, Sch 50, 50, 45, 40 | M5: IUL Protect w/ CVPlus | O5: Type: Perm State: All Avail. Product Name: IUL Protect w/ CVPlus | P5: 24 | Q5: 24 | R5: 24 | S5: 24 | T5: 24 | U5: 24 | V5: 24 | W5: 24 | X5: 24 | Y5: 24
A6: 5 | B6: L-AXA | C6: TBD | I6: Lifetime | J6: IUL Protect w/ CVPlus (Excess Year 1) | K6: No | L6: Diamond, Sch 90, Sch 85, Sch 80, Sch 75, Sch 70, Sch 65, Sch 60, Sch 55, Sch 50, 50, 45, 40 | M6: Excess Year 1 | O6: Product Name: Excess Year 1 | Q6: 2 | R6: 1.5 | S6: 1.5 | T6: 1.5 | U6: 1.5 | V6: 1.5 | W6: 1.5 | X6: 1.5 | Y6: 1.5
A7: 6 | B7: L-AXA | C7: TBD | I7: Lifetime | J7: IUL Protect w/ CVPlus (Years 2-6*) | K7: No | L7: Diamond, Sch 90, Sch 85, Sch 80, Sch 75, Sch 70, Sch 65, Sch 60, Sch 55, Sch 50, 50, 45, 40 | M7: Years 2-6* | O7: Product Name: Years 2-6* | Q7: 4.7 | R7: 4.7 | S7: 4.7 | T7: 4.7 | U7: 4.7 | V7: 4.7 | W7: 4.7 | X7: 4.7 | Y7: 4.7
A8: 7 | B8: L-AXA | C8: TBD | I8: Lifetime | J8: IUL Protect w/ CVPlus (Years 2-10) | K8: No | L8: Diamond, Sch 90, Sch 85, Sch 80, Sch 75, Sch 70, Sch 65, Sch 60, Sch 55, Sch 50, 50, 45, 40 | M8: Years 2-10 | O8: Product Name: Years 2-10 | Q8: 1.5 | R8: 1.5 | S8: 1.5 | T8: 1.5 | U8: 1.5 | V8: 1.5 | W8: 1.5 | X8: 1.5 | Y8: 1.5
A9: 8 | B9: L-AXA | C9: TBD | I9: Lifetime | J9: BrightLife Grow | K9: Yes | L9: Diamond, Sch 90, Sch 85, Sch 80, Sch 75, Sch 70, Sch 65, Sch 60, Sch 55, Sch 50, 50, 45, 40 | M9: BrightLife Grow | O9: Type: Perm State: All Avail. Product Name: BrightLife Grow Sub Name: Series 159 | P9: 103 | Q9: 90 | R9: 85 | S9: 80 | T9: 75 | U9: 70 | V9: 65 | W9: 60 | X9: 55 | Y9: 50
A10: 9 | B10: L-AXA | C10: TBD | I10: Lifetime | J10: BrightLife Grow (Excess Year 1) | K10: No | L10: Diamond, Sch 90, Sch 85, Sch 80, Sch 75, Sch 70, Sch 65, Sch 60, Sch 55, Sch 50, 50, 45, 40 | M10: Excess Year 1 | O10: Product Name: Excess Year 1 | Q10: 2 | R10: 2 | S10: 2 | T10: 1.5 | U10: 1.5 | V10: 1.5 | W10: 1 | X10: 1 | Y10: 1
A11: 10 | B11: L-AXA | C11: TBD | I11: Lifetime | J11: BrightLife Grow (Years 2-10) | K11: No | L11: Diamond, Sch 90, Sch 85, Sch 80, Sch 75, Sch 70, Sch 65, Sch 60, Sch 55, Sch 50, 50, 45, 40 | M11: Years 2-10 | O11: Product Name: Years 2-10 | Q11: 1.5 | R11: 1.5 | S11: 1.5 | T11: 1.5 | U11: 1.5 | V11: 1.5 | W11: 1.5 | X11: 1.5 | Y11: 1.5
A12: 11 | B12: L-AXA | C12: TBD | I12: Lifetime | J12: BrightLife Grow w/CVPlus | K12: Yes | L12: Diamond, Sch 90, Sch 85, Sch 80, Sch 75, Sch 70, Sch 65, Sch 60, Sch 55, Sch 50, 50, 45, 40 | M12: BrightLife Grow w/CVPlus | O12: Type: Perm State: All Avail. Product Name: BrightLife Grow w/CVPlus | P12: 24 | Q12: 24 | R12: 24 | S12: 24 | T12: 24 | U12: 24 | V12: 24 | W12: 24 | X12: 24 | Y12: 24
A13: 12 | B13: L-AXA | C13: TBD | I13: Lifetime | J13: BrightLife Grow w/CVPlus (Excess Year 1) | K13: No | L13: Diamond, Sch 90, Sch 85, Sch 80, Sch 75, Sch 70, Sch 65, Sch 60, Sch 55, Sch 50, 50, 45, 40 | M13: Excess Year 1 | O13: Product Name: Excess Year 1 | Q13: 1.5 | R13: 1.5 | S13: 1.5 | T13: 1.5 | U13: 1.5 | V13: 1.5 | W13: 1.5 | X13: 1.5 | Y13: 1.5
A14: 13 | B14: L-AXA | C14: TBD | I14: Lifetime | J14: BrightLife Grow w/CVPlus (Years 2-6*) | K14: No | L14: Diamond, Sch 90, Sch 85, Sch 80, Sch 75, Sch 70, Sch 65, Sch 60, Sch 55, Sch 50, 50, 45, 40 | M14: Years 2-6* | O14: Product Name: Years 2-6* | Q14: 4.7 | R14: 4.7 | S14: 4.7 | T14: 4.7 | U14: 4.7 | V14: 4.7 | W14: 4.7 | X14: 4.7 | Y14: 4.7
A15: 14 | B15: L-AXA | C15: TBD | I15: Lifetime | J15: BrightLife Grow w/CVPlus (Years 2-10) | K15: No | L15: Diamond, Sch 90, Sch 85, Sch 80, Sch 75, Sch 70, Sch 65, Sch 60, Sch 55, Sch 50, 50, 45, 40 | M15: Years 2-10 | O15: Product Name: Years 2-10 | Q15: 1.5 | R15: 1.5 | S15: 1.5 | T15: 1.5 | U15: 1.5 | V15: 1.5 | W15: 1.5 | X15: 1.5 | Y15: 1.5
A16: 15 | B16: L-AXA | C16: TBD | I16: Lifetime | J16: VUL Legacy | K16: Yes | L16: Diamond, Sch 90, Sch 85, Sch 80, Sch 75, Sch 70, Sch 65, Sch 60, Sch 55, Sch 50, 50, 45, 40 | M16: VUL Legacy | O16: Type: Perm State: All Avail. Product Name: VUL Legacy Sub Name: Series 160 | P16: 93 | Q16: 90 | R16: 85 | S16: 80 | T16: 75 | U16: 70 | V16: 65 | W16: 60 | X16: 55 | Y16: 50
A17: 16 | B17: L-AXA | C17: TBD | I17: Lifetime | J17: VUL Legacy (Excess Year 1) | K17: No | L17: Diamond, Sch 90, Sch 85, Sch 80, Sch 75, Sch 70, Sch 65, Sch 60, Sch 55, Sch 50, 50, 45, 40 | M17: Excess Year 1 | O17: Product Name: Excess Year 1 | Q17: 2 | R17: 2 | S17: 2 | T17: 1.5 | U17: 1.5 | V17: 1.5 | W17: 1 | X17: 1 | Y17: 1
A18: 17 | B18: L-AXA | C18: TBD | I18: Lifetime | J18: VUL Legacy (Years 2-10) | K18: No | L18: Diamond, Sch 90, Sch 85, Sch 80, Sch 75, Sch 70, Sch 65, Sch 60, Sch 55, Sch 50, 50, 45, 40 | M18: Years 2-10 | O18: Product Name: Years 2-10 | Q18: 1.5 | R18: 1.5 | S18: 1.5 | T18: 1.5 | U18: 1.5 | V18: 1.5 | W18: 1.5 | X18: 1.5 | Y18: 1.5
A19: 18 | B19: L-AXA | C19: TBD | I19: Lifetime | J19: VUL Optimizer | K19: Yes | L19: Diamond, Sch 90, Sch 85, Sch 80, Sch 75, Sch 70, Sch 65, Sch 60, Sch 55, Sch 50, 50, 45, 40 | M19: VUL Optimizer | O19: Type: Perm State: All Avail. Product Name: VUL Optimizer Sub Name: Series 160 | P19: 99 | Q19: 90 | R19: 85 | S19: 80 | T19: 75 | U19: 70 | V19: 65 | W19: 60 | X19: 55 | Y19: 50
A20: 19 | B20: L-AXA | C20: TBD | I20: Lifetime | J20: VUL Optimizer (Excess Year 1) | K20: No | L20: Diamond, Sch 90, Sch 85, Sch 80, Sch 75, Sch 70, Sch 65, Sch 60, Sch 55, Sch 50, 50, 45, 40 | M20: Excess Year 1 | O20: Product Name: Excess Year 1 | Q20: 2 | R20: 2 | S20: 2 | T20: 1.5 | U20: 1.5 | V20: 1.5 | W20: 1 | X20: 1 | Y20: 1
A21: 20 | B21: L-AXA | C21: TBD | I21: Lifetime | J21: VUL Optimizer (Years 2-10) | K21: No | L21: Diamond, Sch 90, Sch 85, Sch 80, Sch 75, Sch 70, Sch 65, Sch 60, Sch 55, Sch 50, 50, 45, 40 | M21: Years 2-10 | O21: Product Name: Years 2-10 | Q21: 1.5 | R21: 1.5 | S21: 1.5 | T21: 1.5 | U21: 1.5 | V21: 1.5 | W21: 1.5 | X21: 1.5 | Y21: 1.5
A22: 21 | B22: L-AXA | C22: TBD | I22: Lifetime | J22: VUL Optimizer w/ CVPlus | K22: Yes | L22: Diamond, Sch 90, Sch 85, Sch 80, Sch 75, Sch 70, Sch 65, Sch 60, Sch 55, Sch 50, 50, 45, 40 | M22: VUL Optimizer w/ CVPlus | O22: Type: Perm State: All Avail. Product Name: VUL Optimizer w/ CVPlus Sub Name: Series 160 | P22: 40 | Q22: 40 | R22: 40 | S22: 40 | T22: 40 | U22: 40 | V22: 40 | W22: 40 | X22: 40 | Y22: 40
A23: 22 | B23: L-AXA | C23: TBD | I23: Lifetime | J23: VUL Optimizer w/ CVPlus (Excess Year 1) | K23: No | L23: Diamond, Sch 90, Sch 85, Sch 80, Sch 75, Sch 70, Sch 65, Sch 60, Sch 55, Sch 50, 50, 45, 40 | M23: Excess Year 1 | O23: Product Name: Excess Year 1 | Q23: 3 | R23: 3 | S23: 3 | T23: 3 | U23: 3 | V23: 3 | W23: 3 | X23: 3 | Y23: 3
A24: 23 | B24: L-AXA | C24: TBD | I24: Lifetime | J24: VUL Optimizer w/ CVPlus (Years 2-6*) | K24: No | L24: Diamond, Sch 90, Sch 85, Sch 80, Sch 75, Sch 70, Sch 65, Sch 60, Sch 55, Sch 50, 50, 45, 40 | M24: Years 2-6* | O24: Product Name: Years 2-6* | Q24: 1.5 | R24: 1.5 | S24: 1.5 | T24: 1.5 | U24: 1.5 | V24: 1.5 | W24: 1.5 | X24: 1.5 | Y24: 1.5
A25: 24 | B25: L-AXA | C25: TBD | I25: Lifetime | J25: VUL Optimizer w/ CVPlus (Years 2-10) | K25: No | L25: Diamond, Sch 90, Sch 85, Sch 80, Sch 75, Sch 70, Sch 65, Sch 60, Sch 55, Sch 50, 50, 45, 40 | M25: Years 2-10 | O25: Product Name: Years 2-10 | Q25: 1.5 | R25: 1.5 | S25: 1.5 | T25: 1.5 | U25: 1.5 | V25: 1.5 | W25: 1.5 | X25: 1.5 | Y25: 1.5
A26: 25 | B26: L-AXA | C26: TBD | I26: Lifetime | J26: VUL Survivorship | K26: Yes | L26: Diamond, Sch 90, Sch 85, Sch 80, Sch 75, Sch 70, Sch 65, Sch 60, Sch 55, Sch 50, 50, 45, 40 | M26: VUL Survivorship | O26: Type: Perm State: All Avail. Product Name: VUL Survivorship Sub Name: Series 160 | P26: 93 | Q26: 90 | R26: 85 | S26: 80 | T26: 75 | U26: 70 | V26: 65 | W26: 60 | X26: 55 | Y26: 50
A27: 26 | B27: L-AXA | C27: TBD | I27: Lifetime | J27: VUL Survivorship (Excess Year 1) | K27: No | L27: Diamond, Sch 90, Sch 85, Sch 80, Sch 75, Sch 70, Sch 65, Sch 60, Sch 55, Sch 50, 50, 45, 40 | M27: Excess Year 1 | O27: Product Name: Excess Year 1 | Q27: 2 | R27: 1 | S27: 2 | T27: 1.5 | U27: 1.5 | V27: 1.5 | W27: 1 | X27: 1 | Y27: 1
A28: 27 | B28: L-AXA | C28: TBD | I28: Lifetime | J28: VUL Survivorship (Years 2-10) | K28: No | L28: Diamond, Sch 90, Sch 85, Sch 80, Sch 75, Sch 70, Sch 65, Sch 60, Sch 55, Sch 50, 50, 45, 40 | M28: Years 2-10 | O28: Product Name: Years 2-10 | Q28: 1.5 | R28: 1.5 | S28: 1.5 | T28: 1.5 | U28: 1.5 | V28: 1.5 | W28: 1.5 | X28: 1.5 | Y28: 1.5
A29: 28 | B29: L-AXA | C29: TBD | I29: Lifetime | J29: VUL Survivorship w/ CVPlus | K29: Yes | L29: Diamond, Sch 90, Sch 85, Sch 80, Sch 75, Sch 70, Sch 65, Sch 60, Sch 55, Sch 50, 50, 45, 40 | M29: VUL Survivorship w/ CVPlus | O29: Type: Perm State: All Avail. Product Name: VUL Survivorship w/ CVPlus Sub Name: Series 160 | P29: 40 | Q29: 40 | R29: 40 | S29: 40 | T29: 40 | U29: 40 | V29: 40 | W29: 40 | X29: 40 | Y29: 40
A30: 29 | B30: L-AXA | C30: TBD | I30: Lifetime | J30: VUL Survivorship w/ CVPlus (Excess Year 1) | K30: No | L30: Diamond, Sch 90, Sch 85, Sch 80, Sch 75, Sch 70, Sch 65, Sch 60, Sch 55, Sch 50, 50, 45, 40 | M30: Excess Year 1 | O30: Product Name: Excess Year 1 | Q30: 2 | R30: 2 | S30: 2 | T30: 2 | U30: 2 | V30: 2 | W30: 2 | X30: 2 | Y30: 2
A31: 30 | B31: L-AXA | C31: TBD | I31: Lifetime | J31: VUL Survivorship w/ CVPlus (Years 2-6*) | K31: No | L31: Diamond, Sch 90, Sch 85, Sch 80, Sch 75, Sch 70, Sch 65, Sch 60, Sch 55, Sch 50, 50, 45, 40 | M31: Years 2-6* | O31: Product Name: Years 2-6* | Q31: 1.5 | R31: 1.5 | S31: 1.5 | T31: 1.5 | U31: 1.5 | V31: 1.5 | W31: 1.5 | X31: 1.5 | Y31: 1.5
A32: 31 | B32: L-AXA | C32: TBD | I32: Lifetime | J32: VUL Survivorship w/ CVPlus (Years 2-10) | K32: No | L32: Diamond, Sch 90, Sch 85, Sch 80, Sch 75, Sch 70, Sch 65, Sch 60, Sch 55, Sch 50, 50, 45, 40 | M32: Years 2-10 | O32: Product Name: Years 2-10 | Q32: 1.5 | R32: 1.5 | S32: 1.5 | T32: 1.5 | U32: 1.5 | V32: 1.5 | W32: 1.5 | X32: 1.5 | Y32: 1.5
A33: 32 | B33: L-AXA | C33: TBD | I33: ART | J33: Term ART | K33: Yes | L33: Diamond, Sch 90, Sch 85, Sch 80, Sch 75, Sch 70, Sch 65, Sch 60, Sch 55, Sch 50, 50, 45, 40 | M33: Term ART | O33: Type: Term State: All Avail. Product Name: Term ART Sub Name: Series 160 | P33: 71 | Q33: 70 | R33: 67.5 | S33: 65 | T33: 62.5 | U33: 60 | V33: 57.5 | W33: 55 | X33: 52.5 | Y33: 50
A34: 33 | B34: L-AXA | C34: TBD | I34: ART | J34: Term ART (Years 2-10) | K34: No | L34: Diamond, Sch 90, Sch 85, Sch 80, Sch 75, Sch 70, Sch 65, Sch 60, Sch 55, Sch 50, 50, 45, 40 | M34: Years 2-10 | O34: Product Name: Years 2-10 | Q34: 2.5 | R34: 2.25 | S34: 2 | T34: 1.75 | U34: 1.5 | V34: 1.5 | W34: 1.25 | X34: 1.25 | Y34: 1
A35: 34 | B35: L-AXA | C35: TBD | I35: 10 | J35: Term 10 year | K35: Yes | L35: Diamond, Sch 90, Sch 85, Sch 80, Sch 75, Sch 70, Sch 65, Sch 60, Sch 55, Sch 50, 50, 45, 40 | M35: Term 10 year | O35: Type: Term State: All Avail. Product Name: Term 10 year Sub Name: Series 160 | P35: 91 | Q35: 75 | R35: 72.5 | S35: 70 | T35: 67.5 | U35: 65 | V35: 62.5 | W35: 60 | X35: 57.5 | Y35: 55
A36: 35 | B36: L-AXA | C36: TBD | I36: 15 | J36: Term 15 year | K36: Yes | L36: Diamond, Sch 90, Sch 85, Sch 80, Sch 75, Sch 70, Sch 65, Sch 60, Sch 55, Sch 50, 50, 45, 40 | M36: Term 15 year | O36: Type: Term State: All Avail. Product Name: Term 15 year Sub Name: Series 160 | P36: 101 | Q36: 85 | R36: 82.5 | S36: 80 | T36: 77.5 | U36: 75 | V36: 72.5 | W36: 70 | X36: 67.5 | Y36: 65
A37: 36 | B37: L-AXA | C37: TBD | I37: 20 | J37: Term 20 year | K37: Yes | L37: Diamond, Sch 90, Sch 85, Sch 80, Sch 75, Sch 70, Sch 65, Sch 60, Sch 55, Sch 50, 50, 45, 40 | M37: Term 20 year | O37: Type: Term State: All Avail. Product Name: Term 20 year Sub Name: Series 160 | P37: 111 | Q37: 95 | R37: 92.5 | S37: 90 | T37: 87.5 | U37: 85 | V37: 82.5 | W37: 80 | X37: 77.5 | Y37: 75
A38: 37 | B38: L-AXA | C38: TBD | I38: Lifetime | J38: TermOne Ages 0-79 | K38: Yes | L38: Diamond, Sch 90, Sch 85, Sch 80, Sch 75, Sch 70, Sch 65, Sch 60, Sch 55, Sch 50, 50, 45, 40 | M38: TermOne Ages 0-79 | O38: Type: Term State: All Avail. Product Name: TermOne Ages 0-79 Sub Name: Series 160 | P38: 7 | Q38: 7 | R38: 7 | S38: 7 | T38: 7 | U38: 7 | V38: 7 | W38: 7 | X38: 7 | Y38: 7
A39: 38 | B39: L-AXA | C39: TBD | I39: Lifetime | J39: TermOne Ages 80+ | K39: Yes | L39: Diamond, Sch 90, Sch 85, Sch 80, Sch 75, Sch 70, Sch 65, Sch 60, Sch 55, Sch 50, 50, 45, 40 | M39: TermOne Ages 80+ | O39: Type: Term State: All Avail. Product Name: TermOne Ages 80+ Sub Name: Series 160 | P39: 3.5 | Q39: 3.5 | R39: 3.5 | S39: 3.5 | T39: 3.5 | U39: 3.5 | V39: 3.5 | W39: 3.5 | X39: 3.5 | Y39: 3.5

Sheet L-BALT-FE
A1: Row | B1: Service-Carrier ID | C1: Product Tier | D1: Types | E1: State Available | F1: Old Product name | G1: Sub-Name | H1: Sub-type | I1: Length | J1: Product Name Full | K1: Product Real | L1: All Vendor paycodes | M1: Product | N1: Criteria | O1: Notes | P1: Diamond | Q1: 115 | R1: 110 | S1: 105 | T1: 100 | U1: 95 | V1: 90 | W1: 85 | X1: 80 | Y1: 75 | Z1: 70 | AA1: 65 | AB1: 60 | AC1: 55 | AD1: 50 | AE1: 40
A2: 1 | B2: L-BALT-FE | C2: TBD | I2: Lifetime | J2: aPriority- Level Death Benefit (CPWL Life-pay) | K2: Yes | L2: Diamond, 115, 110, 105, 100, 95, 90, 85, 80, 75, 70, 65, 60, 55, 50, 40 | M2: aPriority- Level Death Benefit | N2: Sub type: CPWL: Life-pay | State: Alabama, Alaska, Arizona, Arkansas, California, Colorado, Connecticut, Delaware, Florida, Georgia, Hawaii, Idaho, Illinois, Indiana, Iowa, Kansas, Kentucky, Louisiana, Maine, Maryland, Massachusetts, Michigan, Minnesota, Mississippi, Missouri, Montana, Nebraska, Nevada, New Hampshire, New Jersey, New Mexico, North Carolina, North Dakota, Ohio, Oklahoma, Oregon, Pennsylvania, Rhode Island, South Carolina, South Dakota, Tennessee, Texas, Utah, Vermont, Virginia, Washington, West Virginia, Wisconsin, Wyoming | P2: 115 | Q2: 110 | R2: 105 | S2: 100 | T2: 95 | U2: 90 | V2: 85 | W2: 80 | X2: 75 | Y2: 70 | Z2: 65 | AA2: 60 | AB2: 55 | AC2: 50 | AD2: 40 | AE2: 40
A3: 2 | B3: L-BALT-FE | C3: TBD | I3: Lifetime | J3: aPriority- Level Death Benefit (CPWL Life-pay) (Renewal Years 2-10) | K3: No | L3: Diamond, 115, 110, 105, 100, 95, 90, 85, 80, 75, 70, 65, 60, 55, 50, 40 | M3: aPriority- Level Death Benefit | N3: Renewal year: 2 to 10 | State: Alabama, Alaska, Arizona, Arkansas, California, Colorado, Connecticut, Delaware, Florida, Georgia, Hawaii, Idaho, Illinois, Indiana, Iowa, Kansas, Kentucky, Louisiana, Maine, Maryland, Massachusetts, Michigan, Minnesota, Mississippi, Missouri, Montana, Nebraska, Nevada, New Hampshire, New Jersey, New Mexico, North Carolina, North Dakota, Ohio, Oklahoma, Oregon, Pennsylvania, Rhode Island, South Carolina, South Dakota, Tennessee, Texas, Utah, Vermont, Virginia, Washington, West Virginia, Wisconsin, Wyoming | Q3: 5 | R3: 4.5 | S3: 4 | T3: 3.5 | U3: 3 | V3: 2.5 | W3: 2 | X3: 2 | Y3: 2 | Z3: 1 | AA3: 1 | AB3: 0 | AC3: 0 | AD3: 0 | AE3: 0
A4: 3 | B4: L-BALT-FE | C4: TBD | I4: Lifetime | J4: aPriority- Level Death Benefit (CPWL Life-pay) (Renewal Years 11+) | K4: No | L4: Diamond, 115, 110, 105, 100, 95, 90, 85, 80, 75, 70, 65, 60, 55, 50, 40 | M4: aPriority- Level Death Benefit | N4: Renewal year: 11+ | State: Alabama, Alaska, Arizona, Arkansas, California, Colorado, Connecticut, Delaware, Florida, Georgia, Hawaii, Idaho, Illinois, Indiana, Iowa, Kansas, Kentucky, Louisiana, Maine, Maryland, Massachusetts, Michigan, Minnesota, Mississippi, Missouri, Montana, Nebraska, Nevada, New Hampshire, New Jersey, New Mexico, North Carolina, North Dakota, Ohio, Oklahoma, Oregon, Pennsylvania, Rhode Island, South Carolina, South Dakota, Tennessee, Texas, Utah, Vermont, Virginia, Washington, West Virginia, Wisconsin, Wyoming | Q4: 0 | R4: 0 | S4: 0 | T4: 0 | U4: 0 | V4: 0 | W4: 0 | X4: 0 | Y4: 0 | Z4: 0 | AA4: 0 | AB4: 0 | AC4: 0 | AD4: 0 | AE4: 0
A5: 4 | B5: L-BALT-FE | C5: TBD | I5: Lifetime | J5: aPriority- Level Death Benefit (CPWL 20-pay) | K5: Yes | L5: Diamond, 115, 110, 105, 100, 95, 90, 85, 80, 75, 70, 65, 60, 55, 50, 40 | M5: aPriority- Level Death Benefit | N5: Sub type: CPWL: 20-pay | State: Alabama, Alaska, Arizona, Arkansas, California, Colorado, Connecticut, Delaware, Florida, Georgia, Hawaii, Idaho, Illinois, Indiana, Iowa, Kansas, Kentucky, Louisiana, Maine, Maryland, Massachusetts, Michigan, Minnesota, Mississippi, Missouri, Montana, Nebraska, Nevada, New Hampshire, New Jersey, New Mexico, North Carolina, North Dakota, Ohio, Oklahoma, Oregon, Pennsylvania, Rhode Island, South Carolina, South Dakota, Tennessee, Texas, Utah, Vermont, Virginia, Washington, West Virginia, Wisconsin, Wyoming | P5: 115 | Q5: 110 | R5: 105 | S5: 100 | T5: 95 | U5: 90 | V5: 85 | W5: 80 | X5: 75 | Y5: 70 | Z5: 65 | AA5: 60 | AB5: 55 | AC5: 50 | AD5: 40 | AE5: 40
A6: 5 | B6: L-BALT-FE | C6: TBD | I6: Lifetime | J6: aPriority- Level Death Benefit (CPWL 20-pay) (Renewal Years 2-10) | K6: No | L6: Diamond, 115, 110, 105, 100, 95, 90, 85, 80, 75, 70, 65, 60, 55, 50, 40 | M6: aPriority- Level Death Benefit | N6: Renewal year: 2 to 10 | State: Alabama, Alaska, Arizona, Arkansas, California, Colorado, Connecticut, Delaware, Florida, Georgia, Hawaii, Idaho, Illinois, Indiana, Iowa, Kansas, Kentucky, Louisiana, Maine, Maryland, Massachusetts, Michigan, Minnesota, Mississippi, Missouri, Montana, Nebraska, Nevada, New Hampshire, New Jersey, New Mexico, North Carolina, North Dakota, Ohio, Oklahoma, Oregon, Pennsylvania, Rhode Island, South Carolina, South Dakota, Tennessee, Texas, Utah, Vermont, Virginia, Washington, West Virginia, Wisconsin, Wyoming | Q6: 5 | R6: 4.5 | S6: 4 | T6: 3.5 | U6: 3 | V6: 2.5 | W6: 2 | X6: 2 | Y6: 2 | Z6: 1 | AA6: 1 | AB6: 0 | AC6: 0 | AD6: 0 | AE6: 0
A7: 6 | B7: L-BALT-FE | C7: TBD | I7: Lifetime | J7: aPriority- Level Death Benefit (CPWL 20-pay) (Renewal Years 11+) | K7: No | L7: Diamond, 115, 110, 105, 100, 95, 90, 85, 80, 75, 70, 65, 60, 55, 50, 40 | M7: aPriority- Level Death Benefit | N7: Renewal year: 11+ | State: Alabama, Alaska, Arizona, Arkansas, California, Colorado, Connecticut, Delaware, Florida, Georgia, Hawaii, Idaho, Illinois, Indiana, Iowa, Kansas, Kentucky, Louisiana, Maine, Maryland, Massachusetts, Michigan, Minnesota, Mississippi, Missouri, Montana, Nebraska, Nevada, New Hampshire, New Jersey, New Mexico, North Carolina, North Dakota, Ohio, Oklahoma, Oregon, Pennsylvania, Rhode Island, South Carolina, South Dakota, Tennessee, Texas, Utah, Vermont, Virginia, Washington, West Virginia, Wisconsin, Wyoming | Q7: 0 | R7: 0 | S7: 0 | T7: 0 | U7: 0 | V7: 0 | W7: 0 | X7: 0 | Y7: 0 | Z7: 0 | AA7: 0 | AB7: 0 | AC7: 0 | AD7: 0 | AE7: 0
A8: 7 | B8: L-BALT-FE | C8: TBD | I8: Lifetime | J8: SilverGuard- Level | K8: Yes | L8: Diamond, 115, 110, 105, 100, 95, 90, 85, 80, 75, 70, 65, 60, 55, 50, 40 | M8: SilverGuard- Level | N8: Sub type: Final Expense | P8: 115 | Q8: 115 | R8: 110 | S8: 105 | T8: 100 | U8: 95 | V8: 90 | W8: 85 | X8: 80 | Y8: 75 | Z8: 70 | AA8: 65 | AB8: 60 | AC8: 55 | AD8: 50 | AE8: 40

Sheet L-BALT-WL
A1: Row | B1: Service-Carrier ID | C1: Product Tier | D1: Types | E1: State Available | F1: Old Product name | G1: Sub-Name | H1: Sub-type | I1: Length | J1: Product Name Full | K1: Product Real | L1: All Vendor paycodes | M1: Product | N1: Criteria | O1: Notes | P1: Diamond | Q1: SPWL14 | R1: SPWL13.5 | S1: SPWL13 | T1: SPWL12.5 | U1: SPWL12 | V1: SPWL11.5 | W1: SPWL11 | X1: SPWL10.5 | Y1: SPWL10 | Z1: SPWL9.5 | AA1: SPWL9 | AB1: SPWL8.5 | AC1: SPWL8 | AD1: SPWL7.5 | AE1: SPWL7 | AF1: SPWL6.5 | AG1: SPWL6
A2: 1 | B2: L-BALT-WL | C2: TBD | I2: Lifetime | J2: SPWL & Generations Legacy (Ages 50-80) | K2: Yes | L2: Diamond, SPWL14, SPWL13.5, SPWL13, SPWL12.5, SPWL12, SPWL11.5, SPWL11, SPWL10.5, SPWL10, SPWL9.5, SPWL9, SPWL8.5, SPWL8, SPWL7.5, SPWL7, SPWL6.5, SPWL6 | M2: SPWL & Generations Legacy | N2: Sub type: Single Premium Whole Life | Issue age: 50 to 80 | State: Alabama, Alaska, Arizona, Arkansas, California, Colorado, Connecticut, Delaware, Florida, Georgia, Hawaii, Idaho, Illinois, Indiana, Iowa, Kansas, Kentucky, Louisiana, Maine, Maryland, Massachusetts, Michigan, Minnesota, Mississippi, Missouri, Montana, Nebraska, Nevada, New Hampshire, New Jersey, New Mexico, North Carolina, North Dakota, Ohio, Oklahoma, Oregon, Pennsylvania, Rhode Island, South Carolina, South Dakota, Tennessee, Texas, Utah, Vermont, Virginia, Washington, West Virginia, Wisconsin, Wyoming | P2: 14.5 | Q2: 14 | R2: 13.5 | S2: 13 | T2: 12.5 | U2: 12 | V2: 11.5 | W2: 11 | X2: 10.5 | Y2: 10 | Z2: 9.5 | AA2: 9 | AB2: 8.5 | AC2: 8 | AD2: 7.5 | AE2: 7 | AF2: 6.5 | AG2: 6
A3: 2 | B3: L-BALT-WL | C3: TBD | I3: Lifetime | J3: SPWL & Generations Legacy (Ages 81-85) | K3: No | L3: Diamond, SPWL14, SPWL13.5, SPWL13, SPWL12.5, SPWL12, SPWL11.5, SPWL11, SPWL10.5, SPWL10, SPWL9.5, SPWL9, SPWL8.5, SPWL8, SPWL7.5, SPWL7, SPWL6.5, SPWL6 | M3: SPWL & Generations Legacy | N3: Sub type: Single Premium Whole Life | Issue age: 81 to 85 | State: Alabama, Alaska, Arizona, Arkansas, California, Colorado, Connecticut, Delaware, Florida, Georgia, Hawaii, Idaho, Illinois, Indiana, Iowa, Kansas, Kentucky, Louisiana, Maine, Maryland, Massachusetts, Michigan, Minnesota, Mississippi, Missouri, Montana, Nebraska, Nevada, New Hampshire, New Jersey, New Mexico, North Carolina, North Dakota, Ohio, Oklahoma, Oregon, Pennsylvania, Rhode Island, South Carolina, South Dakota, Tennessee, Texas, Utah, Vermont, Virginia, Washington, West Virginia, Wisconsin, Wyoming | Q3: 7 | R3: 6.75 | S3: 6.5 | T3: 6.25 | U3: 6 | V3: 5.75 | W3: 5.5 | X3: 5.25 | Y3: 5 | Z3: 4.75 | AA3: 4.5 | AB3: 4.25 | AC3: 4 | AD3: 3.75

Sheet L-BALT-T
A1: Row | B1: Service-Carrier ID | C1: Product Tier | D1: Types | E1: State Available | F1: Old Product name | G1: Sub-Name | H1: Sub-type | I1: Length | J1: Product Name Full | K1: Product Real | L1: All Vendor paycodes | M1: Product | N1: Criteria | O1: Notes | P1: Diamond | Q1: 60 | R1: 55 | S1: 50 | T1: 45 | U1: 40
I2: Lifetime | J2: Term- aPriority | K2: Yes | L2: Diamond, 60, 55, 50, 45, 40 | M2: Term- aPriority | P2: 64 | Q2: 60 | R2: 55 | S2: 50 | T2: 45 | U2: 40
I3: Lifetime | J3: Term- Protector | K3: Yes | L3: Diamond, 60, 55, 50, 45, 40 | M3: Term- Protector | P3: 64 | Q3: 60 | R3: 55 | S3: 50 | T3: 45 | U3: 40

Sheet L-BANNR
A1: Row | B1: Service-Carrier ID | C1: Product Tier | D1: Types | E1: State Available | F1: Old Product name | G1: Sub-Name | H1: Sub-type | I1: Length | J1: Product Name Full | K1: Product Real | L1: All Vendor paycodes | M1: Product | N1: Criteria | O1: Notes | P1: Diamond | Q1: BEGA-1 | R1: AB90 | S1: AB85 | T1: AB80 | U1: AB75 | V1: AB70 | W1: AB65 | X1: AB60 | Y1: BMGA85 | Z1: BMGA80 | AA1: BMGA75 | AB1: BMGA70 | AC1: BMGA65 | AD1: BMGA60 | AE1: BMGA90 | AF1: BEGA90 | AG1: BEGA85 | AH1: BEGA80 | AI1: BEGA75 | AJ1: BEGA70 | AK1: BDGA90 | AL1: BDGA85 | AM1: BDGA80 | AN1: BDGA75 | AO1: BDGA70 | AP1: BDGA65 | AQ1: BDGA60
A2: 1 | B2: L-BANNR | C2: TBD | D2: Perm | E2: All Avail. | G2: 1st Year | H2: UL | I2: Lifetime | J2: Life Step UL | K2: Yes | L2: Diamond, BEGA-1, AB90, AB85, AB80, AB75, AB70, AB65, AB60, BMGA85, BMGA80, BMGA75, BMGA70, BMGA65, BMGA60, BMGA90, BEGA90, BEGA85, BEGA80, BEGA75, BEGA70, BDGA90, BDGA85, BDGA80, BDGA75, BDGA70, BDGA65, BDGA60 | M2: Life Step UL | N2: State: All Available | Policy year: 1 | P2: 89.2 | Q2: 80 | R2: 75 | S2: 70 | T2: 65 | U2: 60 | V2: 55 | W2: 50 | X2: 45 | Y2: 70 | Z2: 65 | AA2: 60 | AB2: 55 | AC2: 50 | AD2: 45 | AE2: 75 | AF2: 75 | AG2: 70 | AH2: 65 | AI2: 60 | AJ2: 55 | AK2: 75 | AL2: 70 | AM2: 65 | AN2: 60 | AO2: 55 | AP2: 50 | AQ2: 45
A3: 2 | B3: L-BANNR | C3: TBD | D3: Perm | E3: All Avail. | H3: UL | I3: Lifetime | J3: Life Step UL | K3: No | L3: Diamond, BEGA-1, AB90, AB85, AB80, AB75, AB70, AB65, AB60, BMGA85, BMGA80, BMGA75, BMGA70, BMGA65, BMGA60, BMGA90, BEGA90, BEGA85, BEGA80, BEGA75, BEGA70, BDGA90, BDGA85, BDGA80, BDGA75, BDGA70, BDGA65, BDGA60 | M3: Life Step UL | N3: Renewal year: 2 to 5 | State: All Available | Q3: 3 | R3: 2 | S3: 2 | T3: 2 | U3: 2 | V3: 2 | W3: 2 | X3: 2 | Y3: 3 | Z3: 3 | AA3: 3 | AB3: 3 | AC3: 3 | AD3: 3 | AE3: 3 | AF3: 3 | AG3: 3 | AH3: 3 | AI3: 3 | AJ3: 3 | AK3: 2.5 | AL3: 2.5 | AM3: 2.5 | AN3: 2.5 | AO3: 2.5 | AP3: 2.5 | AQ3: 2.5
A4: 3 | B4: L-BANNR | C4: TBD | D4: Perm | E4: All Avail. | H4: UL | I4: Lifetime | J4: Life Step UL | K4: No | L4: Diamond, BEGA-1, AB90, AB85, AB80, AB75, AB70, AB65, AB60, BMGA85, BMGA80, BMGA75, BMGA70, BMGA65, BMGA60, BMGA90, BEGA90, BEGA85, BEGA80, BEGA75, BEGA70, BDGA90, BDGA85, BDGA80, BDGA75, BDGA70, BDGA65, BDGA60 | M4: Life Step UL | N4: Renewal year: 6 to 10 | State: All Available | Q4: 3 | R4: 2 | S4: 2 | T4: 2 | U4: 2 | V4: 2 | W4: 2 | X4: 2 | Y4: 3 | Z4: 3 | AA4: 3 | AB4: 3 | AC4: 3 | AD4: 3 | AE4: 3 | AF4: 3 | AG4: 3 | AH4: 3 | AI4: 3 | AJ4: 3 | AK4: 2.5 | AL4: 2.5 | AM4: 2.5 | AN4: 2.5 | AO4: 2.5 | AP4: 2.5 | AQ4: 2.5
A5: 4 | B5: L-BANNR | C5: TBD | D5: Term | E5: All Avail. | G5: 1st Year | H5: Term | I5: 10 | J5: OPTerm 10 | K5: Yes | L5: Diamond, BEGA-1, AB90, AB85, AB80, AB75, AB70, AB65, AB60, BMGA85, BMGA80, BMGA75, BMGA70, BMGA65, BMGA60, BMGA90, BEGA90, BEGA85, BEGA80, BEGA75, BEGA70, BDGA90, BDGA85, BDGA80, BDGA75, BDGA70, BDGA65, BDGA60 | M5: OPTerm 10 | N5: Sub type: 10 Year Term | P5: 96.4 | Q5: 85 | R5: 80 | S5: 75 | T5: 70 | U5: 65 | V5: 60 | W5: 55 | X5: 50 | Y5: 75 | Z5: 70 | AA5: 65 | AB5: 60 | AC5: 55 | AD5: 50 | AE5: 80 | AF5: 80 | AG5: 75 | AH5: 70 | AI5: 65 | AJ5: 60 | AK5: 80 | AL5: 75 | AM5: 70 | AN5: 65 | AO5: 60 | AP5: 55 | AQ5: 50
A6: 5 | B6: L-BANNR | C6: TBD | D6: Term | E6: All Avail. | G6: 1st Year | H6: Term | I6: 15 | J6: OPTerm 15 | K6: Yes | L6: Diamond, BEGA-1, AB90, AB85, AB80, AB75, AB70, AB65, AB60, BMGA85, BMGA80, BMGA75, BMGA70, BMGA65, BMGA60, BMGA90, BEGA90, BEGA85, BEGA80, BEGA75, BEGA70, BDGA90, BDGA85, BDGA80, BDGA75, BDGA70, BDGA65, BDGA60 | M6: OPTerm 15 | N6: Sub type: 15 Year Term | P6: 110.8 | Q6: 95 | R6: 90 | S6: 85 | T6: 80 | U6: 75 | V6: 70 | W6: 65 | X6: 60 | Y6: 85 | Z6: 80 | AA6: 75 | AB6: 70 | AC6: 65 | AD6: 60 | AE6: 90 | AF6: 90 | AG6: 85 | AH6: 80 | AI6: 75 | AJ6: 70 | AK6: 90 | AL6: 85 | AM6: 80 | AN6: 75 | AO6: 70 | AP6: 65 | AQ6: 60
A7: 6 | B7: L-BANNR | C7: TBD | D7: Term | E7: All Avail. | G7: 1st Year | H7: Term | I7: 20 | J7: OPTerm 20 | K7: Yes | L7: Diamond, BEGA-1, AB90, AB85, AB80, AB75, AB70, AB65, AB60, BMGA85, BMGA80, BMGA75, BMGA70, BMGA65, BMGA60, BMGA90, BEGA90, BEGA85, BEGA80, BEGA75, BEGA70, BDGA90, BDGA85, BDGA80, BDGA75, BDGA70, BDGA65, BDGA60 | M7: OPTerm 20 | N7: Sub type: 20 Year Term | P7: 118 | Q7: 100 | R7: 95 | S7: 90 | T7: 85 | U7: 80 | V7: 75 | W7: 70 | X7: 65 | Y7: 90 | Z7: 85 | AA7: 80 | AB7: 75 | AC7: 70 | AD7: 65 | AE7: 95 | AF7: 95 | AG7: 90 | AH7: 85 | AI7: 80 | AJ7: 75 | AK7: 95 | AL7: 90 | AM7: 85 | AN7: 80 | AO7: 75 | AP7: 70 | AQ7: 65
I8: 25 | J8: OPTerm 25 | K8: Yes | L8: Diamond, BEGA-1, AB90, AB85, AB80, AB75, AB70, AB65, AB60, BMGA85, BMGA80, BMGA75, BMGA70, BMGA65, BMGA60, BMGA90, BEGA90, BEGA85, BEGA80, BEGA75, BEGA70, BDGA90, BDGA85, BDGA80, BDGA75, BDGA70, BDGA65, BDGA60 | M8: OPTerm 25 | N8: Sub type: 25 Year Term | P8: 118 | Q8: 100 | R8: 95 | S8: 90 | T8: 85 | U8: 80 | V8: 75 | W8: 70 | X8: 65 | Y8: 90 | Z8: 85 | AA8: 80 | AB8: 75 | AC8: 70 | AD8: 65 | AE8: 95 | AF8: 95 | AG8: 90 | AH8: 85 | AI8: 80 | AJ8: 75 | AK8: 95 | AL8: 90 | AM8: 85 | AN8: 80 | AO8: 75 | AP8: 70 | AQ8: 65
I9: 30 | J9: OPTerm 30 | K9: Yes | L9: Diamond, BEGA-1, AB90, AB85, AB80, AB75, AB70, AB65, AB60, BMGA85, BMGA80, BMGA75, BMGA70, BMGA65, BMGA60, BMGA90, BEGA90, BEGA85, BEGA80, BEGA75, BEGA70, BDGA90, BDGA85, BDGA80, BDGA75, BDGA70, BDGA65, BDGA60 | M9: OPTerm 30 | N9: Sub type: 30 Year Term | P9: 118 | Q9: 100 | R9: 95 | S9: 90 | T9: 85 | U9: 80 | V9: 75 | W9: 70 | X9: 65 | Y9: 90 | Z9: 85 | AA9: 80 | AB9: 75 | AC9: 70 | AD9: 65 | AE9: 95 | AF9: 95 | AG9: 90 | AH9: 85 | AI9: 80 | AJ9: 75 | AK9: 95 | AL9: 90 | AM9: 85 | AN9: 80 | AO9: 75 | AP9: 70 | AQ9: 65
I10: 35 | J10: OPTerm 35 | K10: Yes | L10: Diamond, BEGA-1, AB90, AB85, AB80, AB75, AB70, AB65, AB60, BMGA85, BMGA80, BMGA75, BMGA70, BMGA65, BMGA60, BMGA90, BEGA90, BEGA85, BEGA80, BEGA75, BEGA70, BDGA90, BDGA85, BDGA80, BDGA75, BDGA70, BDGA65, BDGA60 | M10: OPTerm 35 | N10: Sub type: 35 Year Term | P10: 118 | Q10: 100 | R10: 95 | S10: 90 | T10: 85 | U10: 80 | V10: 75 | W10: 70 | X10: 65 | Y10: 90 | Z10: 85 | AA10: 80 | AB10: 75 | AC10: 70 | AD10: 65 | AE10: 95 | AF10: 95 | AG10: 90 | AH10: 85 | AI10: 80 | AJ10: 75 | AK10: 95 | AL10: 90 | AM10: 85 | AN10: 80 | AO10: 75 | AP10: 70 | AQ10: 65
I11: 40 | J11: OPTerm 40 | K11: Yes | L11: Diamond, BEGA-1, AB90, AB85, AB80, AB75, AB70, AB65, AB60, BMGA85, BMGA80, BMGA75, BMGA70, BMGA65, BMGA60, BMGA90, BEGA90, BEGA85, BEGA80, BEGA75, BEGA70, BDGA90, BDGA85, BDGA80, BDGA75, BDGA70, BDGA65, BDGA60 | M11: OPTerm 40 | N11: Sub type: 40 Year Term | P11: 118 | Q11: 100 | R11: 95 | S11: 90 | T11: 85 | U11: 80 | V11: 75 | W11: 70 | X11: 65 | Y11: 90 | Z11: 85 | AA11: 80 | AB11: 75 | AC11: 70 | AD11: 65 | AE11: 95 | AF11: 95 | AG11: 90 | AH11: 85 | AI11: 80 | AJ11: 75 | AK11: 95 | AL11: 90 | AM11: 85 | AN11: 80 | AO11: 75 | AP11: 70 | AQ11: 65

Sheet L-BRIGT
A1: Row | B1: Service-Carrier ID | C1: Product Tier | D1: Types | E1: State Available | F1: Old Product name | G1: Sub-Name | H1: Sub-type | I1: Length | J1: Product Name Full | K1: Product Real | L1: All Vendor paycodes | M1: Product | N1: Criteria | O1: Notes | P1: Diamond | Q1: Max Base
A2: 1 | B2: L_BRIGT | C2: TBD | D2: Perm | E2: Non-NY | F2: Brighthouse Conversion Whole Life | H2: WL | I2: Life | J2: Brighthouse Conversion Whole Life | K2: Yes | L2: Diamond, Max Base | M2: Brighthouse Conversion Whole Life | O2: Type: Perm State: Non-NY Product Name: Brighthouse Conversion Whole Life | P2: 10 | Q2: 10
A3: 2 | B3: L_BRIGT | C3: TBD | D3: Term | E3: Non-NY | F3: One Year Term w/ CRO | H3: Term | I3: 1 | J3: One Year Term w/ CRO | K3: Yes | L3: Diamond, Max Base | M3: One Year Term w/ CRO | O3: Type: Term State: Non-NY Product Name: One Year Term w/ CRO | P3: 6 | Q3: 6

Sheet L-CORE-AGLA
A1: Row | B1: Service-Carrier ID | C1: Product Tier | D1: Types | E1: State Available | F1: Old Product name | G1: Sub-Name | H1: Sub-type | I1: Length | J1: Product Name Full | K1: Product Real | L1: All Vendor paycodes | M1: Product | N1: Criteria | O1: Notes | P1: Diamond | Q1: 11 | R1: 10 | S1: 9 | T1: 8 | U1: 7 | V1: 6 | W1: 5 | X1: 4 | Y1: 3 | Z1: 2 | AA1: 1
A2: 1 | B2: L_AGLA | C2: TBD | D2: Term | E2: All Avail. | G2: 20-30 & 35 Year | H2: Term | I2: 35 | J2: QoL Flex Term 35 Year | K2: Yes | L2: Diamond, 11, 10, 9, 8, 7, 6, 5, 4, 3, 2, 1 | M2: QoL Flex Term | N2: Sub type: 35 Year | State: All Available | P2: 104 | Q2: 95 | R2: 90 | S2: 85 | T2: 80 | U2: 75 | V2: 70 | W2: 65 | X2: 60 | Y2: 55 | Z2: 50 | AA2: 45
A3: 2 | B3: L_AGLA | C3: TBD | D3: Term | E3: All Avail. | G3: 15-19 Year | H3: Term | I3: 30 | J3: QoL Flex Term 30 Year | K3: Yes | L3: Diamond, 11, 10, 9, 8, 7, 6, 5, 4, 3, 2, 1 | M3: QoL Flex Term | N3: Sub type: 30 Year | State: Alabama, Alaska, Arizona, Arkansas, California, Colorado, Connecticut, Delaware, Florida, Georgia, Hawaii, Idaho, Illinois, Indiana, Iowa, Kansas, Kentucky, Louisiana, Maine, Maryland, Massachusetts, Michigan, Minnesota, Mississippi, Missouri, Montana, Nebraska, Nevada, New Hampshire, New Jersey, New Mexico, North Carolina, North Dakota, Ohio, Oklahoma, Oregon, Pennsylvania, Rhode Island, South Carolina, South Dakota, Tennessee, Texas, Utah, Vermont, Virginia, Washington, West Virginia, Wisconsin, Wyoming | P3: 104 | Q3: 95 | R3: 90 | S3: 85 | T3: 80 | U3: 75 | V3: 70 | W3: 65 | X3: 60 | Y3: 55 | Z3: 50 | AA3: 45
A4: 3 | B4: L_AGLA | C4: TBD | D4: Term | E4: All Avail. | G4: 10 Year | H4: Term | I4: 29 | J4: QoL Flex Term 29 Year | K4: Yes | L4: Diamond, 11, 10, 9, 8, 7, 6, 5, 4, 3, 2, 1 | M4: QoL Flex Term | N4: Sub type: 29 Year | State: Alabama, Alaska, Arizona, Arkansas, California, Colorado, Connecticut, Delaware, Florida, Georgia, Hawaii, Idaho, Illinois, Indiana, Iowa, Kansas, Kentucky, Louisiana, Maine, Maryland, Massachusetts, Michigan, Minnesota, Mississippi, Missouri, Montana, Nebraska, Nevada, New Hampshire, New Jersey, New Mexico, North Carolina, North Dakota, Ohio, Oklahoma, Oregon, Pennsylvania, Rhode Island, South Carolina, South Dakota, Tennessee, Texas, Utah, Vermont, Virginia, Washington, West Virginia, Wisconsin, Wyoming | P4: 104 | Q4: 95 | R4: 90 | S4: 85 | T4: 80 | U4: 75 | V4: 70 | W4: 65 | X4: 60 | Y4: 55 | Z4: 50 | AA4: 45
A5: 4 | B5: L_AGLA | C5: TBD | D5: Perm | E5: All Avail. | H5: IUL | I5: 28 | J5: QoL Flex Term 28 Year | K5: Yes | L5: Diamond, 11, 10, 9, 8, 7, 6, 5, 4, 3, 2, 1 | M5: QoL Flex Term | N5: Sub type: 28 Year | State: Alabama, Alaska, Arizona, Arkansas, California, Colorado, Connecticut, Delaware, Florida, Georgia, Hawaii, Idaho, Illinois, Indiana, Iowa, Kansas, Kentucky, Louisiana, Maine, Maryland, Massachusetts, Michigan, Minnesota, Mississippi, Missouri, Montana, Nebraska, Nevada, New Hampshire, New Jersey, New Mexico, North Carolina, North Dakota, Ohio, Oklahoma, Oregon, Pennsylvania, Rhode Island, South Carolina, South Dakota, Tennessee, Texas, Utah, Vermont, Virginia, Washington, West Virginia, Wisconsin, Wyoming | P5: 104 | Q5: 95 | R5: 90 | S5: 85 | T5: 80 | U5: 75 | V5: 70 | W5: 65 | X5: 60 | Y5: 55 | Z5: 50 | AA5: 45
A6: 5 | B6: L_AGLA | C6: TBD | D6: Perm | E6: All Avail. | G6: Excess Year 2 | H6: IUL | I6: 27 | J6: QoL Flex Term 27 Year | K6: Yes | L6: Diamond, 11, 10, 9, 8, 7, 6, 5, 4, 3, 2, 1 | M6: QoL Flex Term | N6: Sub type: 27 Year | State: Alabama, Alaska, Arizona, Arkansas, California, Colorado, Connecticut, Delaware, Florida, Georgia, Hawaii, Idaho, Illinois, Indiana, Iowa, Kansas, Kentucky, Louisiana, Maine, Maryland, Massachusetts, Michigan, Minnesota, Mississippi, Missouri, Montana, Nebraska, Nevada, New Hampshire, New Jersey, New Mexico, North Carolina, North Dakota, Ohio, Oklahoma, Oregon, Pennsylvania, Rhode Island, South Carolina, South Dakota, Tennessee, Texas, Utah, Vermont, Virginia, Washington, West Virginia, Wisconsin, Wyoming | P6: 104 | Q6: 95 | R6: 90 | S6: 85 | T6: 80 | U6: 75 | V6: 70 | W6: 65 | X6: 60 | Y6: 55 | Z6: 50 | AA6: 45
A7: 6 | B7: L_AGLA | C7: TBD | D7: Perm | E7: All Avail. | G7: Excess Years 2+ | H7: IUL | I7: 26 | J7: QoL Flex Term 26 Year | K7: Yes | L7: Diamond, 11, 10, 9, 8, 7, 6, 5, 4, 3, 2, 1 | M7: QoL Flex Term | N7: Sub type: 26 Year | State: Alabama, Alaska, Arizona, Arkansas, California, Colorado, Connecticut, Delaware, Florida, Georgia, Hawaii, Idaho, Illinois, Indiana, Iowa, Kansas, Kentucky, Louisiana, Maine, Maryland, Massachusetts, Michigan, Minnesota, Mississippi, Missouri, Montana, Nebraska, Nevada, New Hampshire, New Jersey, New Mexico, North Carolina, North Dakota, Ohio, Oklahoma, Oregon, Pennsylvania, Rhode Island, South Carolina, South Dakota, Tennessee, Texas, Utah, Vermont, Virginia, Washington, West Virginia, Wisconsin, Wyoming | P7: 104 | Q7: 95 | R7: 90 | S7: 85 | T7: 80 | U7: 75 | V7: 70 | W7: 65 | X7: 60 | Y7: 55 | Z7: 50 | AA7: 45
A8: 7 | B8: L_AGLA | C8: TBD | D8: Perm | E8: All Avail. | H8: IUL | I8: 25 | J8: QoL Flex Term 25 Year | K8: Yes | L8: Diamond, 11, 10, 9, 8, 7, 6, 5, 4, 3, 2, 1 | M8: QoL Flex Term | N8: Sub type: 25 Year | State: Alabama, Alaska, Arizona, Arkansas, California, Colorado, Connecticut, Delaware, Florida, Georgia, Hawaii, Idaho, Illinois, Indiana, Iowa, Kansas, Kentucky, Louisiana, Maine, Maryland, Massachusetts, Michigan, Minnesota, Mississippi, Missouri, Montana, Nebraska, Nevada, New Hampshire, New Jersey, New Mexico, North Carolina, North Dakota, Ohio, Oklahoma, Oregon, Pennsylvania, Rhode Island, South Carolina, South Dakota, Tennessee, Texas, Utah, Vermont, Virginia, Washington, West Virginia, Wisconsin, Wyoming | P8: 104 | Q8: 95 | R8: 90 | S8: 85 | T8: 80 | U8: 75 | V8: 70 | W8: 65 | X8: 60 | Y8: 55 | Z8: 50 | AA8: 45
A9: 8 | B9: L_AGLA | C9: TBD | D9: Perm | E9: All Avail. | H9: IUL | I9: 24 | J9: QoL Flex Term 24 Year | K9: Yes | L9: Diamond, 11, 10, 9, 8, 7, 6, 5, 4, 3, 2, 1 | M9: QoL Flex Term | N9: Sub type: 24 Year | State: Alabama, Alaska, Arizona, Arkansas, California, Colorado, Connecticut, Delaware, Florida, Georgia, Hawaii, Idaho, Illinois, Indiana, Iowa, Kansas, Kentucky, Louisiana, Maine, Maryland, Massachusetts, Michigan, Minnesota, Mississippi, Missouri, Montana, Nebraska, Nevada, New Hampshire, New Jersey, New Mexico, North Carolina, North Dakota, Ohio, Oklahoma, Oregon, Pennsylvania, Rhode Island, South Carolina, South Dakota, Tennessee, Texas, Utah, Vermont, Virginia, Washington, West Virginia, Wisconsin, Wyoming | P9: 104 | Q9: 95 | R9: 90 | S9: 85 | T9: 80 | U9: 75 | V9: 70 | W9: 65 | X9: 60 | Y9: 55 | Z9: 50 | AA9: 45
A10: 9 | B10: L_AGLA | C10: TBD | D10: Perm | E10: All Avail. | H10: IUL | I10: 23 | J10: QoL Flex Term 23 Year | K10: Yes | L10: Diamond, 11, 10, 9, 8, 7, 6, 5, 4, 3, 2, 1 | M10: QoL Flex Term | N10: Sub type: 23 Year | State: Alabama, Alaska, Arizona, Arkansas, California, Colorado, Connecticut, Delaware, Florida, Georgia, Hawaii, Idaho, Illinois, Indiana, Iowa, Kansas, Kentucky, Louisiana, Maine, Maryland, Massachusetts, Michigan, Minnesota, Mississippi, Missouri, Montana, Nebraska, Nevada, New Hampshire, New Jersey, New Mexico, North Carolina, North Dakota, Ohio, Oklahoma, Oregon, Pennsylvania, Rhode Island, South Carolina, South Dakota, Tennessee, Texas, Utah, Vermont, Virginia, Washington, West Virginia, Wisconsin, Wyoming | P10: 104 | Q10: 95 | R10: 90 | S10: 85 | T10: 80 | U10: 75 | V10: 70 | W10: 65 | X10: 60 | Y10: 55 | Z10: 50 | AA10: 45
A11: 10 | B11: L_AGLA | C11: TBD | D11: Perm | E11: All Avail. | H11: IUL | I11: 22 | J11: QoL Flex Term 22 Year | K11: Yes | L11: Diamond, 11, 10, 9, 8, 7, 6, 5, 4, 3, 2, 1 | M11: QoL Flex Term | N11: Sub type: 22 Year | State: Alabama, Alaska, Arizona, Arkansas, California, Colorado, Connecticut, Delaware, Florida, Georgia, Hawaii, Idaho, Illinois, Indiana, Iowa, Kansas, Kentucky, Louisiana, Maine, Maryland, Massachusetts, Michigan, Minnesota, Mississippi, Missouri, Montana, Nebraska, Nevada, New Hampshire, New Jersey, New Mexico, North Carolina, North Dakota, Ohio, Oklahoma, Oregon, Pennsylvania, Rhode Island, South Carolina, South Dakota, Tennessee, Texas, Utah, Vermont, Virginia, Washington, West Virginia, Wisconsin, Wyoming | P11: 104 | Q11: 95 | R11: 90 | S11: 85 | T11: 80 | U11: 75 | V11: 70 | W11: 65 | X11: 60 | Y11: 55 | Z11: 50 | AA11: 45
A12: 11 | B12: L_AGLA | C12: TBD | D12: Perm | E12: All Avail. | H12: IUL | I12: 21 | J12: QoL Flex Term 21 Year | K12: Yes | L12: Diamond, 11, 10, 9, 8, 7, 6, 5, 4, 3, 2, 1 | M12: QoL Flex Term | N12: Sub type: 21 Year | State: Alabama, Alaska, Arizona, Arkansas, California, Colorado, Connecticut, Delaware, Florida, Georgia, Hawaii, Idaho, Illinois, Indiana, Iowa, Kansas, Kentucky, Louisiana, Maine, Maryland, Massachusetts, Michigan, Minnesota, Mississippi, Missouri, Montana, Nebraska, Nevada, New Hampshire, New Jersey, New Mexico, North Carolina, North Dakota, Ohio, Oklahoma, Oregon, Pennsylvania, Rhode Island, South Carolina, South Dakota, Tennessee, Texas, Utah, Vermont, Virginia, Washington, West Virginia, Wisconsin, Wyoming | P12: 104 | Q12: 95 | R12: 90 | S12: 85 | T12: 80 | U12: 75 | V12: 70 | W12: 65 | X12: 60 | Y12: 55 | Z12: 50 | AA12: 45
A13: 12 | B13: L_AGLA | C13: TBD | D13: Perm | E13: All Avail. | H13: UL | I13: 20 | J13: QoL Flex Term 20 Year | K13: Yes | L13: Diamond, 11, 10, 9, 8, 7, 6, 5, 4, 3, 2, 1 | M13: QoL Flex Term | N13: Sub type: 20 Year | State: Alabama, Alaska, Arizona, Arkansas, California, Colorado, Connecticut, Delaware, Florida, Georgia, Hawaii, Idaho, Illinois, Indiana, Iowa, Kansas, Kentucky, Louisiana, Maine, Maryland, Massachusetts, Michigan, Minnesota, Mississippi, Missouri, Montana, Nebraska, Nevada, New Hampshire, New Jersey, New Mexico, North Carolina, North Dakota, Ohio, Oklahoma, Oregon, Pennsylvania, Rhode Island, South Carolina, South Dakota, Tennessee, Texas, Utah, Vermont, Virginia, Washington, West Virginia, Wisconsin, Wyoming | P13: 104 | Q13: 95 | R13: 90 | S13: 85 | T13: 80 | U13: 75 | V13: 70 | W13: 65 | X13: 60 | Y13: 55 | Z13: 50 | AA13: 45
A14: 13 | B14: L_AGLA | C14: TBD | D14: Perm | E14: All Avail. | H14: UL | I14: 19 | J14: QoL Flex Term 19 Year | K14: Yes | L14: Diamond, 11, 10, 9, 8, 7, 6, 5, 4, 3, 2, 1 | M14: QoL Flex Term | N14: Sub type: 19 Year | State: Alabama, Alaska, Arizona, Arkansas, California, Colorado, Connecticut, Delaware, Florida, Georgia, Hawaii, Idaho, Illinois, Indiana, Iowa, Kansas, Kentucky, Louisiana, Maine, Maryland, Massachusetts, Michigan, Minnesota, Mississippi, Missouri, Montana, Nebraska, Nevada, New Hampshire, New Jersey, New Mexico, North Carolina, North Dakota, Ohio, Oklahoma, Oregon, Pennsylvania, Rhode Island, South Carolina, South Dakota, Tennessee, Texas, Utah, Vermont, Virginia, Washington, West Virginia, Wisconsin, Wyoming | P14: 89 | Q14: 85 | R14: 80 | S14: 75 | T14: 70 | U14: 65 | V14: 60 | W14: 55 | X14: 50 | Y14: 45 | Z14: 40 | AA14: 35
A15: 14 | B15: L_AGLA | C15: TBD | D15: Perm | E15: All Avail. | H15: UL | I15: 18 | J15: QoL Flex Term 18 Year | K15: Yes | L15: Diamond, 11, 10, 9, 8, 7, 6, 5, 4, 3, 2, 1 | M15: QoL Flex Term | N15: Sub type: 18 Year | State: Alabama, Alaska, Arizona, Arkansas, California, Colorado, Connecticut, Delaware, Florida, Georgia, Hawaii, Idaho, Illinois, Indiana, Iowa, Kansas, Kentucky, Louisiana, Maine, Maryland, Massachusetts, Michigan, Minnesota, Mississippi, Missouri, Montana, Nebraska, Nevada, New Hampshire, New Jersey, New Mexico, North Carolina, North Dakota, Ohio, Oklahoma, Oregon, Pennsylvania, Rhode Island, South Carolina, South Dakota, Tennessee, Texas, Utah, Vermont, Virginia, Washington, West Virginia, Wisconsin, Wyoming | P15: 89 | Q15: 85 | R15: 80 | S15: 75 | T15: 70 | U15: 65 | V15: 60 | W15: 55 | X15: 50 | Y15: 45 | Z15: 40 | AA15: 35
A16: 15 | B16: L_AGLA | C16: TBD | D16: Perm | E16: All Avail. | G16: Conversion Only | H16: WL | I16: 17 | J16: QoL Flex Term 17 Year | K16: Yes | L16: Diamond, 11, 10, 9, 8, 7, 6, 5, 4, 3, 2, 1 | M16: QoL Flex Term | N16: Sub type: 17 Year | State: Alabama, Alaska, Arizona, Arkansas, California, Colorado, Connecticut, Delaware, Florida, Georgia, Hawaii, Idaho, Illinois, Indiana, Iowa, Kansas, Kentucky, Louisiana, Maine, Maryland, Massachusetts, Michigan, Minnesota, Mississippi, Missouri, Montana, Nebraska, Nevada, New Hampshire, New Jersey, New Mexico, North Carolina, North Dakota, Ohio, Oklahoma, Oregon, Pennsylvania, Rhode Island, South Carolina, South Dakota, Tennessee, Texas, Utah, Vermont, Virginia, Washington, West Virginia, Wisconsin, Wyoming | P16: 89 | Q16: 85 | R16: 80 | S16: 75 | T16: 70 | U16: 65 | V16: 60 | W16: 55 | X16: 50 | Y16: 45 | Z16: 40 | AA16: 35
A17: 16 | B17: L_AGLA | C17: TBD | D17: Perm | E17: All Avail. | H17: WL | I17: 16 | J17: QoL Flex Term 16 Year | K17: Yes | L17: Diamond, 11, 10, 9, 8, 7, 6, 5, 4, 3, 2, 1 | M17: QoL Flex Term | N17: Sub type: 16 Year | State: Alabama, Alaska, Arizona, Arkansas, California, Colorado, Connecticut, Delaware, Florida, Georgia, Hawaii, Idaho, Illinois, Indiana, Iowa, Kansas, Kentucky, Louisiana, Maine, Maryland, Massachusetts, Michigan, Minnesota, Mississippi, Missouri, Montana, Nebraska, Nevada, New Hampshire, New Jersey, New Mexico, North Carolina, North Dakota, Ohio, Oklahoma, Oregon, Pennsylvania, Rhode Island, South Carolina, South Dakota, Tennessee, Texas, Utah, Vermont, Virginia, Washington, West Virginia, Wisconsin, Wyoming | P17: 89 | Q17: 85 | R17: 80 | S17: 75 | T17: 70 | U17: 65 | V17: 60 | W17: 55 | X17: 50 | Y17: 45 | Z17: 40 | AA17: 35
A18: 17 | B18: L_AGLA | C18: TBD | D18: Perm | E18: All Avail. | I18: 15 | J18: QoL Flex Term 15 Year | K18: Yes | L18: Diamond, 11, 10, 9, 8, 7, 6, 5, 4, 3, 2, 1 | M18: QoL Flex Term | N18: Sub type: 15 Year | State: All Available | P18: 89 | Q18: 85 | R18: 80 | S18: 75 | T18: 70 | U18: 65 | V18: 60 | W18: 55 | X18: 50 | Y18: 45 | Z18: 40 | AA18: 35
A19: 18 | B19: L_AGLA | C19: TBD | D19: Perm | E19: All Avail. | I19: 10 | J19: QoL Flex Term 10 Year | K19: Yes | L19: Diamond, 11, 10, 9, 8, 7, 6, 5, 4, 3, 2, 1 | M19: QoL Flex Term | N19: Sub type: 10 Year | State: All Available | P19: 79 | Q19: 75 | R19: 70 | S19: 65 | T19: 60 | U19: 55 | V19: 50 | W19: 45 | X19: 40 | Y19: 35 | Z19: 30 | AA19: 25
A20: 19 | B20: L_AGLA | C20: TBD | D20: Perm | E20: All Avail. | I20: Lifetime | J20: QoL Max Accumulator+ | K20: Yes | L20: Diamond, 11, 10, 9, 8, 7, 6, 5, 4, 3, 2, 1 | M20: QoL Max Accumulator+ | N20: State: All Available | P20: 119 | Q20: 90 | R20: 85 | S20: 80 | T20: 75 | U20: 70 | V20: 65 | W20: 60 | X20: 55 | Y20: 50 | Z20: 45 | AA20: 40
A21: 20 | B21: L_AGLA | C21: TBD | D21: Perm | E21: All Avail. | I21: Lifetime | J21: QoL Max Accumulator+ (Excess Year 1) | K21: No | L21: Diamond, 11, 10, 9, 8, 7, 6, 5, 4, 3, 2, 1 | M21: QoL Max Accumulator+ | N21: Excess year: 1 | Q21: 1.25 | R21: 1.15 | S21: 1 | T21: 1 | U21: 1 | V21: 1 | W21: 1 | X21: 1 | Y21: 1 | Z21: 1 | AA21: 1
A22: 21 | B22: L_AGLA | C22: TBD | D22: Perm | E22: All Avail. | I22: Lifetime | J22: QoL Max Accumulator+ (Excess Year 2+) | K22: No | L22: Diamond, 11, 10, 9, 8, 7, 6, 5, 4, 3, 2, 1 | M22: QoL Max Accumulator+ | N22: Excess year: 2+ | Q22: 2 | R22: 2 | S22: 2 | T22: 2 | U22: 2 | V22: 2 | W22: 2 | X22: 2 | Y22: 2 | Z22: 2 | AA22: 2
A23: 22 | B23: L_AGLA | C23: TBD | D23: Perm | E23: All Avail. | I23: Lifetime | J23: QoL Max Accumulator+ (Renewal Years 2-10) | K23: No | L23: Diamond, 11, 10, 9, 8, 7, 6, 5, 4, 3, 2, 1 | M23: QoL Max Accumulator+ | N23: Renewal year: 2 to 10 | State: All Available | Q23: 2 | R23: 2 | S23: 2 | T23: 2 | U23: 2 | V23: 2 | W23: 2 | X23: 2 | Y23: 2 | Z23: 2 | AA23: 2
A24: 23 | B24: L_AGLA | C24: TBD | D24: Perm | E24: All Avail. | I24: Lifetime | J24: QoL Max Accumulator+ III With Early Cash Value Rider | K24: No | L24: Diamond, 11, 10, 9, 8, 7, 6, 5, 4, 3, 2, 1 | M24: QoL Max Accumulator+ III With Early Cash Value Rider | N24: Sub type: With Early Cash Value Rider | State: All Available | Q24: 20 | R24: 19 | S24: 18 | T24: 17 | U24: 16 | V24: 15 | W24: 14 | X24: 13 | Y24: 12 | Z24: 11 | AA24: 10
A25: 24 | B25: L_AGLA | C25: TBD | D25: Perm | E25: All Avail. | I25: Lifetime | J25: QoL Max Accumulator+ III With Early Cash Value Rider (Excess Year 1) | K25: No | L25: Diamond, 11, 10, 9, 8, 7, 6, 5, 4, 3, 2, 1 | M25: QoL Max Accumulator+ III With Early Cash Value Rider | N25: Excess year: 1 | Q25: 1.25 | R25: 1.15 | S25: 1 | T25: 1 | U25: 1 | V25: 1 | W25: 1 | X25: 1 | Y25: 1 | Z25: 1 | AA25: 1
A26: 25 | B26: L_AGLA | C26: TBD | D26: Perm | E26: All Avail. | I26: Lifetime | J26: QoL Max Accumulator+ III With Early Cash Value Rider (Renewal Years 2-7) | K26: No | L26: Diamond, 11, 10, 9, 8, 7, 6, 5, 4, 3, 2, 1 | M26: QoL Max Accumulator+ III With Early Cash Value Rider | N26: Renewal year: 2 to 7 | State: All Available | Q26: 11 | R26: 10 | S26: 9 | T26: 8 | U26: 7 | V26: 6 | W26: 5 | X26: 4 | Y26: 3 | Z26: 2 | AA26: 1
A27: 26 | B27: L_AGLA | C27: TBD | D27: Perm | E27: All Avail. | I27: Lifetime | J27: QoL Value+ Protector | K27: Yes | L27: Diamond, 11, 10, 9, 8, 7, 6, 5, 4, 3, 2, 1 | M27: QoL Value+ Protector | N27: State: All Available | P27: 109 | Q27: 90 | R27: 85 | S27: 80 | T27: 75 | U27: 70 | V27: 65 | W27: 60 | X27: 55 | Y27: 50 | Z27: 45 | AA27: 40
A28: 27 | B28: L_AGLA | C28: TBD | D28: Perm | E28: All Avail. | I28: Lifetime | J28: QoL Value+ Protector (Excess Year 1) | K28: No | L28: Diamond, 11, 10, 9, 8, 7, 6, 5, 4, 3, 2, 1 | M28: QoL Value+ Protector | N28: Excess year: 1 | Q28: 1.25 | R28: 1.15 | S28: 1 | T28: 1 | U28: 1 | V28: 1 | W28: 1 | X28: 1 | Y28: 1 | Z28: 1 | AA28: 1
A29: 28 | B29: L_AGLA | C29: TBD | D29: Perm | E29: All Avail. | I29: Lifetime | J29: QoL Value+ Protector (Excess Year 2+) | K29: No | L29: Diamond, 11, 10, 9, 8, 7, 6, 5, 4, 3, 2, 1 | M29: QoL Value+ Protector | N29: Excess year: 2+ | Q29: 2 | R29: 2 | S29: 2 | T29: 2 | U29: 2 | V29: 2 | W29: 2 | X29: 2 | Y29: 2 | Z29: 2 | AA29: 2
A30: 29 | B30: L_AGLA | C30: TBD | D30: Perm | E30: All Avail. | I30: Lifetime | J30: QoL Value+ Protector (Renewal Years 2-10) | K30: No | L30: Diamond, 11, 10, 9, 8, 7, 6, 5, 4, 3, 2, 1 | M30: QoL Value+ Protector | N30: Renewal year: 2 to 10 | State: All Available | Q30: 2 | R30: 2 | S30: 2 | T30: 2 | U30: 2 | V30: 2 | W30: 2 | X30: 2 | Y30: 2 | Z30: 2 | AA30: 2
A31: 30 | B31: L_AGLA | C31: TBD | D31: Perm | E31: All Avail. | I31: Lifetime | J31: QoL Guarantee Plus GUL II | K31: Yes | L31: Diamond, 11, 10, 9, 8, 7, 6, 5, 4, 3, 2, 1 | M31: QoL Guarantee Plus GUL II | N31: State: All Available | P31: 99 | Q31: 90 | R31: 85 | S31: 80 | T31: 75 | U31: 70 | V31: 65 | W31: 60 | X31: 55 | Y31: 50 | Z31: 45 | AA31: 40
A32: 31 | B32: L_AGLA | C32: TBD | D32: Perm | E32: All Avail. | I32: Lifetime | J32: QoL Guarantee Plus GUL II (Excess Year 1) | K32: No | L32: Diamond, 11, 10, 9, 8, 7, 6, 5, 4, 3, 2, 1 | M32: QoL Guarantee Plus GUL II | N32: Excess year: 1+ | Q32: 1.25 | R32: 1.15 | S32: 1 | T32: 1 | U32: 1 | V32: 1 | W32: 1 | X32: 1 | Y32: 1 | Z32: 1 | AA32: 1
A33: 32 | B33: L_AGLA | C33: TBD | D33: Perm | E33: All Avail. | I33: Lifetime | J33: QoL Guarantee Plus GUL II (Renewal Years 2-10) | K33: No | L33: Diamond, 11, 10, 9, 8, 7, 6, 5, 4, 3, 2, 1 | M33: QoL Guarantee Plus GUL II | N33: Renewal year: 2 to 10 | State: All Available | Q33: 2 | R33: 2 | S33: 2 | T33: 2 | U33: 2 | V33: 2 | W33: 2 | X33: 2 | Y33: 2 | Z33: 2 | AA33: 2
A34: 33 | B34: L_AGLA | C34: TBD | D34: Perm | E34: All Avail. | I34: Lifetime | J34: American Elite Whole Life | K34: Yes | L34: Diamond, 11, 10, 9, 8, 7, 6, 5, 4, 3, 2, 1 | M34: American Elite Whole Life | N34: Sub type: Conversion Only | State: All Available | P34: 65 | Q34: 65 | R34: 61 | S34: 58 | T34: 54 | U34: 51 | V34: 47 | W34: 43 | X34: 40 | Y34: 36 | Z34: 32 | AA34: 28
A35: 34 | B35: L_AGLA | C35: TBD | D35: Perm | E35: All Avail. | I35: Lifetime | J35: American Elite Whole Life (Renewal Years 2-10) | K35: No | L35: Diamond, 11, 10, 9, 8, 7, 6, 5, 4, 3, 2, 1 | M35: American Elite Whole Life | N35: Renewal year: 2 to 10 | State: All Available | Q35: 2 | R35: 2 | S35: 2 | T35: 2 | U35: 2 | V35: 2 | W35: 2 | X35: 2 | Y35: 2 | Z35: 2 | AA35: 2

Sheet L-CORE
A1: Row | B1: Service-Carrier ID | C1: Product Tier | D1: Types | E1: State Available | F1: Old Product name | G1: Sub-Name | H1: Sub-type | I1: Length | J1: Product Name Full | K1: Product Real | L1: All Vendor paycodes | M1: Product | N1: Criteria | O1: Notes | P1: Diamond | Q1: A | R1: B | S1: C | T1: D | U1: E | V1: F | W1: G | X1: H | Y1: I | Z1: J | AA1: M | AB1: N
A2: 1 | B2: L_CORE | C2: TBD | D2: Term | E2: Non-NY | G2: 20-30 & 35 yr | H2: Term | I2: 20, 21, 22, 23, 24, 25, 30, 35 | J2: AG Select-A-Term 35 Year | K2: Yes | L2: Diamond, A, B, C, D, E, F, G, H, I, J, M, N | M2: AG Select-A-Term | N2: Sub type: 35 Year | State: Alabama, Alaska, Arizona, Arkansas, California, Colorado, Connecticut, Delaware, Florida, Georgia, Hawaii, Idaho, Illinois, Indiana, Iowa, Kansas, Kentucky, Louisiana, Maine, Maryland, Massachusetts, Michigan, Minnesota, Mississippi, Missouri, Montana, Nebraska, Nevada, New Hampshire, New Jersey, New Mexico, North Carolina, North Dakota, Ohio, Oklahoma, Oregon, Pennsylvania, Rhode Island, South Carolina, South Dakota, Tennessee, Texas, Utah, Vermont, Virginia, Washington, West Virginia, Wisconsin, Wyoming | P2: 114 | Q2: 95 | R2: 95 | S2: 95 | T2: 95 | U2: 95 | V2: 95 | W2: 95 | X2: 95 | Y2: 95 | Z2: 95 | AA2: 45 | AB2: 40
A3: 2 | B3: L_CORE | C3: TBD | D3: Term | E3: Non-NY | G3: 19 yr | H3: Term | I3: 19 | J3: AG Select-A-Term 30 Year | K3: Yes | L3: Diamond, A, B, C, D, E, F, G, H, I, J, M, N | M3: AG Select-A-Term | N3: Sub type: 30 Year | State: Alabama, Alaska, Arizona, Arkansas, California, Colorado, Connecticut, Delaware, Florida, Georgia, Hawaii, Idaho, Illinois, Indiana, Iowa, Kansas, Kentucky, Louisiana, Maine, Maryland, Massachusetts, Michigan, Minnesota, Mississippi, Missouri, Montana, Nebraska, Nevada, New Hampshire, New Jersey, New Mexico, North Carolina, North Dakota, Ohio, Oklahoma, Oregon, Pennsylvania, Rhode Island, South Carolina, South Dakota, Tennessee, Texas, Utah, Vermont, Virginia, Washington, West Virginia, Wisconsin, Wyoming | P3: 114 | Q3: 95 | R3: 95 | S3: 95 | T3: 95 | U3: 95 | V3: 95 | W3: 95 | X3: 95 | Y3: 95 | Z3: 95 | AA3: 45 | AB3: 40
A4: 3 | B4: L_CORE | C4: TBD | D4: Term | E4: Non-NY | G4: 18 yr | H4: Term | I4: 18 | J4: AG Select-A-Term 29 Year | K4: Yes | L4: Diamond, A, B, C, D, E, F, G, H, I, J, M, N | M4: AG Select-A-Term | N4: Sub type: 29 Year | State: Alabama, Alaska, Arizona, Arkansas, California, Colorado, Connecticut, Delaware, Florida, Georgia, Hawaii, Idaho, Illinois, Indiana, Iowa, Kansas, Kentucky, Louisiana, Maine, Maryland, Massachusetts, Michigan, Minnesota, Mississippi, Missouri, Montana, Nebraska, Nevada, New Hampshire, New Jersey, New Mexico, North Carolina, North Dakota, Ohio, Oklahoma, Oregon, Pennsylvania, Rhode Island, South Carolina, South Dakota, Tennessee, Texas, Utah, Vermont, Virginia, Washington, West Virginia, Wisconsin, Wyoming | P4: 114 | Q4: 95 | R4: 95 | S4: 95 | T4: 95 | U4: 95 | V4: 95 | W4: 95 | X4: 95 | Y4: 95 | Z4: 95 | AA4: 45 | AB4: 40
A5: 4 | B5: L_CORE | C5: TBD | D5: Term | E5: Non-NY | G5: 17 yr | H5: Term | I5: 17 | J5: AG Select-A-Term 28 Year | K5: Yes | L5: Diamond, A, B, C, D, E, F, G, H, I, J, M, N | M5: AG Select-A-Term | N5: Sub type: 28 Year | State: Alabama, Alaska, Arizona, Arkansas, California, Colorado, Connecticut, Delaware, Florida, Georgia, Hawaii, Idaho, Illinois, Indiana, Iowa, Kansas, Kentucky, Louisiana, Maine, Maryland, Massachusetts, Michigan, Minnesota, Mississippi, Missouri, Montana, Nebraska, Nevada, New Hampshire, New Jersey, New Mexico, North Carolina, North Dakota, Ohio, Oklahoma, Oregon, Pennsylvania, Rhode Island, South Carolina, South Dakota, Tennessee, Texas, Utah, Vermont, Virginia, Washington, West Virginia, Wisconsin, Wyoming | P5: 114 | Q5: 95 | R5: 95 | S5: 95 | T5: 95 | U5: 95 | V5: 95 | W5: 95 | X5: 95 | Y5: 95 | Z5: 95 | AA5: 45 | AB5: 40
A6: 5 | B6: L_CORE | C6: TBD | D6: Term | E6: Non-NY | G6: 16yr | H6: Term | I6: 16 | J6: AG Select-A-Term 27 Year | K6: Yes | L6: Diamond, A, B, C, D, E, F, G, H, I, J, M, N | M6: AG Select-A-Term | N6: Sub type: 27 Year | State: Alabama, Alaska, Arizona, Arkansas, California, Colorado, Connecticut, Delaware, Florida, Georgia, Hawaii, Idaho, Illinois, Indiana, Iowa, Kansas, Kentucky, Louisiana, Maine, Maryland, Massachusetts, Michigan, Minnesota, Mississippi, Missouri, Montana, Nebraska, Nevada, New Hampshire, New Jersey, New Mexico, North Carolina, North Dakota, Ohio, Oklahoma, Oregon, Pennsylvania, Rhode Island, South Carolina, South Dakota, Tennessee, Texas, Utah, Vermont, Virginia, Washington, West Virginia, Wisconsin, Wyoming | P6: 114 | Q6: 95 | R6: 95 | S6: 95 | T6: 95 | U6: 95 | V6: 95 | W6: 95 | X6: 95 | Y6: 95 | Z6: 95 | AA6: 45 | AB6: 40
A7: 6 | B7: L_CORE | C7: TBD | D7: Term | E7: Non-NY | G7: 15yr | H7: Term | I7: 15 | J7: AG Select-A-Term 26 Year | K7: Yes | L7: Diamond, A, B, C, D, E, F, G, H, I, J, M, N | M7: AG Select-A-Term | N7: Sub type: 26 Year | State: Alabama, Alaska, Arizona, Arkansas, California, Colorado, Connecticut, Delaware, Florida, Georgia, Hawaii, Idaho, Illinois, Indiana, Iowa, Kansas, Kentucky, Louisiana, Maine, Maryland, Massachusetts, Michigan, Minnesota, Mississippi, Missouri, Montana, Nebraska, Nevada, New Hampshire, New Jersey, New Mexico, North Carolina, North Dakota, Ohio, Oklahoma, Oregon, Pennsylvania, Rhode Island, South Carolina, South Dakota, Tennessee, Texas, Utah, Vermont, Virginia, Washington, West Virginia, Wisconsin, Wyoming | P7: 114 | Q7: 95 | R7: 95 | S7: 95 | T7: 95 | U7: 95 | V7: 95 | W7: 95 | X7: 95 | Y7: 95 | Z7: 95 | AA7: 45 | AB7: 40
A8: 7 | B8: L_CORE | C8: TBD | D8: Term | E8: Non-NY | G8: 10 Year | H8: Term | I8: 10 | J8: AG Select-A-Term 25 Year | K8: Yes | L8: Diamond, A, B, C, D, E, F, G, H, I, J, M, N | M8: AG Select-A-Term | N8: Sub type: 25 Year | State: Alabama, Alaska, Arizona, Arkansas, California, Colorado, Connecticut, Delaware, Florida, Georgia, Hawaii, Idaho, Illinois, Indiana, Iowa, Kansas, Kentucky, Louisiana, Maine, Maryland, Massachusetts, Michigan, Minnesota, Mississippi, Missouri, Montana, Nebraska, Nevada, New Hampshire, New Jersey, New Mexico, North Carolina, North Dakota, Ohio, Oklahoma, Oregon, Pennsylvania, Rhode Island, South Carolina, South Dakota, Tennessee, Texas, Utah, Vermont, Virginia, Washington, West Virginia, Wisconsin, Wyoming | P8: 114 | Q8: 95 | R8: 95 | S8: 95 | T8: 95 | U8: 95 | V8: 95 | W8: 95 | X8: 95 | Y8: 95 | Z8: 95 | AA8: 45 | AB8: 40
A9: 8 | B9: L_CORE | C9: TBD | D9: Perm | E9: Non-NY | H9: UL | I9: 120 | J9: AG Select-A-Term 24 Year | K9: Yes | L9: Diamond, A, B, C, D, E, F, G, H, I, J, M, N | M9: AG Select-A-Term | N9: Sub type: 24 Year | State: Alabama, Alaska, Arizona, Arkansas, California, Colorado, Connecticut, Delaware, Florida, Georgia, Hawaii, Idaho, Illinois, Indiana, Iowa, Kansas, Kentucky, Louisiana, Maine, Maryland, Massachusetts, Michigan, Minnesota, Mississippi, Missouri, Montana, Nebraska, Nevada, New Hampshire, New Jersey, New Mexico, North Carolina, North Dakota, Ohio, Oklahoma, Oregon, Pennsylvania, Rhode Island, South Carolina, South Dakota, Tennessee, Texas, Utah, Vermont, Virginia, Washington, West Virginia, Wisconsin, Wyoming | P9: 114 | Q9: 95 | R9: 95 | S9: 95 | T9: 95 | U9: 95 | V9: 95 | W9: 95 | X9: 95 | Y9: 95 | Z9: 95 | AA9: 45 | AB9: 40
A10: 9 | B10: L_CORE | C10: TBD | D10: Perm | E10: Non-NY | H10: IUL | I10: 120 | J10: AG Select-A-Term 23 Year | K10: Yes | L10: Diamond, A, B, C, D, E, F, G, H, I, J, M, N | M10: AG Select-A-Term | N10: Sub type: 23 Year | State: Alabama, Alaska, Arizona, Arkansas, California, Colorado, Connecticut, Delaware, Florida, Georgia, Hawaii, Idaho, Illinois, Indiana, Iowa, Kansas, Kentucky, Louisiana, Maine, Maryland, Massachusetts, Michigan, Minnesota, Mississippi, Missouri, Montana, Nebraska, Nevada, New Hampshire, New Jersey, New Mexico, North Carolina, North Dakota, Ohio, Oklahoma, Oregon, Pennsylvania, Rhode Island, South Carolina, South Dakota, Tennessee, Texas, Utah, Vermont, Virginia, Washington, West Virginia, Wisconsin, Wyoming | P10: 114 | Q10: 95 | R10: 95 | S10: 95 | T10: 95 | U10: 95 | V10: 95 | W10: 95 | X10: 95 | Y10: 95 | Z10: 95 | AA10: 45 | AB10: 40
A11: 10 | B11: L_CORE | C11: TBD | D11: Perm | E11: Non-NY | H11: UL | I11: 120 | J11: AG Select-A-Term 22 Year | K11: Yes | L11: Diamond, A, B, C, D, E, F, G, H, I, J, M, N | M11: AG Select-A-Term | N11: Sub type: 22 Year | State: Alabama, Alaska, Arizona, Arkansas, California, Colorado, Connecticut, Delaware, Florida, Georgia, Hawaii, Idaho, Illinois, Indiana, Iowa, Kansas, Kentucky, Louisiana, Maine, Maryland, Massachusetts, Michigan, Minnesota, Mississippi, Missouri, Montana, Nebraska, Nevada, New Hampshire, New Jersey, New Mexico, North Carolina, North Dakota, Ohio, Oklahoma, Oregon, Pennsylvania, Rhode Island, South Carolina, South Dakota, Tennessee, Texas, Utah, Vermont, Virginia, Washington, West Virginia, Wisconsin, Wyoming | P11: 114 | Q11: 95 | R11: 95 | S11: 95 | T11: 95 | U11: 95 | V11: 95 | W11: 95 | X11: 95 | Y11: 95 | Z11: 95 | AA11: 45 | AB11: 40
A12: 11 | B12: L_CORE | C12: TBD | D12: Perm | E12: Non-NY | H12: IUL | I12: 120 | J12: AG Select-A-Term 21 Year | K12: Yes | L12: Diamond, A, B, C, D, E, F, G, H, I, J, M, N | M12: AG Select-A-Term | N12: Sub type: 21 Year | State: Alabama, Alaska, Arizona, Arkansas, California, Colorado, Connecticut, Delaware, Florida, Georgia, Hawaii, Idaho, Illinois, Indiana, Iowa, Kansas, Kentucky, Louisiana, Maine, Maryland, Massachusetts, Michigan, Minnesota, Mississippi, Missouri, Montana, Nebraska, Nevada, New Hampshire, New Jersey, New Mexico, North Carolina, North Dakota, Ohio, Oklahoma, Oregon, Pennsylvania, Rhode Island, South Carolina, South Dakota, Tennessee, Texas, Utah, Vermont, Virginia, Washington, West Virginia, Wisconsin, Wyoming | P12: 114 | Q12: 95 | R12: 95 | S12: 95 | T12: 95 | U12: 95 | V12: 95 | W12: 95 | X12: 95 | Y12: 95 | Z12: 95 | AA12: 45 | AB12: 40
J13: AG Select-A-Term 20 Year | K13: Yes | L13: Diamond, A, B, C, D, E, F, G, H, I, J, M, N | M13: AG Select-A-Term | N13: Sub type: 20 Year | State: Alabama, Alaska, Arizona, Arkansas, California, Colorado, Connecticut, Delaware, Florida, Georgia, Hawaii, Idaho, Illinois, Indiana, Iowa, Kansas, Kentucky, Louisiana, Maine, Maryland, Massachusetts, Michigan, Minnesota, Mississippi, Missouri, Montana, Nebraska, Nevada, New Hampshire, New Jersey, New Mexico, North Carolina, North Dakota, Ohio, Oklahoma, Oregon, Pennsylvania, Rhode Island, South Carolina, South Dakota, Tennessee, Texas, Utah, Vermont, Virginia, Washington, West Virginia, Wisconsin, Wyoming | P13: 114 | Q13: 95 | R13: 95 | S13: 95 | T13: 95 | U13: 95 | V13: 95 | W13: 95 | X13: 95 | Y13: 95 | Z13: 95 | AA13: 45 | AB13: 40
J14: AG Select-A-Term 19 Year | K14: Yes | L14: Diamond, A, B, C, D, E, F, G, H, I, J, M, N | M14: AG Select-A-Term | N14: Sub type: 19 yr | State: Alabama, Alaska, Arizona, Arkansas, California, Colorado, Connecticut, Delaware, Florida, Georgia, Hawaii, Idaho, Illinois, Indiana, Iowa, Kansas, Kentucky, Louisiana, Maine, Maryland, Massachusetts, Michigan, Minnesota, Mississippi, Missouri, Montana, Nebraska, Nevada, New Hampshire, New Jersey, New Mexico, North Carolina, North Dakota, Ohio, Oklahoma, Oregon, Pennsylvania, Rhode Island, South Carolina, South Dakota, Tennessee, Texas, Utah, Vermont, Virginia, Washington, West Virginia, Wisconsin, Wyoming | P14: 113 | Q14: 94 | R14: 94 | S14: 94 | T14: 94 | U14: 94 | V14: 94 | W14: 94 | X14: 94 | Y14: 94 | Z14: 94 | AA14: 44 | AB14: 39
J15: AG Select-A-Term 18 Year | K15: Yes | L15: Diamond, A, B, C, D, E, F, G, H, I, J, M, N | M15: AG Select-A-Term | N15: Sub type: 18 yr | State: Alabama, Alaska, Arizona, Arkansas, California, Colorado, Connecticut, Delaware, Florida, Georgia, Hawaii, Idaho, Illinois, Indiana, Iowa, Kansas, Kentucky, Louisiana, Maine, Maryland, Massachusetts, Michigan, Minnesota, Mississippi, Missouri, Montana, Nebraska, Nevada, New Hampshire, New Jersey, New Mexico, North Carolina, North Dakota, Ohio, Oklahoma, Oregon, Pennsylvania, Rhode Island, South Carolina, South Dakota, Tennessee, Texas, Utah, Vermont, Virginia, Washington, West Virginia, Wisconsin, Wyoming | P15: 112 | Q15: 93 | R15: 93 | S15: 93 | T15: 93 | U15: 93 | V15: 93 | W15: 93 | X15: 93 | Y15: 93 | Z15: 93 | AA15: 43 | AB15: 38
J16: AG Select-A-Term 17 Year | K16: Yes | L16: Diamond, A, B, C, D, E, F, G, H, I, J, M, N | M16: AG Select-A-Term | N16: Sub type: 17 yr | State: Alabama, Alaska, Arizona, Arkansas, California, Colorado, Connecticut, Delaware, Florida, Georgia, Hawaii, Idaho, Illinois, Indiana, Iowa, Kansas, Kentucky, Louisiana, Maine, Maryland, Massachusetts, Michigan, Minnesota, Mississippi, Missouri, Montana, Nebraska, Nevada, New Hampshire, New Jersey, New Mexico, North Carolina, North Dakota, Ohio, Oklahoma, Oregon, Pennsylvania, Rhode Island, South Carolina, South Dakota, Tennessee, Texas, Utah, Vermont, Virginia, Washington, West Virginia, Wisconsin, Wyoming | P16: 111 | Q16: 92 | R16: 92 | S16: 92 | T16: 92 | U16: 92 | V16: 92 | W16: 92 | X16: 92 | Y16: 92 | Z16: 92 | AA16: 42 | AB16: 37
J17: AG Select-A-Term 16 Year | K17: Yes | L17: Diamond, A, B, C, D, E, F, G, H, I, J, M, N | M17: AG Select-A-Term | N17: Sub type: 16 yr | State: Alabama, Alaska, Arizona, Arkansas, California, Colorado, Connecticut, Delaware, Florida, Georgia, Hawaii, Idaho, Illinois, Indiana, Iowa, Kansas, Kentucky, Louisiana, Maine, Maryland, Massachusetts, Michigan, Minnesota, Mississippi, Missouri, Montana, Nebraska, Nevada, New Hampshire, New Jersey, New Mexico, North Carolina, North Dakota, Ohio, Oklahoma, Oregon, Pennsylvania, Rhode Island, South Carolina, South Dakota, Tennessee, Texas, Utah, Vermont, Virginia, Washington, West Virginia, Wisconsin, Wyoming | P17: 110 | Q17: 91 | R17: 91 | S17: 91 | T17: 91 | U17: 91 | V17: 91 | W17: 91 | X17: 91 | Y17: 91 | Z17: 91 | AA17: 41 | AB17: 36
J18: AG Select-A-Term 15 Year | K18: Yes | L18: Diamond, A, B, C, D, E, F, G, H, I, J, M, N | M18: AG Select-A-Term | N18: Sub type: 15 yr | State: Alabama, Alaska, Arizona, Arkansas, California, Colorado, Connecticut, Delaware, Florida, Georgia, Hawaii, Idaho, Illinois, Indiana, Iowa, Kansas, Kentucky, Louisiana, Maine, Maryland, Massachusetts, Michigan, Minnesota, Mississippi, Missouri, Montana, Nebraska, Nevada, New Hampshire, New Jersey, New Mexico, North Carolina, North Dakota, Ohio, Oklahoma, Oregon, Pennsylvania, Rhode Island, South Carolina, South Dakota, Tennessee, Texas, Utah, Vermont, Virginia, Washington, West Virginia, Wisconsin, Wyoming | P18: 109 | Q18: 90 | R18: 90 | S18: 90 | T18: 90 | U18: 90 | V18: 90 | W18: 90 | X18: 90 | Y18: 90 | Z18: 90 | AA18: 40 | AB18: 35
J19: AG Select-A-Term 10 Year | K19: Yes | L19: Diamond, A, B, C, D, E, F, G, H, I, J, M, N | M19: AG Select-A-Term | N19: Sub type: 10 yr | State: Alabama, Alaska, Arizona, Arkansas, California, Colorado, Connecticut, Delaware, Florida, Georgia, Hawaii, Idaho, Illinois, Indiana, Iowa, Kansas, Kentucky, Louisiana, Maine, Maryland, Massachusetts, Michigan, Minnesota, Mississippi, Missouri, Montana, Nebraska, Nevada, New Hampshire, New Jersey, New Mexico, North Carolina, North Dakota, Ohio, Oklahoma, Oregon, Pennsylvania, Rhode Island, South Carolina, South Dakota, Tennessee, Texas, Utah, Vermont, Virginia, Washington, West Virginia, Wisconsin, Wyoming | P19: 99 | Q19: 80 | R19: 80 | S19: 80 | T19: 80 | U19: 80 | V19: 80 | W19: 80 | X19: 80 | Y19: 80 | Z19: 80 | AA19: 30 | AB19: 25
J20: AG Secure Lifetime GUL 3 | K20: Yes | L20: Diamond, A, B, C, D, E, F, G, H, I, J, M, N | M20: AG Secure Lifetime GUL 3 | N20: Sub type: AG Secure Lifetime GUL 3 | State: Alabama, Alaska, Arizona, Arkansas, California, Colorado, Connecticut, Delaware, Florida, Georgia, Hawaii, Idaho, Illinois, Indiana, Iowa, Kansas, Kentucky, Louisiana, Maine, Maryland, Massachusetts, Michigan, Minnesota, Mississippi, Missouri, Montana, Nebraska, Nevada, New Hampshire, New Jersey, New Mexico, North Carolina, North Dakota, Ohio, Oklahoma, Oregon, Pennsylvania, Rhode Island, South Carolina, South Dakota, Tennessee, Texas, Utah, Vermont, Virginia, Washington, West Virginia, Wisconsin, Wyoming | P20: 99 | Q20: 80 | R20: 80 | S20: 80 | T20: 80 | U20: 80 | V20: 80 | W20: 80 | X20: 80 | Y20: 80 | Z20: 80 | AA20: 30 | AB20: 25
J21: Max Accumulator+ IUL II and III | K21: Yes | L21: Diamond, A, B, C, D, E, F, G, H, I, J, M, N | M21: Max Accumulator+ IUL II and III | N21: Sub type: Max Accumulator+ IUL II and III | State: Alabama, Alaska, Arizona, Arkansas, California, Colorado, Connecticut, Delaware, Florida, Georgia, Hawaii, Idaho, Illinois, Indiana, Iowa, Kansas, Kentucky, Louisiana, Maine, Maryland, Massachusetts, Michigan, Minnesota, Mississippi, Missouri, Montana, Nebraska, Nevada, New Hampshire, New Jersey, New Mexico, North Carolina, North Dakota, Ohio, Oklahoma, Oregon, Pennsylvania, Rhode Island, South Carolina, South Dakota, Tennessee, Texas, Utah, Vermont, Virginia, Washington, West Virginia, Wisconsin, Wyoming | P21: 109 | Q21: 80 | R21: 80 | S21: 80 | T21: 80 | U21: 80 | V21: 80 | W21: 80 | X21: 80 | Y21: 80 | Z21: 80 | AA21: 30 | AB21: 25
J22: Max Accumulator+ IUL III with ECV Rider | K22: No | L22: Diamond, A, B, C, D, E, F, G, H, I, J, M, N | M22: Max Accumulator+ IUL III with ECV Rider | N22: Sub type: Max Accumulator+ IUL III with ECV Rider | State: Alabama, Alaska, Arizona, Arkansas, California, Colorado, Connecticut, Delaware, Florida, Georgia, Hawaii, Idaho, Illinois, Indiana, Iowa, Kansas, Kentucky, Louisiana, Maine, Maryland, Massachusetts, Michigan, Minnesota, Mississippi, Missouri, Montana, Nebraska, Nevada, New Hampshire, New Jersey, New Mexico, North Carolina, North Dakota, Ohio, Oklahoma, Oregon, Pennsylvania, Rhode Island, South Carolina, South Dakota, Tennessee, Texas, Utah, Vermont, Virginia, Washington, West Virginia, Wisconsin, Wyoming | Q22: 19 | R22: 19 | S22: 19 | T22: 19 | U22: 19 | V22: 19 | W22: 19 | X22: 19 | Y22: 19 | Z22: 19 | AA22: 10 | AB22: 10
J23: Value+ Protector II | K23: Yes | L23: Diamond, A, B, C, D, E, F, G, H, I, J, M, N | M23: Value+ Protector II | N23: Sub type: Value+ Protector II | State: Alabama, Alaska, Arizona, Arkansas, California, Colorado, Connecticut, Delaware, Florida, Georgia, Hawaii, Idaho, Illinois, Indiana, Iowa, Kansas, Kentucky, Louisiana, Maine, Maryland, Massachusetts, Michigan, Minnesota, Mississippi, Missouri, Montana, Nebraska, Nevada, New Hampshire, New Jersey, New Mexico, North Carolina, North Dakota, Ohio, Oklahoma, Oregon, Pennsylvania, Rhode Island, South Carolina, South Dakota, Tennessee, Texas, Utah, Vermont, Virginia, Washington, West Virginia, Wisconsin, Wyoming | P23: 99 | Q23: 80 | R23: 80 | S23: 80 | T23: 80 | U23: 80 | V23: 80 | W23: 80 | X23: 80 | Y23: 80 | Z23: 80 | AA23: 30 | AB23: 25
J24: Protection Extend IUL (Conversions Only) | K24: Yes | L24: Diamond, A, B, C, D, E, F, G, H, I, J, M, N | M24: Protection Extend IUL (Conversions Only) | N24: Sub type: (Conversions Only) | State: Alabama, Alaska, Arizona, Arkansas, California, Colorado, Connecticut, Delaware, Florida, Georgia, Hawaii, Idaho, Illinois, Indiana, Iowa, Kansas, Kentucky, Louisiana, Maine, Maryland, Massachusetts, Michigan, Minnesota, Mississippi, Missouri, Montana, Nebraska, Nevada, New Hampshire, New Jersey, New Mexico, North Carolina, North Dakota, Ohio, Oklahoma, Oregon, Pennsylvania, Rhode Island, South Carolina, South Dakota, Tennessee, Texas, Utah, Vermont, Virginia, Washington, West Virginia, Wisconsin, Wyoming | P24: 34 | Q24: 33 | R24: 33 | S24: 33 | T24: 33 | U24: 33 | V24: 33 | W24: 33 | X24: 33 | Y24: 33 | Z24: 33 | AA24: 0 | AB24: 0

Sheet L-CORENY
A1: Row | B1: Service-Carrier ID | C1: Product Tier | D1: Types | E1: State Available | F1: Old Product name | G1: Sub-Name | H1: Sub-type | I1: Length | J1: Product Name Full | K1: Product Real | L1: All Vendor paycodes | M1: Product | N1: Criteria | O1: Notes | P1: Diamond | Q1: Producer
A2: 1 | B2: L_CORENY | C2: TBD | D2: Perm | E2: NY | F2: Max Accumulator+ II | G2: Personally Produced | H2: TBD | J2: Max Accumulator+ II (NY) (Personally Produced) | K2: Yes | L2: Diamond, Producer | M2: Max Accumulator+ II | N2: Sub type: Max Accumulator+ II Sub Name: Personally Produced | State: New York | P2: 65 | Q2: 50
A3: 2 | B3: L_CORENY | C3: TBD | D3: Perm | E3: NY | F3: Year 2 | H3: TBD | J3: Max Accumulator+ II (NY) (Personally Produced)(Year 2 ) | K3: No | L3: Diamond, Producer | M3: Year 2 | N3: Renewal year: 2 | State: New York | Q3: 8
A4: 3 | B4: L_CORENY | C4: TBD | D4: Perm | E4: NY | F4: Year 3 | H4: TBD | J4: Max Accumulator+ II (NY)(Personally Produced)(Year 3) | K4: No | L4: Diamond, Producer | M4: Year 3 | N4: Renewal year: 3 | State: New York | Q4: 5
A5: 4 | B5: L_CORENY | C5: TBD | D5: Perm | E5: NY | F5: Year 4 | H5: TBD | J5: Max Accumulator+ II (NY)(Personally Produced)(Year 4) | K5: No | L5: Diamond, Producer | M5: Year 4 | N5: Renewal year: 4 | State: New York | Q5: 1.5
A6: 5 | B6: L_CORENY | C6: TBD | D6: Perm | E6: NY | F6: Year 5 | H6: TBD | J6: Max Accumulator+ II (NY)(Personally Produced)(Year 5) | K6: No | L6: Diamond, Producer | M6: Year 5 | N6: Renewal year: 5 | State: New York | Q6: 1.5
A7: 6 | B7: L_CORENY | C7: TBD | D7: Perm | E7: NY | F7: Years 6-10 | H7: TBD | J7: Max Accumulator+ II (NY)(Personally Produced)(Years 6-10) | K7: No | L7: Diamond, Producer | M7: Years 6-10 | N7: Renewal year: 6 to 10 | State: New York | Q7: 1.5
A8: 7 | B8: L_CORENY | C8: TBD | D8: Perm | E8: NY | F8: Excess (Year 1-10) | H8: TBD | J8: Max Accumulator+ II ( NY)(Personally Produced)(Year 1-10) | K8: No | L8: Diamond, Producer | M8: Excess (Year 1-10) | O8: Product Name: Excess (Year 1-10) | Q8: 1.5
A9: 8 | B9: L_CORENY | C9: TBD | D9: Perm | E9: NY | F9: Max Accumulator+ II | G9: Non-Personally Produced | H9: TBD | J9: Max Accumulator+ II (NY) (Non-Personally Produced) | K9: Yes | L9: Diamond, Producer | M9: Max Accumulator+ II | N9: Sub type: Max Accumulator+ II Sub Name: Non-Personally Produced | State: New York | O9: Type: Perm State: NY Product Name: Max Accumulator+ II Sub Name: Non-Personally Produced | P9: 73 | Q9: 50
A10: 9 | B10: L_CORENY | C10: TBD | D10: Perm | E10: NY | F10: Year 2 | H10: TBD | J10: Max Accumulator+ II (NY)(Non-Personally Produced)(Year 2) | K10: No | L10: Diamond, Producer | M10: Year 2 | N10: Renewal year: 2 | State: New York | O10: Product Name: Year 2 | Q10: 8
A11: 10 | B11: L_CORENY | C11: TBD | D11: Perm | E11: NY | F11: Year 3 | H11: TBD | J11: Max Accumulator+ II (NY)(Non-Personally Produced)(Year 3) | K11: No | L11: Diamond, Producer | M11: Year 3 | N11: Renewal year: 3 | State: New York | O11: Product Name: Year 3 | Q11: 5
A12: 11 | B12: L_CORENY | C12: TBD | D12: Perm | E12: NY | F12: Year 4 | H12: TBD | J12: Max Accumulator+ II (NY)(Non-Personally Produced)(Year 4) | K12: No | L12: Diamond, Producer | M12: Year 4 | N12: Renewal year: 4 | State: New York | O12: Product Name: Year 4 | Q12: 1.5
A13: 12 | B13: L_CORENY | C13: TBD | D13: Perm | E13: NY | F13: Year 5 | H13: TBD | J13: Max Accumulator+ II (NY)(Non-Personally Produced)(Year 5 ) | K13: No | L13: Diamond, Producer | M13: Year 5 | N13: Renewal year: 5 | State: New York | O13: Product Name: Year 5 | Q13: 1.5
A14: 13 | B14: L_CORENY | C14: TBD | D14: Perm | E14: NY | F14: Years 6-10 | H14: TBD | J14: Max Accumulator+ II (NY)(Non-Personally Produced)(Year 6-10) | K14: No | L14: Diamond, Producer | M14: Years 6-10 | N14: Renewal year: 6 to 10 | State: New York | O14: Product Name: Years 6-10 | Q14: 1.5
A15: 14 | B15: L_CORENY | C15: TBD | D15: Perm | E15: NY | F15: Excess (Year 1-10) | H15: TBD | J15: Max Accumulator+ II (NY)(Non-Personally Produced) (Excess Year 1-10) | K15: No | L15: Diamond, Producer | M15: Excess (Year 1-10) | O15: Product Name: Excess (Year 1-10) | Q15: 1.5
A16: 15 | B16: L_CORENY | C16: TBD | D16: Perm | E16: NY | F16: Value+ Protector II | G16: Personally Produced | H16: TBD | J16: Value+ Protector II (NY)( Personally Produced) | K16: Yes | L16: Diamond, Producer | M16: Value+ Protector II | N16: Sub type: Value+ Protector II Sub Name: Personally Produced | State: New York | P16: 65 | Q16: 50
A17: 16 | B17: L_CORENY | C17: TBD | D17: Perm | E17: NY | F17: Year 2 | H17: TBD | J17: Value+ Protector II (NY) ( Personally Produced)(Year 2) | K17: No | L17: Diamond, Producer | M17: Year 2 | N17: Renewal year: 2 | State: New York | Q17: 8
A18: 17 | B18: L_CORENY | C18: TBD | D18: Perm | E18: NY | F18: Year 3 | H18: TBD | J18: Value+ Protector II (NY)( Personally Produced)(Year 3) | K18: No | L18: Diamond, Producer | M18: Year 3 | N18: Renewal year: 3 | State: New York | Q18: 5
A19: 18 | B19: L_CORENY | C19: TBD | D19: Perm | E19: NY | F19: Year 4 | H19: TBD | J19: Value+ Protector II (NY)( Personally Produced)(Year 4) | K19: No | L19: Diamond, Producer | M19: Year 4 | N19: Renewal year: 4 | State: New York | Q19: 1.5
A20: 19 | B20: L_CORENY | C20: TBD | D20: Perm | E20: NY | F20: Year 5 | H20: TBD | J20: Value+ Protector II (NY) ( Personally Produced) (Year 5) | K20: No | L20: Diamond, Producer | M20: Year 5 | N20: Renewal year: 5 | State: New York | Q20: 1.5
A21: 20 | B21: L_CORENY | C21: TBD | D21: Perm | E21: NY | F21: Years 6-10 | H21: TBD | J21: Value+ Protector II (NY)( Personally Produced)(Year 6-10) | K21: No | L21: Diamond, Producer | M21: Years 6-10 | N21: Renewal year: 6 to 10 | State: New York | Q21: 1.5
A22: 21 | B22: L_CORENY | C22: TBD | D22: Perm | E22: NY | F22: Excess (Years 1-10) | H22: TBD | J22: Value+ Protector II (NY)( Personally Produced)( Excess Years 1-10) | K22: No | L22: Diamond, Producer | M22: Excess (Years 1-10) | O22: Product Name: Excess (Years 1-10) | Q22: 1.5
A23: 22 | B23: L_CORENY | C23: TBD | D23: Perm | E23: NY | F23: Value+ Protector II | G23: Non-Personally Produced | H23: TBD | J23: Value+ Protector II (NY)( Non-Personally Produced) | K23: Yes | L23: Diamond, Producer | M23: Value+ Protector II | N23: Sub type: Value+ Protector II Sub Name: Non-Personally Produced | State: New York | P23: 73 | Q23: 50
A24: 23 | B24: L_CORENY | C24: TBD | D24: Perm | E24: NY | F24: Year 2 | H24: TBD | J24: Value+ Protector II (NY)( Non-Personally Produced)(Year 2) | K24: No | L24: Diamond, Producer | M24: Year 2 | N24: Renewal year: 2 | State: New York | Q24: 8
A25: 24 | B25: L_CORENY | C25: TBD | D25: Perm | E25: NY | F25: Year 3 | H25: TBD | J25: Value+ Protector II (NY)( Non-Personally Produced)( Year 3) | K25: No | L25: Diamond, Producer | M25: Year 3 | N25: Renewal year: 3 | State: New York | Q25: 5
A26: 25 | B26: L_CORENY | C26: TBD | D26: Perm | E26: NY | F26: Year 4 | H26: TBD | J26: Value+ Protector II (NY)( Non-Personally Produced)( Year 4) | K26: No | L26: Diamond, Producer | M26: Year 4 | N26: Renewal year: 4 | State: New York | Q26: 1.5
A27: 26 | B27: L_CORENY | C27: TBD | D27: Perm | E27: NY | F27: Year 5 | H27: TBD | J27: Value+ Protector II (NY)( Non-Personally Produced) ( Year 5) | K27: No | L27: Diamond, Producer | M27: Year 5 | N27: Renewal year: 5 | State: New York | Q27: 1.5
A28: 27 | B28: L_CORENY | C28: TBD | D28: Perm | E28: NY | F28: Years 6-10 | H28: TBD | J28: Value+ Protector II (NY)( Non-Personally Produced) ( Year 6-10) | K28: No | L28: Diamond, Producer | M28: Years 6-10 | N28: Renewal year: 6 to 10 | State: New York | Q28: 1.5
A29: 28 | B29: L_CORENY | C29: TBD | D29: Perm | E29: NY | F29: Excess (Years 1-10) | H29: TBD | J29: Value+ Protector II (NY)( Non-Personally Produced) (Excess Years 1-10) | K29: No | L29: Diamond, Producer | M29: Excess (Years 1-10) | O29: Product Name: Excess (Years 1-10) | Q29: 1.5
A30: 29 | B30: L_CORENY | C30: TBD | D30: Perm | E30: NY | F30: Protection Extend IUL | G30: Personally Produced | H30: TBD | J30: Protection Extend IUL (NY) (Personally Produced) | K30: Yes | L30: Diamond, Producer | M30: Protection Extend IUL | O30: Type: Perm State: NY Product Name: Protection Extend IUL Sub Name: Personally Produced | P30: 35 | Q30: 35
A31: 30 | B31: L_CORENY | C31: TBD | D31: Perm | E31: NY | F31: Year 2 | H31: TBD | J31: Protection Extend IUL (NY) (Personally Produced)(Year 2) | K31: No | L31: Diamond, Producer | M31: Year 2 | O31: Product Name: Year 2 | Q31: 35
A32: 31 | B32: L_CORENY | C32: TBD | D32: Perm | E32: NY | F32: Year 3 | H32: TBD | J32: Protection Extend IUL (NY) (Personally Produced)(Year 3) | K32: No | L32: Diamond, Producer | M32: Year 3 | O32: Product Name: Year 3 | Q32: 35
A33: 32 | B33: L_CORENY | C33: TBD | D33: Perm | E33: NY | F33: Year 4 | H33: TBD | J33: Protection Extend IUL (NY) (Personally Produced)(Year 4) | K33: No | L33: Diamond, Producer | M33: Year 4 | O33: Product Name: Year 4 | Q33: 0
A34: 33 | B34: L_CORENY | C34: TBD | D34: Perm | E34: NY | F34: Year 5 | H34: TBD | J34: Protection Extend IUL (NY) (Personally Produced)(Year 5) | K34: No | L34: Diamond, Producer | M34: Year 5 | O34: Product Name: Year 5 | Q34: 0
A35: 34 | B35: L_CORENY | C35: TBD | D35: Perm | E35: NY | F35: Years 6-10 | H35: TBD | J35: Protection Extend IUL (NY) (Personally Produced)(Year 6-10) | K35: No | L35: Diamond, Producer | M35: Years 6-10 | O35: Product Name: Years 6-10 | Q35: 0
A36: 35 | B36: L_CORENY | C36: TBD | D36: Perm | E36: NY | F36: Excess (Year 1-2) | H36: TBD | J36: Protection Extend IUL(NY)(Personally Produced)(Excess Year 1-2) | K36: No | L36: Diamond, Producer | M36: Excess (Year 1-2) | O36: Product Name: Excess (Year 1-2) | Q36: 2
A37: 36 | B37: L_CORENY | C37: TBD | D37: Perm | E37: NY | F37: Excess (Year 3-10) | H37: TBD | J37: Protection Extend IUL(NY)(Personally Produced)(Excess Year 3-10) | K37: No | L37: Diamond, Producer | M37: Excess (Year 3-10) | O37: Product Name: Excess (Year 3-10) | Q37: 1
A38: 37 | B38: L_CORENY | C38: TBD | D38: Perm | E38: NY | F38: Protection Extend IUL | G38: Non-Personally Produced | H38: TBD | J38: Protection Extend IUL (NY) ( Non - Personally Produced) | K38: Yes | L38: Diamond, Producer | M38: Protection Extend IUL | O38: Type: Perm State: NY Product Name: Protection Extend IUL Sub Name: Non-Personally Produced | P38: 35 | Q38: 35
A39: 38 | B39: L_CORENY | C39: TBD | D39: Perm | E39: NY | F39: Year 2 | H39: TBD | J39: Protection Extend IUL (NY) ( Non - Personally Produced) (Year 2) | K39: No | L39: Diamond, Producer | M39: Year 2 | O39: Product Name: Year 2 | Q39: 35
A40: 39 | B40: L_CORENY | C40: TBD | D40: Perm | E40: NY | F40: Year 3 | H40: TBD | J40: Protection Extend IUL (NY) ( Non - Personally Produced) (Year 3) | K40: No | L40: Diamond, Producer | M40: Year 3 | O40: Product Name: Year 3 | Q40: 35
A41: 40 | B41: L_CORENY | C41: TBD | D41: Perm | E41: NY | F41: Year 4 | H41: TBD | J41: Protection Extend IUL (NY) ( Non - Personally Produced) (Year 4) | K41: No | L41: Diamond, Producer | M41: Year 4 | O41: Product Name: Year 4 | Q41: 0
A42: 41 | B42: L_CORENY | C42: TBD | D42: Perm | E42: NY | F42: Year 5 | H42: TBD | J42: Protection Extend IUL (NY) ( Non - Personally Produced) (Year 5) | K42: No | L42: Diamond, Producer | M42: Year 5 | O42: Product Name: Year 5 | Q42: 0
A43: 42 | B43: L_CORENY | C43: TBD | D43: Perm | E43: NY | F43: Years 6-10 | H43: TBD | J43: Protection Extend IUL (NY) ( Non - Personally Produced) (Year 6-10) | K43: No | L43: Diamond, Producer | M43: Years 6-10 | O43: Product Name: Years 6-10 | Q43: 0
A44: 43 | B44: L_CORENY | C44: TBD | D44: Perm | E44: NY | F44: Excess (Year 1-2) | H44: TBD | J44: Protection Extend IUL (NY)( Non - Personally Produced) (Excess Years 1-2) | K44: No | L44: Diamond, Producer | M44: Excess (Year 1-2) | O44: Product Name: Excess (Year 1-2) | Q44: 2
A45: 44 | B45: L_CORENY | C45: TBD | D45: Perm | E45: NY | F45: Excess (Year 3-10) | H45: TBD | J45: Protection Extend IUL (NY)( Non - Personally Produced) (Excess Years 3-10) | K45: No | L45: Diamond, Producer | M45: Excess (Year 3-10) | O45: Product Name: Excess (Year 3-10) | Q45: 1
A46: 45 | B46: L_CORENY | C46: TBD | D46: Perm | E46: NY | F46: AG Secure Lifetime GUL 3 | G46: Personally Produced | H46: TBD | J46: AG Secure Lifetime GUL 3 (NY) (Personally Produced) | K46: Yes | L46: Diamond, Producer | M46: AG Secure Lifetime GUL 3 | N46: Sub type: AG Secure Lifetime GUL 3 Sub Name: Personally Produced | State: New York | P46: 65 | Q46: 50
A47: 46 | B47: L_CORENY | C47: TBD | D47: Perm | E47: NY | F47: Year 2 | H47: TBD | J47: AG Secure Lifetime GUL 3 (NY)(Personally Produced)(Year 2) | K47: No | L47: Diamond, Producer | M47: Year 2 | N47: Renewal year: 2 | State: New York | Q47: 5
A48: 47 | B48: L_CORENY | C48: TBD | D48: Perm | E48: NY | H48: TBD | J48: AG Secure Lifetime GUL 3 (NY)(Personally Produced)(Year 3) | K48: No | L48: Diamond, Producer | M48: Year 3 | N48: Renewal year: 3 | State: New York | Q48: 3
A49: 48 | B49: L_CORENY | C49: TBD | D49: Perm | E49: NY | F49: Year 3 | H49: TBD | J49: AG Secure Lifetime GUL 3 (NY)(Personally Produced)(Year 4) | K49: No | L49: Diamond, Producer | M49: Year 4 | N49: Renewal year: 4 | State: New York | Q49: 1.5
A50: 49 | B50: L_CORENY | C50: TBD | D50: Perm | E50: NY | F50: Year 5 | H50: TBD | J50: AG Secure Lifetime GUL 3 (NY)(Personally Produced)(Year 5) | K50: No | L50: Diamond, Producer | M50: Year 5 | N50: Renewal year: 5 | State: New York | Q50: 1.5
A51: 50 | B51: L_CORENY | C51: TBD | D51: Perm | E51: NY | F51: Years 6-10 | H51: TBD | J51: AG Secure Lifetime GUL 3 (NY)(Personally Produced)(Year 6-10) | K51: No | L51: Diamond, Producer | M51: Years 6-10 | N51: Renewal year: 6 to 10 | State: New York | Q51: 1.5
A52: 51 | B52: L_CORENY | C52: TBD | D52: Perm | E52: NY | F52: Excess (Years 1-10) | H52: TBD | J52: AG Secure Lifetime GUL 3 (NY)(Personally Produced) (Excess Years 1-10) | K52: No | L52: Diamond, Producer | M52: Excess (Years 1-10) | O52: Product Name: Excess (Years 1-10) | Q52: 1.5
A53: 52 | B53: L_CORENY | C53: TBD | D53: Perm | E53: NY | F53: AG Secure Lifetime GUL 3 | G53: Non-Personally Produced | H53: TBD | J53: AG Secure Lifetime GUL 3 (NY) (Non-Personally Produced) | K53: Yes | L53: Diamond, Producer | M53: AG Secure Lifetime GUL 3 | O53: Type: Perm State: NY Product Name: AG Secure Lifetime GUL 3 Sub Name: Non-Personally Produced | P53: 73 | Q53: 50
A54: 53 | B54: L_CORENY | C54: TBD | D54: Perm | E54: NY | F54: Year 2 | H54: TBD | J54: AG Secure Lifetime GUL 3 (NY) (Non-Personally Produced) (Year 2) | K54: No | L54: Diamond, Producer | M54: Year 2 | O54: Product Name: Year 2 | Q54: 8
A55: 54 | B55: L_CORENY | C55: TBD | D55: Perm | E55: NY | F55: Year 3 | H55: TBD | J55: AG Secure Lifetime GUL 3 (NY) (Non-Personally Produced) (Year 3) | K55: No | L55: Diamond, Producer | M55: Year 3 | O55: Product Name: Year 3 | Q55: 5
A56: 55 | B56: L_CORENY | C56: TBD | D56: Perm | E56: NY | F56: Year 4 | H56: TBD | J56: AG Secure Lifetime GUL 3 (NY) (Non-Personally Produced) (Year 4) | K56: No | L56: Diamond, Producer | M56: Year 4 | O56: Product Name: Year 4 | Q56: 1.5
A57: 56 | B57: L_CORENY | C57: TBD | D57: Perm | E57: NY | F57: Year 5 | H57: TBD | J57: AG Secure Lifetime GUL 3 (NY) (Non-Personally Produced) (Year 5) | K57: No | L57: Diamond, Producer | M57: Year 5 | O57: Product Name: Year 5 | Q57: 1.5
A58: 57 | B58: L_CORENY | C58: TBD | D58: Perm | E58: NY | F58: Years 6-10 | H58: TBD | J58: AG Secure Lifetime GUL 3 (NY) (Non-Personally Produced) (Year 6-10) | K58: No | L58: Diamond, Producer | M58: Years 6-10 | O58: Product Name: Years 6-10 | Q58: 1.5
A59: 58 | B59: L_CORENY | C59: TBD | D59: Perm | E59: NY | F59: Excess (Years 1-10) | H59: TBD | J59: AG Secure Lifetime GUL 3 (NY)(Non-Personally Produced)( Excess Years 1-10) | K59: No | L59: Diamond, Producer | M59: Excess (Years 1-10) | O59: Product Name: Excess (Years 1-10) | Q59: 1.5
A60: 59 | B60: L_CORENY | C60: TBD | D60: Term | E60: NY | F60: AG Select-a-Term 10 Year | G60: Personally Produced | H60: TBD | J60: AG Select-a-Term 10 Year (NY)( Personally Produced) | K60: Yes | L60: Diamond, Producer | M60: AG Select-a-Term 10 Year | N60: Sub type: 10 Year Sub Name: Personally Produced | State: New York | P60: 65 | Q60: 40
A61: 60 | B61: L_CORENY | C61: TBD | D61: Term | E61: NY | F61: Year 2 | H61: TBD | J61: AG Select-a-Term 10 Year (NY)( Personally Produced)(Year 2) | K61: No | L61: Diamond, Producer | M61: Year 2 | N61: Renewal year: 2 | State: New York | Q61: 4
A62: 61 | B62: L_CORENY | C62: TBD | D62: Term | E62: NY | F62: Year 3 | H62: TBD | J62: AG Select-a-Term 10 Year (NY)( Personally Produced)(Year 3) | K62: No | L62: Diamond, Producer | M62: Year 3 | N62: Renewal year: 3 | State: New York | Q62: 0
A63: 62 | B63: L_CORENY | C63: TBD | D63: Term | E63: NY | F63: Year 4 | H63: TBD | J63: AG Select-a-Term 10 Year (NY)( Personally Produced) (Year 4) | K63: No | L63: Diamond, Producer | M63: Year 4 | N63: Renewal year: 4 | State: New York | Q63: 0
A64: 63 | B64: L_CORENY | C64: TBD | D64: Term | E64: NY | F64: Year 5 | H64: TBD | J64: AG Select-a-Term 10 Year (NY)( Personally Produced)(Year 5) | K64: No | L64: Diamond, Producer | M64: Year 5 | N64: Renewal year: 5 | State: New York | Q64: 0
A65: 64 | B65: L_CORENY | C65: TBD | D65: Term | E65: NY | F65: AG Select-a-Term 10 Year | G65: Non(Personally Produced | H65: TBD | J65: AG Select-a-Term 10 Year (NY) (Non-Personally Produced) | K65: Yes | L65: Diamond, Producer | M65: AG Select-a-Term 10 Year | N65: Sub type: 10 Year Sub Name: Non-Personally Produced | State: New York | P65: 73 | Q65: 40
A66: 65 | B66: L_CORENY | C66: TBD | D66: Term | E66: NY | F66: Year 2 | H66: TBD | J66: AG Select(a(Term 10 Year (NY)(Non-Personally Produced) (Year 2) | K66: No | L66: Diamond, Producer | M66: Year 2 | N66: Renewal year: 2 | State: New York | Q66: 4
A67: 66 | B67: L_CORENY | C67: TBD | D67: Term | E67: NY | F67: Year 3 | H67: TBD | J67: AG Select(a(Term 10 Year (NY)(Non-Personally Produced)(Year 3) | K67: No | L67: Diamond, Producer | M67: Year 3 | N67: Renewal year: 3 | State: New York | Q67: 0
A68: 67 | B68: L_CORENY | C68: TBD | D68: Term | E68: NY | F68: Year 4 | H68: TBD | J68: AG Select(a(Term 10 Year (NY)(Non-Personally Produced)(Year 4) | K68: No | L68: Diamond, Producer | M68: Year 4 | N68: Renewal year: 4 | State: New York | Q68: 0
A69: 68 | B69: L_CORENY | C69: TBD | D69: Term | E69: NY | F69: Year 5 | H69: TBD | J69: AG Select(a(Term 10 Year (NY)(Non-Personally Produced)(Year 5) | K69: No | L69: Diamond, Producer | M69: Year 5 | N69: Renewal year: 5 | State: New York | Q69: 0
A70: 69 | B70: L_CORENY | C70: TBD | D70: Term | E70: NY | F70: AG Select-a-Term 15-19 Years | G70: Personally Produced | H70: TBD | J70: AG Select-a-Term 15-19 Years (NY) (Personally Produced) | K70: Yes | L70: Diamond, Producer | M70: AG Select-a-Term 15-19 Years | O70: Type: Term State: NY Product Name: AG Select-a-Term 15-19 Years Sub Name: Personally Produced | P70: 65 | Q70: 40
A71: 70 | B71: L_CORENY | C71: TBD | D71: Term | E71: NY | F71: Year 2 | H71: TBD | J71: AG Select-a-Term 15-19 Years (NY) (Personally Produced) (Year 2) | K71: No | L71: Diamond, Producer | M71: Year 2 | O71: Product Name: Year 2 | Q71: 4
A72: 71 | B72: L_CORENY | C72: TBD | D72: Term | E72: NY | F72: Year 3 | H72: TBD | J72: AG Select-a-Term 15-19 Years (NY) (Personally Produced) (Year 3) | K72: No | L72: Diamond, Producer | M72: Year 3 | O72: Product Name: Year 3 | Q72: 2
A73: 72 | B73: L_CORENY | C73: TBD | D73: Term | E73: NY | F73: Year 4 | H73: TBD | J73: AG Select-a-Term 15-19 Years (NY) (Personally Produced) (Year 4) | K73: No | L73: Diamond, Producer | M73: Year 4 | O73: Product Name: Year 4 | Q73: 1
A74: 73 | B74: L_CORENY | C74: TBD | D74: Term | E74: NY | F74: Year 5 | H74: TBD | J74: AG Select-a-Term 15-19 Years (NY) (Personally Produced) (Year 5) | K74: No | L74: Diamond, Producer | M74: Year 5 | O74: Product Name: Year 5 | Q74: 1
A75: 74 | B75: L_CORENY | C75: TBD | D75: Term | E75: NY | F75: Years 6-10 | H75: TBD | J75: AG Select-a-Term 15-19 Years (NY) (Personally Produced) (Year 6-10) | K75: No | L75: Diamond, Producer | M75: Years 6-10 | O75: Product Name: Years 6-10 | Q75: 1
A76: 75 | B76: L_CORENY | C76: TBD | D76: Term | E76: NY | F76: AG Select-a-Term 15-19 Years | G76: Non-Personally Produced | H76: TBD | J76: AG Select-a-Term 15-19 Years (NY) (Non-Personally Produced) | K76: Yes | L76: Diamond, Producer | M76: AG Select-a-Term 15-19 Years | O76: Type: Term State: NY Product Name: AG Select-a-Term 15-19 Years Sub Name: Non-Personally Produced | P76: 73 | Q76: 40
A77: 76 | B77: L_CORENY | C77: TBD | D77: Term | E77: NY | F77: Year 2 | H77: TBD | J77: AG Select-a-Term 15-19 Years (NY) (Non-Personally Produced)(Year 2) | K77: No | L77: Diamond, Producer | M77: Year 2 | O77: Product Name: Year 2 | Q77: 4
A78: 77 | B78: L_CORENY | C78: TBD | D78: Term | E78: NY | F78: Year 3 | H78: TBD | J78: AG Select-a-Term 15-19 Years (NY) (Non-Personally Produced)(Year 3) | K78: No | L78: Diamond, Producer | M78: Year 3 | O78: Product Name: Year 3 | Q78: 2
A79: 78 | B79: L_CORENY | C79: TBD | D79: Term | E79: NY | F79: Year 4 | H79: TBD | J79: AG Select-a-Term 15-19 Years (NY) (Non-Personally Produced)(Year 4) | K79: No | L79: Diamond, Producer | M79: Year 4 | O79: Product Name: Year 4 | Q79: 1
A80: 79 | B80: L_CORENY | C80: TBD | D80: Term | E80: NY | F80: Year 5 | H80: TBD | J80: AG Select-a-Term 15-19 Years (NY) (Non-Personally Produced)(Year5) | K80: No | L80: Diamond, Producer | M80: Year 5 | O80: Product Name: Year 5 | Q80: 1
A81: 80 | B81: L_CORENY | C81: TBD | D81: Term | E81: NY | F81: Years 6-10 | H81: TBD | J81: AG Select-a-Term 15-19 Years (NY) (Non-Personally Produced)(Year 6-10) | K81: No | L81: Diamond, Producer | M81: Years 6-10 | O81: Product Name: Years 6-10 | Q81: 1
A82: 81 | B82: L_CORENY | C82: TBD | D82: Term | E82: NY | F82: AG Select-a-Term 20-30 - 35 Years | G82: Personally Produced | H82: TBD | J82: AG Select-a-Term 20-30 - 35 Years (NY) (Personally Produced) | K82: Yes | L82: Diamond, Producer | M82: AG Select-a-Term 20-30, 35 Years | O82: Type: Term State: NY Product Name: AG Select-a-Term 20-30, 35 Years Sub Name: Personally Produced | P82: 65 | Q82: 40
A83: 82 | B83: L_CORENY | C83: TBD | D83: Term | E83: NY | F83: Year 2 | H83: TBD | J83: AG Select-a-Term 20-30 - 35 Years (NY) (Personally Produced) (Year 2) | K83: No | L83: Diamond, Producer | M83: Year 2 | O83: Product Name: Year 2 | Q83: 4
A84: 83 | B84: L_CORENY | C84: TBD | D84: Term | E84: NY | F84: Year 3 | H84: TBD | J84: AG Select-a-Term 20-30 - 35 Years (NY) (Personally Produced) (Year 3) | K84: No | L84: Diamond, Producer | M84: Year 3 | O84: Product Name: Year 3 | Q84: 2
A85: 84 | B85: L_CORENY | C85: TBD | D85: Term | E85: NY | F85: Year 4 | H85: TBD | J85: AG Select-a-Term 20-30 - 35 Years (NY) (Personally Produced) (Year 4) | K85: No | L85: Diamond, Producer | M85: Year 4 | O85: Product Name: Year 4 | Q85: 1
A86: 85 | B86: L_CORENY | C86: TBD | D86: Term | E86: NY | F86: Year 5 | H86: TBD | J86: AG Select-a-Term 20-30 - 35 Years (NY) (Personally Produced) (Year 5) | K86: No | L86: Diamond, Producer | M86: Year 5 | O86: Product Name: Year 5 | Q86: 1
A87: 86 | B87: L_CORENY | C87: TBD | D87: Term | E87: NY | F87: Years 6-10 | H87: TBD | J87: AG Select-a-Term 20-30 - 35 Years (NY) (Personally Produced) (Year 6-10) | K87: No | L87: Diamond, Producer | M87: Years 6-10 | O87: Product Name: Years 6-10 | Q87: 1
A88: 87 | B88: L_CORENY | C88: TBD | D88: Term | E88: NY | F88: AG Select-a-Term 20-30 - 35 Years | G88: Non-Personally Produced | H88: TBD | J88: AG Select-a-Term 20-30 - 35 Years (NY) (Non-Personally Produced) | K88: Yes | L88: Diamond, Producer | M88: AG Select-a-Term 20-30, 35 Years | O88: Type: Term State: NY Product Name: AG Select-a-Term 20-30, 35 Years Sub Name: Non-Personally Produced | P88: 73 | Q88: 40
A89: 88 | B89: L_CORENY | C89: TBD | D89: Term | E89: NY | F89: Year 2 | H89: TBD | J89: AG Select-a-Term 20-30 - 35 Years (NY) (Non-Personally Produced) (Year 2) | K89: No | L89: Diamond, Producer | M89: Year 2 | O89: Product Name: Year 2 | Q89: 4
A90: 89 | B90: L_CORENY | C90: TBD | D90: Term | E90: NY | F90: Year 3 | H90: TBD | J90: AG Select-a-Term 20-30 - 35 Years (NY) (Non-Personally Produced) (Year 3) | K90: No | L90: Diamond, Producer | M90: Year 3 | O90: Product Name: Year 3 | Q90: 2
A91: 90 | B91: L_CORENY | C91: TBD | D91: Term | E91: NY | F91: Year 4 | H91: TBD | J91: AG Select-a-Term 20-30 - 35 Years (NY) (Non-Personally Produced) (Year 4) | K91: No | L91: Diamond, Producer | M91: Year 4 | O91: Product Name: Year 4 | Q91: 1
A92: 91 | B92: L_CORENY | C92: TBD | D92: Term | E92: NY | F92: Year 5 | H92: TBD | J92: AG Select-a-Term 20-30 - 35 Years (NY) (Non-Personally Produced) (Year 5) | K92: No | L92: Diamond, Producer | M92: Year 5 | O92: Product Name: Year 5 | Q92: 1
A93: 92 | B93: L_CORENY | C93: TBD | D93: Term | E93: NY | F93: Years 6-10 | H93: TBD | J93: AG Select-a-Term 20-30 - 35 Years (NY) (Non-Personally Produced) (Year 6-10) | K93: No | L93: Diamond, Producer | M93: Years 6-10 | O93: Product Name: Years 6-10 | Q93: 1
A94: 93 | B94: L_CORENY | C94: TBD | D94: Term | E94: NY | F94: American Elite 2 | G94: Personally Produced | H94: TBD | J94: American Elite 2 (NY)( Personally Produced) | K94: Yes | L94: Diamond, Producer | M94: American Elite 2 | O94: State: NY Product Name: American Elite 2 Sub Name: Personally Produced | P94: 35 | Q94: 35
A95: 94 | B95: L_CORENY | C95: TBD | D95: Term | E95: NY | F95: Year 2 | H95: TBD | J95: American Elite 2 (NY)( Personally Produced) (Year 2) | K95: No | L95: Diamond, Producer | M95: Year 2 | O95: Product Name: Year 2 | Q95: 7
A96: 95 | B96: L_CORENY | C96: TBD | D96: Term | E96: NY | F96: Year 3 | H96: TBD | J96: American Elite 2 (NY)( Personally Produced) (Year 3) | K96: No | L96: Diamond, Producer | M96: Year 3 | O96: Product Name: Year 3 | Q96: 2.5
A97: 96 | B97: L_CORENY | C97: TBD | D97: Term | E97: NY | F97: Year 4 | H97: TBD | J97: American Elite 2 (NY)( Personally Produced) (Year 4) | K97: No | L97: Diamond, Producer | M97: Year 4 | O97: Product Name: Year 4 | Q97: 2.5
A98: 97 | B98: L_CORENY | C98: TBD | D98: Term | E98: NY | F98: Year 5 | H98: TBD | J98: American Elite 2 (NY)( Personally Produced) (Year 5) | K98: No | L98: Diamond, Producer | M98: Year 5 | O98: Product Name: Year 5 | Q98: 2.5
A99: 98 | B99: L_CORENY | C99: TBD | D99: Term | E99: NY | F99: Years 6-10 | H99: TBD | J99: American Elite 2 (NY)( Personally Produced) (Year 6-10) | K99: No | L99: Diamond, Producer | M99: Years 6-10 | O99: Product Name: Years 6-10 | Q99: 2.5
A100: 99 | B100: L_CORENY | C100: TBD | D100: Term | E100: NY | F100: American Elite 2 | G100: Non-Personally Produced | H100: TBD | J100: American Elite 2 (NY) (Non-Personally Produced) | K100: Yes | L100: Diamond, Producer | M100: American Elite 2 | N100: Sub type: American Elite 2 Sub Name: Non-Personally Produced | State: New York | P100: 35 | Q100: 35
...

Sheet L-CORERN
A1: Row | B1: Service-Carrier ID | C1: Product Tier | D1: Types | E1: State Available | F1: Old Product name | G1: Sub-Name | H1: Sub-type | I1: Length | J1: Product Name Full | K1: Product Real | L1: All Vendor paycodes | M1: Product | N1: Criteria | O1: Notes | P1: Diamond | Q1: E | R1: F | S1: G
A2: 1 | B2: L_CORERN | C2: TBD | D2: Term | E2: Non-NY | G2: 20-30 & 35 yr | H2: Term | I2: 35 | J2: AG Select-A-Term Renewals 35 Year (Years 2-5) | K2: Yes | L2: Diamond, E, F, G | M2: AG Select-A-Term Renewals (Years 2-5) | N2: Sub type: 35 Year Term | Renewal year: 2 to 5 | State: Alabama, Alaska, Arizona, Arkansas, California, Colorado, Connecticut, Delaware, Florida, Georgia, Hawaii, Idaho, Illinois, Indiana, Iowa, Kansas, Kentucky, Louisiana, Maine, Maryland, Massachusetts, Michigan, Minnesota, Mississippi, Missouri, Montana, Nebraska, Nevada, New Hampshire, New Jersey, New Mexico, North Carolina, North Dakota, Ohio, Oklahoma, Oregon, Pennsylvania, Rhode Island, South Carolina, South Dakota, Tennessee, Texas, Utah, Vermont, Virginia, Washington, West Virginia, Wisconsin, Wyoming | P2: 0 | Q2: 0 | R2: 0 | S2: 0
A3: 2 | B3: L_CORERN | C3: TBD | D3: Term | E3: Non-NY | G3: 19 yr | H3: Term | I3: 30 | J3: AG Select-A-Term Renewals 30 Year (Years 2-5) | K3: Yes | L3: Diamond, E, F, G | M3: AG Select-A-Term Renewals (Years 2-5) | N3: Sub type: 30 Year Term | Renewal year: 2 to 5 | State: Alabama, Alaska, Arizona, Arkansas, California, Colorado, Connecticut, Delaware, Florida, Georgia, Hawaii, Idaho, Illinois, Indiana, Iowa, Kansas, Kentucky, Louisiana, Maine, Maryland, Massachusetts, Michigan, Minnesota, Mississippi, Missouri, Montana, Nebraska, Nevada, New Hampshire, New Jersey, New Mexico, North Carolina, North Dakota, Ohio, Oklahoma, Oregon, Pennsylvania, Rhode Island, South Carolina, South Dakota, Tennessee, Texas, Utah, Vermont, Virginia, Washington, West Virginia, Wisconsin, Wyoming | P3: 0 | Q3: 0 | R3: 0 | S3: 0
A4: 3 | B4: L_CORERN | C4: TBD | D4: Term | E4: Non-NY | G4: 18 yr | H4: Term | I4: 29 | J4: AG Select-A-Term Renewals 29 Year (Years 2-5) | K4: Yes | L4: Diamond, E, F, G | M4: AG Select-A-Term Renewals (Years 2-5) | N4: Sub type: 29 year Term | Renewal year: 2 to 5 | State: Alabama, Alaska, Arizona, Arkansas, California, Colorado, Connecticut, Delaware, Florida, Georgia, Hawaii, Idaho, Illinois, Indiana, Iowa, Kansas, Kentucky, Louisiana, Maine, Maryland, Massachusetts, Michigan, Minnesota, Mississippi, Missouri, Montana, Nebraska, Nevada, New Hampshire, New Jersey, New Mexico, North Carolina, North Dakota, Ohio, Oklahoma, Oregon, Pennsylvania, Rhode Island, South Carolina, South Dakota, Tennessee, Texas, Utah, Vermont, Virginia, Washington, West Virginia, Wisconsin, Wyoming | P4: 0 | Q4: 0 | R4: 0 | S4: 0
A5: 4 | B5: L_CORERN | C5: TBD | D5: Term | E5: Non-NY | G5: 17 yr | H5: Term | I5: 28 | J5: AG Select-A-Term Renewals 28 Year (Years 2-5) | K5: Yes | L5: Diamond, E, F, G | M5: AG Select-A-Term Renewals (Years 2-5) | N5: Sub type: 28 Year Term | Renewal year: 2 to 5 | State: Alabama, Alaska, Arizona, Arkansas, California, Colorado, Connecticut, Delaware, Florida, Georgia, Hawaii, Idaho, Illinois, Indiana, Iowa, Kansas, Kentucky, Louisiana, Maine, Maryland, Massachusetts, Michigan, Minnesota, Mississippi, Missouri, Montana, Nebraska, Nevada, New Hampshire, New Jersey, New Mexico, North Carolina, North Dakota, Ohio, Oklahoma, Oregon, Pennsylvania, Rhode Island, South Carolina, South Dakota, Tennessee, Texas, Utah, Vermont, Virginia, Washington, West Virginia, Wisconsin, Wyoming | P5: 0 | Q5: 0 | R5: 0 | S5: 0
A6: 5 | B6: L_CORERN | C6: TBD | D6: Term | E6: Non-NY | G6: 16 yr | H6: Term | I6: 27 | J6: AG Select-A-Term Renewals 27 Year (Years 2-5) | K6: Yes | L6: Diamond, E, F, G | M6: AG Select-A-Term Renewals (Years 2-5) | N6: Sub type: 27 Year Term | Renewal year: 2 to 5 | State: Alabama, Alaska, Arizona, Arkansas, California, Colorado, Connecticut, Delaware, Florida, Georgia, Hawaii, Idaho, Illinois, Indiana, Iowa, Kansas, Kentucky, Louisiana, Maine, Maryland, Massachusetts, Michigan, Minnesota, Mississippi, Missouri, Montana, Nebraska, Nevada, New Hampshire, New Jersey, New Mexico, North Carolina, North Dakota, Ohio, Oklahoma, Oregon, Pennsylvania, Rhode Island, South Carolina, South Dakota, Tennessee, Texas, Utah, Vermont, Virginia, Washington, West Virginia, Wisconsin, Wyoming | P6: 0 | Q6: 0 | R6: 0 | S6: 0
A7: 6 | B7: L_CORERN | C7: TBD | D7: Term | E7: Non-NY | G7: 15 yr | H7: Term | I7: 26 | J7: AG Select-A-Term Renewals 26 Year (Years 2-5) | K7: Yes | L7: Diamond, E, F, G | M7: AG Select-A-Term Renewals (Years 2-5) | N7: Sub type: 26 Year Term | Renewal year: 2 to 5 | State: Alabama, Alaska, Arizona, Arkansas, California, Colorado, Connecticut, Delaware, Florida, Georgia, Hawaii, Idaho, Illinois, Indiana, Iowa, Kansas, Kentucky, Louisiana, Maine, Maryland, Massachusetts, Michigan, Minnesota, Mississippi, Missouri, Montana, Nebraska, Nevada, New Hampshire, New Jersey, New Mexico, North Carolina, North Dakota, Ohio, Oklahoma, Oregon, Pennsylvania, Rhode Island, South Carolina, South Dakota, Tennessee, Texas, Utah, Vermont, Virginia, Washington, West Virginia, Wisconsin, Wyoming | P7: 0 | Q7: 0 | R7: 0 | S7: 0
A8: 7 | B8: L_CORERN | C8: TBD | D8: Term | E8: Non-NY | G8: 10 yr | H8: Term | I8: 25 | J8: AG Select-A-Term Renewals 25 Year (Years 2-5) | K8: Yes | L8: Diamond, E, F, G | M8: AG Select-A-Term Renewals (Years 2-5) | N8: Sub type: 25 Year Term | Renewal year: 2 to 5 | State: Alabama, Alaska, Arizona, Arkansas, California, Colorado, Connecticut, Delaware, Florida, Georgia, Hawaii, Idaho, Illinois, Indiana, Iowa, Kansas, Kentucky, Louisiana, Maine, Maryland, Massachusetts, Michigan, Minnesota, Mississippi, Missouri, Montana, Nebraska, Nevada, New Hampshire, New Jersey, New Mexico, North Carolina, North Dakota, Ohio, Oklahoma, Oregon, Pennsylvania, Rhode Island, South Carolina, South Dakota, Tennessee, Texas, Utah, Vermont, Virginia, Washington, West Virginia, Wisconsin, Wyoming | P8: 0 | Q8: 0 | R8: 0 | S8: 0
A9: 8 | B9: L_CORERN | C9: TBD | D9: Perm | E9: Non-NY | H9: UL | I9: 24 | J9: AG Select-A-Term Renewals 24 Year (Years 2-5) | K9: Yes | L9: Diamond, E, F, G | M9: AG Select-A-Term Renewals (Years 2-5) | N9: Sub type: 24 Year Term | Renewal year: 2 to 5 | State: Alabama, Alaska, Arizona, Arkansas, California, Colorado, Connecticut, Delaware, Florida, Georgia, Hawaii, Idaho, Illinois, Indiana, Iowa, Kansas, Kentucky, Louisiana, Maine, Maryland, Massachusetts, Michigan, Minnesota, Mississippi, Missouri, Montana, Nebraska, Nevada, New Hampshire, New Jersey, New Mexico, North Carolina, North Dakota, Ohio, Oklahoma, Oregon, Pennsylvania, Rhode Island, South Carolina, South Dakota, Tennessee, Texas, Utah, Vermont, Virginia, Washington, West Virginia, Wisconsin, Wyoming | P9: 0 | Q9: 0 | R9: 0 | S9: 0
A10: 9 | B10: L_CORERN | C10: TBD | D10: Perm | E10: Non-NY | H10: IUL | I10: 23 | J10: AG Select-A-Term Renewals 23 Year (Years 2-5) | K10: Yes | L10: Diamond, E, F, G | M10: AG Select-A-Term Renewals (Years 2-5) | N10: Sub type: 23 Year Term | Renewal year: 2 to 5 | State: Alabama, Alaska, Arizona, Arkansas, California, Colorado, Connecticut, Delaware, Florida, Georgia, Hawaii, Idaho, Illinois, Indiana, Iowa, Kansas, Kentucky, Louisiana, Maine, Maryland, Massachusetts, Michigan, Minnesota, Mississippi, Missouri, Montana, Nebraska, Nevada, New Hampshire, New Jersey, New Mexico, North Carolina, North Dakota, Ohio, Oklahoma, Oregon, Pennsylvania, Rhode Island, South Carolina, South Dakota, Tennessee, Texas, Utah, Vermont, Virginia, Washington, West Virginia, Wisconsin, Wyoming | P10: 0 | Q10: 0 | R10: 0 | S10: 0
A11: 10 | B11: L_CORERN | C11: TBD | D11: Perm | E11: Non-NY | H11: IUL | I11: 22 | J11: AG Select-A-Term Renewals 22 Year (Years 2-5) | K11: Yes | L11: Diamond, E, F, G | M11: AG Select-A-Term Renewals (Years 2-5) | N11: Sub type: 22 Year Term | Renewal year: 2 to 5 | State: Alabama, Alaska, Arizona, Arkansas, California, Colorado, Connecticut, Delaware, Florida, Georgia, Hawaii, Idaho, Illinois, Indiana, Iowa, Kansas, Kentucky, Louisiana, Maine, Maryland, Massachusetts, Michigan, Minnesota, Mississippi, Missouri, Montana, Nebraska, Nevada, New Hampshire, New Jersey, New Mexico, North Carolina, North Dakota, Ohio, Oklahoma, Oregon, Pennsylvania, Rhode Island, South Carolina, South Dakota, Tennessee, Texas, Utah, Vermont, Virginia, Washington, West Virginia, Wisconsin, Wyoming | P11: 0 | Q11: 0 | R11: 0 | S11: 0
A12: 11 | B12: L_CORERN | C12: TBD | D12: Perm | E12: Non-NY | G12: (Conversions Only) | H12: IUL | I12: 21 | J12: AG Select-A-Term Renewals 21 Year (Years 2-5) | K12: Yes | L12: Diamond, E, F, G | M12: AG Select-A-Term Renewals (Years 2-5) | N12: Sub type: 21 Year Term | Renewal year: 2 to 5 | State: Alabama, Alaska, Arizona, Arkansas, California, Colorado, Connecticut, Delaware, Florida, Georgia, Hawaii, Idaho, Illinois, Indiana, Iowa, Kansas, Kentucky, Louisiana, Maine, Maryland, Massachusetts, Michigan, Minnesota, Mississippi, Missouri, Montana, Nebraska, Nevada, New Hampshire, New Jersey, New Mexico, North Carolina, North Dakota, Ohio, Oklahoma, Oregon, Pennsylvania, Rhode Island, South Carolina, South Dakota, Tennessee, Texas, Utah, Vermont, Virginia, Washington, West Virginia, Wisconsin, Wyoming | P12: 0 | Q12: 0 | R12: 0 | S12: 0
A13: 12 | G13: (Conversions Only) | H13: IUL | I13: 20 | J13: AG Select-A-Term Renewals 20 Year (Years 2-5) | K13: Yes | L13: Diamond, E, F, G | M13: AG Select-A-Term Renewals (Years 2-5) | N13: Sub type: 20 Year Term | Renewal year: 2 to 5 | State: Alabama, Alaska, Arizona, Arkansas, California, Colorado, Connecticut, Delaware, Florida, Georgia, Hawaii, Idaho, Illinois, Indiana, Iowa, Kansas, Kentucky, Louisiana, Maine, Maryland, Massachusetts, Michigan, Minnesota, Mississippi, Missouri, Montana, Nebraska, Nevada, New Hampshire, New Jersey, New Mexico, North Carolina, North Dakota, Ohio, Oklahoma, Oregon, Pennsylvania, Rhode Island, South Carolina, South Dakota, Tennessee, Texas, Utah, Vermont, Virginia, Washington, West Virginia, Wisconsin, Wyoming | P13: 0 | Q13: 0 | R13: 0 | S13: 0
A14: 13 | G14: (Conversions Only) | H14: IUL | I14: 19 | J14: AG Select-A-Term Renewals 19 Year (Years 2-5) | K14: No | L14: Diamond, E, F, G | M14: AG Select-A-Term Renewals (Years 2-5) | N14: Sub type: 19 Year Term | Renewal year: 2 to 5 | State: Alabama, Alaska, Arizona, Arkansas, California, Colorado, Connecticut, Delaware, Florida, Georgia, Hawaii, Idaho, Illinois, Indiana, Iowa, Kansas, Kentucky, Louisiana, Maine, Maryland, Massachusetts, Michigan, Minnesota, Mississippi, Missouri, Montana, Nebraska, Nevada, New Hampshire, New Jersey, New Mexico, North Carolina, North Dakota, Ohio, Oklahoma, Oregon, Pennsylvania, Rhode Island, South Carolina, South Dakota, Tennessee, Texas, Utah, Vermont, Virginia, Washington, West Virginia, Wisconsin, Wyoming | Q14: 0 | R14: 0 | S14: 0
A15: 14 | G15: (Conversions Only) | H15: IUL | I15: 18 | J15: AG Select-A-Term Renewals 18 Year (Years 2-5) | K15: No | L15: Diamond, E, F, G | M15: AG Select-A-Term Renewals (Years 2-5) | N15: Sub type: 18 Year Term | Renewal year: 2 to 5 | State: Alabama, Alaska, Arizona, Arkansas, California, Colorado, Connecticut, Delaware, Florida, Georgia, Hawaii, Idaho, Illinois, Indiana, Iowa, Kansas, Kentucky, Louisiana, Maine, Maryland, Massachusetts, Michigan, Minnesota, Mississippi, Missouri, Montana, Nebraska, Nevada, New Hampshire, New Jersey, New Mexico, North Carolina, North Dakota, Ohio, Oklahoma, Oregon, Pennsylvania, Rhode Island, South Carolina, South Dakota, Tennessee, Texas, Utah, Vermont, Virginia, Washington, West Virginia, Wisconsin, Wyoming | Q15: 0 | R15: 0 | S15: 0
I16: 17 | J16: AG Select-A-Term Renewals 17 Year (Years 2-5) | K16: No | L16: Diamond, E, F, G | M16: AG Select-A-Term Renewals (Years 2-5) | N16: Sub type: 17 Year Term | Renewal year: 2 to 5 | State: Alabama, Alaska, Arizona, Arkansas, California, Colorado, Connecticut, Delaware, Florida, Georgia, Hawaii, Idaho, Illinois, Indiana, Iowa, Kansas, Kentucky, Louisiana, Maine, Maryland, Massachusetts, Michigan, Minnesota, Mississippi, Missouri, Montana, Nebraska, Nevada, New Hampshire, New Jersey, New Mexico, North Carolina, North Dakota, Ohio, Oklahoma, Oregon, Pennsylvania, Rhode Island, South Carolina, South Dakota, Tennessee, Texas, Utah, Vermont, Virginia, Washington, West Virginia, Wisconsin, Wyoming | Q16: 0 | R16: 0 | S16: 0
I17: 16 | J17: AG Select-A-Term Renewals 16 Year (Years 2-5) | K17: No | L17: Diamond, E, F, G | M17: AG Select-A-Term Renewals (Years 2-5) | N17: Sub type: 16 year Term | Renewal year: 2 to 5 | State: Alabama, Alaska, Arizona, Arkansas, California, Colorado, Connecticut, Delaware, Florida, Georgia, Hawaii, Idaho, Illinois, Indiana, Iowa, Kansas, Kentucky, Louisiana, Maine, Maryland, Massachusetts, Michigan, Minnesota, Mississippi, Missouri, Montana, Nebraska, Nevada, New Hampshire, New Jersey, New Mexico, North Carolina, North Dakota, Ohio, Oklahoma, Oregon, Pennsylvania, Rhode Island, South Carolina, South Dakota, Tennessee, Texas, Utah, Vermont, Virginia, Washington, West Virginia, Wisconsin, Wyoming | Q17: 0 | R17: 0 | S17: 0
I18: 15 | J18: AG Select-A-Term Renewals 15 Year (Years 2-5) | K18: No | L18: Diamond, E, F, G | M18: AG Select-A-Term Renewals (Years 2-5) | N18: Sub type: 15 Year Term | Renewal year: 2 to 5 | State: Alabama, Alaska, Arizona, Arkansas, California, Colorado, Connecticut, Delaware, Florida, Georgia, Hawaii, Idaho, Illinois, Indiana, Iowa, Kansas, Kentucky, Louisiana, Maine, Maryland, Massachusetts, Michigan, Minnesota, Mississippi, Missouri, Montana, Nebraska, Nevada, New Hampshire, New Jersey, New Mexico, North Carolina, North Dakota, Ohio, Oklahoma, Oregon, Pennsylvania, Rhode Island, South Carolina, South Dakota, Tennessee, Texas, Utah, Vermont, Virginia, Washington, West Virginia, Wisconsin, Wyoming | Q18: 0 | R18: 0 | S18: 0
I19: 10 | J19: AG Select-A-Term Renewals 10 Year (Years 2-5) | K19: No | L19: Diamond, E, F, G | M19: AG Select-A-Term Renewals (Years 2-5) | N19: Sub type: 10 Year Term | Renewal year: 2 to 5 | State: Alabama, Alaska, Arizona, Arkansas, California, Colorado, Connecticut, Delaware, Florida, Georgia, Hawaii, Idaho, Illinois, Indiana, Iowa, Kansas, Kentucky, Louisiana, Maine, Maryland, Massachusetts, Michigan, Minnesota, Mississippi, Missouri, Montana, Nebraska, Nevada, New Hampshire, New Jersey, New Mexico, North Carolina, North Dakota, Ohio, Oklahoma, Oregon, Pennsylvania, Rhode Island, South Carolina, South Dakota, Tennessee, Texas, Utah, Vermont, Virginia, Washington, West Virginia, Wisconsin, Wyoming | Q19: 0 | R19: 0 | S19: 0
I20: Lifetime | J20: AG Secure Lifetime GUL 3 Renewals (Years 2-10) | K20: No | L20: Diamond, E, F, G | M20: AG Secure Lifetime GUL 3 Renewals (Years 2-10) | N20: Renewal year: 2 to 10 | State: Alabama, Alaska, Arizona, Arkansas, California, Colorado, Connecticut, Delaware, Florida, Georgia, Hawaii, Idaho, Illinois, Indiana, Iowa, Kansas, Kentucky, Louisiana, Maine, Maryland, Massachusetts, Michigan, Minnesota, Mississippi, Missouri, Montana, Nebraska, Nevada, New Hampshire, New Jersey, New Mexico, North Carolina, North Dakota, Ohio, Oklahoma, Oregon, Pennsylvania, Rhode Island, South Carolina, South Dakota, Tennessee, Texas, Utah, Vermont, Virginia, Washington, West Virginia, Wisconsin, Wyoming | Q20: 0.25 | R20: 0 | S20: 0
I21: Lifetime | J21: Max Accumulator+ II Renewals (Years 2-10) | K21: No | L21: Diamond, E, F, G | M21: Max Accumulator+ II Renewals (Years 2-10) | N21: Renewal year: 2 to 10 | State: Alabama, Alaska, Arizona, Arkansas, California, Colorado, Connecticut, Delaware, Florida, Georgia, Hawaii, Idaho, Illinois, Indiana, Iowa, Kansas, Kentucky, Louisiana, Maine, Maryland, Massachusetts, Michigan, Minnesota, Mississippi, Missouri, Montana, Nebraska, Nevada, New Hampshire, New Jersey, New Mexico, North Carolina, North Dakota, Ohio, Oklahoma, Oregon, Pennsylvania, Rhode Island, South Carolina, South Dakota, Tennessee, Texas, Utah, Vermont, Virginia, Washington, West Virginia, Wisconsin, Wyoming | Q21: 0.25 | R21: 0 | S21: 0
I22: Lifetime | J22: Value+ Protector II Renewals (Years 2-10) | K22: No | L22: Diamond, E, F, G | M22: Value+ Protector II Renewals (Years 2-10) | N22: Renewal year: 2 to 10 | State: Alabama, Alaska, Arizona, Arkansas, California, Colorado, Connecticut, Delaware, Florida, Georgia, Hawaii, Idaho, Illinois, Indiana, Iowa, Kansas, Kentucky, Louisiana, Maine, Maryland, Massachusetts, Michigan, Minnesota, Mississippi, Missouri, Montana, Nebraska, Nevada, New Hampshire, New Jersey, New Mexico, North Carolina, North Dakota, Ohio, Oklahoma, Oregon, Pennsylvania, Rhode Island, South Carolina, South Dakota, Tennessee, Texas, Utah, Vermont, Virginia, Washington, West Virginia, Wisconsin, Wyoming | Q22: 0.25 | R22: 0 | S22: 0
I23: Lifetime | J23: Protection Extend IUL Renewals (Year 2-3) | K23: No | L23: Diamond, E, F, G | M23: Protection Extend IUL Renewals (Year 2-3) | N23: Sub type: (Conversions Only) | Renewal year: 2 to 3 | State: Alabama, Alaska, Arizona, Arkansas, California, Colorado, Connecticut, Delaware, Florida, Georgia, Hawaii, Idaho, Illinois, Indiana, Iowa, Kansas, Kentucky, Louisiana, Maine, Maryland, Massachusetts, Michigan, Minnesota, Mississippi, Missouri, Montana, Nebraska, Nevada, New Hampshire, New Jersey, New Mexico, North Carolina, North Dakota, Ohio, Oklahoma, Oregon, Pennsylvania, Rhode Island, South Carolina, South Dakota, Tennessee, Texas, Utah, Vermont, Virginia, Washington, West Virginia, Wisconsin, Wyoming | Q23: 25 | R23: 23 | S23: 19
I24: Lifetime | J24: Protection Extend IUL Renewals (Year 4-10) | K24: No | L24: Diamond, E, F, G | M24: Protection Extend IUL Renewals (Year 4-10) | N24: Sub type: (Conversions Only) | Renewal year: 4 to 10 | State: Alabama, Alaska, Arizona, Arkansas, California, Colorado, Connecticut, Delaware, Florida, Georgia, Hawaii, Idaho, Illinois, Indiana, Iowa, Kansas, Kentucky, Louisiana, Maine, Maryland, Massachusetts, Michigan, Minnesota, Mississippi, Missouri, Montana, Nebraska, Nevada, New Hampshire, New Jersey, New Mexico, North Carolina, North Dakota, Ohio, Oklahoma, Oregon, Pennsylvania, Rhode Island, South Carolina, South Dakota, Tennessee, Texas, Utah, Vermont, Virginia, Washington, West Virginia, Wisconsin, Wyoming | Q24: 0 | R24: 0 | S24: 0
I25: Lifetime | J25: Protection Extend IUL Excess (Year 1-2) | K25: No | L25: Diamond, E, F, G | M25: Protection Extend IUL Excess (Year 1-2) | N25: Sub type: (Conversions Only) | State: Alabama, Alaska, Arizona, Arkansas, California, Colorado, Connecticut, Delaware, Florida, Georgia, Hawaii, Idaho, Illinois, Indiana, Iowa, Kansas, Kentucky, Louisiana, Maine, Maryland, Massachusetts, Michigan, Minnesota, Mississippi, Missouri, Montana, Nebraska, Nevada, New Hampshire, New Jersey, New Mexico, North Carolina, North Dakota, Ohio, Oklahoma, Oregon, Pennsylvania, Rhode Island, South Carolina, South Dakota, Tennessee, Texas, Utah, Vermont, Virginia, Washington, West Virginia, Wisconsin, Wyoming | Excess year: 1 to 2 | Q25: 0.75 | R25: 0.5 | S25: 0.25
I26: Lifetime | J26: Protection Extend IUL Excess (Year 3-10) | K26: No | L26: Diamond, E, F, G | M26: Protection Extend IUL Excess (Year 3-10) | N26: Sub type: (Conversions Only) | State: Alabama, Alaska, Arizona, Arkansas, California, Colorado, Connecticut, Delaware, Florida, Georgia, Hawaii, Idaho, Illinois, Indiana, Iowa, Kansas, Kentucky, Louisiana, Maine, Maryland, Massachusetts, Michigan, Minnesota, Mississippi, Missouri, Montana, Nebraska, Nevada, New Hampshire, New Jersey, New Mexico, North Carolina, North Dakota, Ohio, Oklahoma, Oregon, Pennsylvania, Rhode Island, South Carolina, South Dakota, Tennessee, Texas, Utah, Vermont, Virginia, Washington, West Virginia, Wisconsin, Wyoming | Excess year: 3 to 10 | Q26: 0.25 | R26: 0.25 | S26: 0.25

Sheet L-CORESIM
A1: Row | B1: Service-Carrier ID | C1: Product Tier | D1: Types | E1: State Available | F1: Old Product name | G1: Sub-Name | H1: Sub-type | I1: Length | J1: Product Name Full | K1: Product Real | L1: All Vendor paycodes | M1: Product | N1: Criteria | O1: Notes | P1: Diamond | Q1: J | R1: K | S1: L | T1: M | U1: N | V1: P | W1: Q | X1: T | Y1: U | Z1: R | AA1: S | AB1: Y | AC1: V | AD1: W | AE1: Z | AF1: A | AG1: B | AH1: C | AI1: D
I2: Lifetime | J2: SimpliNow Legacy Max | K2: Yes | L2: Diamond, J, K, L, M, N, P, Q, T, U, R, S, Y, V, W, Z, A, B, C, D | M2: SimpliNow Legacy Max | N2: State: Alabama, Alaska, Arizona, Arkansas, California, Colorado, Connecticut, Delaware, Florida, Georgia, Hawaii, Idaho, Illinois, Indiana, Iowa, Kansas, Kentucky, Louisiana, Maine, Maryland, Massachusetts, Michigan, Minnesota, Mississippi, Missouri, Montana, Nebraska, Nevada, New Hampshire, New Jersey, New Mexico, North Carolina, North Dakota, Ohio, Oklahoma, Oregon, Pennsylvania, Rhode Island, South Carolina, South Dakota, Tennessee, Texas, Utah, Vermont, Virginia, Washington, West Virginia, Wisconsin, Wyoming | Type: Perm | P2: 136 | Q2: 127 | R2: 122 | S2: 117 | T2: 112 | U2: 107 | V2: 102 | W2: 97 | X2: 92 | Y2: 87 | Z2: 82 | AA2: 77 | AB2: 72 | AC2: 67 | AD2: 62 | AE2: 57 | AF2: 52 | AG2: 47 | AH2: 42 | AI2: 37
I3: Lifetime | J3: SimpliNow Legacy Max (Renewal years 2-5) | K3: No | L3: Diamond, J, K, L, M, N, P, Q, T, U, R, S, Y, V, W, Z, A, B, C, D | M3: SimpliNow Legacy Max | N3: Renewal year: 2 to 5 | State: Alabama, Alaska, Arizona, Arkansas, California, Colorado, Connecticut, Delaware, Florida, Georgia, Hawaii, Idaho, Illinois, Indiana, Iowa, Kansas, Kentucky, Louisiana, Maine, Maryland, Massachusetts, Michigan, Minnesota, Mississippi, Missouri, Montana, Nebraska, Nevada, New Hampshire, New Jersey, New Mexico, North Carolina, North Dakota, Ohio, Oklahoma, Oregon, Pennsylvania, Rhode Island, South Carolina, South Dakota, Tennessee, Texas, Utah, Vermont, Virginia, Washington, West Virginia, Wisconsin, Wyoming | Q3: 5.5 | R3: 5.25 | S3: 5 | T3: 4.75 | U3: 4.5 | V3: 4.25 | W3: 4 | X3: 3.75 | Y3: 3.5 | Z3: 3.25 | AA3: 3 | AB3: 2.75 | AC3: 2.5 | AD3: 2.25 | AE3: 2 | AF3: 1.75 | AG3: 1.5 | AH3: 1.25 | AI3: 1
I4: Lifetime | J4: SimpliNow Legacy Max (Renewal Years 6-10) | K4: No | L4: Diamond, J, K, L, M, N, P, Q, T, U, R, S, Y, V, W, Z, A, B, C, D | M4: SimpliNow Legacy Max | N4: Renewal year: 6 to 10 | State: Alabama, Alaska, Arizona, Arkansas, California, Colorado, Connecticut, Delaware, Florida, Georgia, Hawaii, Idaho, Illinois, Indiana, Iowa, Kansas, Kentucky, Louisiana, Maine, Maryland, Massachusetts, Michigan, Minnesota, Mississippi, Missouri, Montana, Nebraska, Nevada, New Hampshire, New Jersey, New Mexico, North Carolina, North Dakota, Ohio, Oklahoma, Oregon, Pennsylvania, Rhode Island, South Carolina, South Dakota, Tennessee, Texas, Utah, Vermont, Virginia, Washington, West Virginia, Wisconsin, Wyoming | Q4: 3.25 | R4: 3 | S4: 2.75 | T4: 2.5 | U4: 2.25 | V4: 2 | W4: 1.75 | X4: 1.5 | Y4: 1.25 | Z4: 1 | AA4: 0.75 | AB4: 0.5 | AC4: 0.25 | AD4: 0 | AE4: 0 | AF4: 0 | AG4: 0 | AH4: 0 | AI4: 0
I5: Lifetime | J5: SimpliNow Legacy Max (Renewal Years 11+) | K5: No | L5: Diamond, J, K, L, M, N, P, Q, T, U, R, S, Y, V, W, Z, A, B, C, D | M5: SimpliNow Legacy Max | N5: Renewal year: 11+ | State: Alabama, Alaska, Arizona, Arkansas, California, Colorado, Connecticut, Delaware, Florida, Georgia, Hawaii, Idaho, Illinois, Indiana, Iowa, Kansas, Kentucky, Louisiana, Maine, Maryland, Massachusetts, Michigan, Minnesota, Mississippi, Missouri, Montana, Nebraska, Nevada, New Hampshire, New Jersey, New Mexico, North Carolina, North Dakota, Ohio, Oklahoma, Oregon, Pennsylvania, Rhode Island, South Carolina, South Dakota, Tennessee, Texas, Utah, Vermont, Virginia, Washington, West Virginia, Wisconsin, Wyoming | Q5: 0 | R5: 0 | S5: 0 | T5: 0 | U5: 0 | V5: 0 | W5: 0 | X5: 0 | Y5: 0 | Z5: 0 | AA5: 0 | AB5: 0 | AC5: 0 | AD5: 0 | AE5: 0 | AF5: 0 | AG5: 0 | AH5: 0 | AI5: 0
